Workbook

Sheet JUST RAN
A1: date | B1: id | C1: recession | D1: federal_purchases_deflator_growth | E1: consumption_grants_deflator_growth | F1: investment_grants_deflator_growth | G1: state_purchases_deflator_growth | H1: consumption_deflator_growth | I1: real_potential_gdp_growth | J1: gdp | K1: consumption | L1: uncertainty | M1: federal_purchases | N1: consumption_grants | O1: investment_grants | P1: state_purchases | Q1: federal_non_corporate_taxes | R1: state_non_corporate_taxes | S1: federal_corporate_taxes | T1: supply_side_ira | U1: state_corporate_taxes | V1: federal_social_benefits | W1: state_social_benefits | X1: rebate_checks | Y1: rebate_checks_arp | Z1: federal_ui | AA1: state_ui | AB1: federal_subsidies | AC1: federal_aid_to_small_businesses_arp | AD1: federal_other_direct_aid_arp | AE1: federal_other_vulnerable_arp | AF1: federal_student_loans | AG1: state_subsidies | AH1: federal_health_outlays | AI1: state_health_outlays | AJ1: post_mpc_federal_non_corporate_taxes | AK1: post_mpc_state_non_corporate_taxes | AL1: post_mpc_federal_corporate_taxes | AM1: post_mpc_state_corporate_taxes | AN1: post_mpc_federal_social_benefits | AO1: post_mpc_state_social_benefits | AP1: post_mpc_rebate_checks | AQ1: post_mpc_rebate_checks_arp | AR1: post_mpc_federal_ui | AS1: post_mpc_state_ui | AT1: post_mpc_federal_subsidies | AU1: post_mpc_federal_aid_to_small_businesses_arp | AV1: post_mpc_federal_other_vulnerable_arp | AW1: post_mpc_federal_student_loans | AX1: post_mpc_state_subsidies | AY1: post_mpc_federal_health_outlays | AZ1: post_mpc_state_health_outlays
A2: 2023 Q2 | B2: historical | C2: -1 | D2: 0.006582718 | E2: -0.0073827309 | F2: 0.0021322445 | G2: -0.0056211973 | H2: 0.0073926308 | I2: 0.0056240488 | J2: 27530.1 | K2: 18693.1 | L2: 0 | M2: 1738.8 | N2: 436.07272 | O2: 76.015143 | P2: 2934.6 | Q2: 4210.6 | R2: 2236.1 | S2: 415.5 | T2: 46.245323 | U2: 170.2 | V2: 2006.4269 | W2: 183.8 | X2: 0 | Y2: 0 | Z2: 0 | AA2: 32.8 | AB2: 101.3 | AC2: 12.726 | AD2: 1.416 | AE2: 12 | AF2: 45 | AG2: 0.7 | AH2: 1659.996 | AI2: 267.104 | AJ2: -2564.838 | AK2: -1347.348 | AL2: -144.40667 | AM2: -55.99 | AN2: 1790.1942 | AO2: 188.1225 | AP2: 2.1784 | AQ2: 41.153 | AR2: 9.157 | AS2: 22.948 | AT2: 159.5619 | AU2: 14.28301 | AV2: 28.976026 | AW2: 40.95 | AX2: 0.5679 | AY2: 1444.3544 | AZ2: 210.74558
A3: 2023 Q3 | B3: historical | C3: -1 | D3: 0.0094033912 | E3: 0.016732699 | F3: 0.00035461796 | G3: 0.013706093 | H3: 0.0067310092 | I3: 0.0056687159 | J3: 28074.8 | K3: 18961.8 | L3: 0 | M3: 1784.4 | N3: 417.91594 | O3: 76.015143 | P3: 3005.4 | Q3: 4257.9 | R3: 2270.3 | S3: 428.4 | T3: 62.071265 | U3: 168.5 | V3: 2016.4269 | W3: 185.9 | X3: 0 | Y3: 0 | Z3: 0 | AA3: 34.9 | AB3: 103.5 | AC3: 12.726 | AD3: 1.416 | AE3: 12 | AF3: 2.081508 | AG3: 0.7 | AH3: 1613.65 | AI3: 290.05 | AJ3: -2589.162 | AK3: -1357.608 | AL3: -150.09667 | AM3: -58.886667 | AN3: 1810.0624 | AO3: 184.0275 | AP3: 0 | AQ3: 41.153 | AR3: 0.67 | AS3: 26.182 | AT3: 136.66702 | AU3: 14.499352 | AV3: 22.99411 | AW3: 32.366302 | AX3: 0.5706 | AY3: 1456.9297 | AZ3: 229.62533
A4: 2023 Q4 | B4: historical | C4: -1 | D4: 0.0070345423 | E4: 0.00071349046 | F4: 0.0032733965 | G4: 0.0011916352 | H4: 0.0045206985 | I4: 0.0057213587 | J4: 28424.7 | K4: 19190.6 | L4: 0 | M4: 1812 | N4: 434.04594 | O4: 77.674143 | P4: 3049 | Q4: 4302.2 | R4: 2301.1 | S4: 442.7 | T4: 68.31219 | U4: 172.7 | V4: 2024.999 | W4: 189.5 | X4: 0 | Y4: 0 | Z4: 0 | AA4: 35.5 | AB4: 98 | AC4: 1.365 | AD4: 1.479 | AE4: 4.222 | AF4: 2.100618 | AG4: 0.7 | AH4: 1658.388 | AI4: 252.912 | AJ4: -2609.964 | AK4: -1367.988 | AL4: -156.48667 | AM4: -62.036667 | AN4: 1814.9933 | AO4: 168.84 | AP4: 0 | AQ4: 41.153 | AR4: 0.174 | AS4: 28.155 | AT4: 126.927 | AU4: 14.261254 | AV4: 16.69038 | AW4: 25.07398 | AX4: 0.5733 | AY4: 1475.7446 | AZ4: 236.95538
A5: 2024 Q1 | B5: historical | C5: -1 | D5: 0.01026393 | E5: 0.008782995 | F5: 0.0044129366 | G5: 0.0079425584 | H5: 0.0088526155 | I5: 0.0057507902 | J5: 28708.2 | K5: 19443.8 | L5: 0 | M5: 1834.3 | N5: 437.85294 | O5: 77.674143 | P5: 3097.5 | Q5: 4390.9 | R5: 2325.5 | S5: 472.3 | T5: 78.014538 | U5: 173.2 | V5: 2131.899 | W5: 194.8 | X5: 0 | Y5: 0 | Z5: 0 | AA5: 35.5 | AB5: 95 | AC5: 1.365 | AD5: 1.479 | AE5: 4.222 | AF5: 2.58153 | AG5: 0.7 | AH5: 1680.381 | AI5: 298.119 | AJ5: -2614.512 | AK5: -1373.712 | AL5: -162.89667 | AM5: -65.09 | AN5: 1840.4441 | AO5: 169.65 | AP5: 0 | AQ5: 34.1285 | AR5: 0.08 | AS5: 29.581 | AT5: 118.68525 | AU5: 14.023156 | AV5: 12.61027 | AW5: 18.306452 | AX5: 0.5418 | AY5: 1487.7934 | AZ5: 249.34162
A6: 2024 Q2 | B6: historical | C6: -1 | D6: 0.0075830466 | E6: 0.0028193299 | F6: 0.0024774522 | G6: 0.0027475708 | H6: 0.0064180979 | I6: 0.0058015415 | J6: 29147 | K6: 19756.1 | L6: 0 | M6: 1867.5 | N6: 447.07611 | O6: 77.674143 | P6: 3127.6 | Q6: 4456.6 | R6: 2363.6 | S6: 495.3 | T6: 85.438722 | U6: 170.6 | V6: 2160.999 | W6: 199.2 | X6: 0 | Y6: 0 | Z6: 0 | AA6: 36.1 | AB6: 93 | AC6: 1.365 | AD6: 1.479 | AE6: 4.222 | AF6: 2.604045 | AG6: 0.7 | AH6: 1707.978 | AI6: 314.922 | AJ6: -2622.426 | AK6: -1378.08 | AL6: -168.09667 | AM6: -67.456667 | AN6: 1875.2229 | AO6: 173.115 | AP6: 0 | AQ6: 27.388 | AR6: 0.035 | AS6: 30.805 | AT6: 96.491025 | AU6: 13.047051 | AV6: 9.32794 | AW6: 11.957994 | AX6: 0.4005 | AY6: 1498.5893 | AZ6: 260.10068
A7: 2024 Q3 | B7: historical | C7: -1 | D7: 0.0059965041 | E7: 0.0039266712 | F7: 0.0065105722 | G7: 0.0044025399 | H7: 0.0042217342 | I7: 0.0057505722 | J7: 29511.7 | K7: 20032.8 | L7: 0 | M7: 1917.9 | N7: 468.80533 | O7: 77.674143 | P7: 3169.1 | Q7: 4526.7 | R7: 2400.1 | S7: 490.6 | T7: 79.629003 | U7: 170.1 | V7: 2181.299 | W7: 209 | X7: 0 | Y7: 0 | Z7: 0 | AA7: 37 | AB7: 92.1 | AC7: 1.365 | AD7: 1.479 | AE7: 4.222 | AF7: 2.626465 | AG7: 0.7 | AH7: 1744.359 | AI7: 315.441 | AJ7: -2629.842 | AK7: -1390.32 | AL7: -172.82667 | AM7: -69.003333 | AN7: 1912.3191 | AO7: 178.3125 | AP7: 0 | AQ7: 20.6475 | AR7: 0.012 | AS7: 31.843 | AT7: 75.838725 | AU7: 8.517842 | AV7: 6.35096 | AW7: 8.1834539 | AX7: 0.4014 | AY7: 1527.9988 | AZ7: 265.81365
A8: 2024 Q4 | B8: historical | C8: -1 | D8: 0.0059688045 | E8: 0.0032787138 | F8: 0.0035235298 | G8: 0.003325747 | H8: 0.0062373921 | I8: 0.0057438004 | J8: 29825.2 | K8: 20351.3 | L8: 0 | M8: 1950 | N8: 473.51933 | O8: 79.268143 | P8: 3200.8 | Q8: 4590.3 | R8: 2436.6 | S8: 508.6 | T8: 71.179167 | U8: 174.2 | V8: 2212.098 | W8: 204.3 | X8: 0 | Y8: 0 | Z8: 0 | AA8: 37.3 | AB8: 94 | AC8: -0.901 | AD8: 1.63 | AE8: 2.372 | AF8: 2.649835 | AG8: 0.7 | AH8: 1786.697 | AI8: 314.303 | AJ8: -2642.622 | AK8: -1404.93 | AL8: -177.31333 | AM8: -69.03 | AN8: 1954.4164 | AO8: 181.6425 | AP8: 0 | AQ8: 13.836 | AR8: 0 | AS8: 32.631 | AT8: 65.877975 | AU8: 6.576191 | AV8: 4.56094 | AW8: 6.1234738 | AX8: 0.4023 | AY8: 1556.8684 | AZ8: 279.62662
A9: 2025 Q1 | B9: historical | C9: -1 | D9: 0.014353684 | E9: 0.0099039593 | F9: 0.0066231529 | G9: 0.0092720593 | H9: 0.0084681203 | I9: 0.0056201408 | J9: 30042.1 | K9: 20555 | L9: 0 | M9: 1949.7 | N9: 435.153 | O9: 79.268143 | P9: 3245.8 | Q9: 4710.9 | R9: 2460.1 | S9: 469.2 | T9: 73.980636 | U9: 184.4 | V9: 2312.798 | W9: 203.3 | X9: 0 | Y9: 0 | Z9: 0 | AA9: 37.1 | AB9: 107 | AC9: -0.901 | AD9: 1.63 | AE9: 2.372 | AF9: 2.645442 | AG9: 0.7 | AH9: 1811.332 | AI9: 316.468 | AJ9: -2684.838 | AK9: -1421.406 | AL9: -180.12 | AM9: -69.02 | AN9: 1995.1186 | AO9: 183.555 | AP9: 0 | AQ9: 7.0245 | AR9: 0 | AS9: 33.123 | AT9: 61.47135 | AU9: 4.63454 | AV9: 3.85754 | AW9: 4.0318455 | AX9: 0.3861 | AY9: 1586.3323 | AZ9: 283.75515
A10: 2025 Q2 | B10: historical | C10: -1 | D10: 0.017075286 | E10: 0.0023603402 | F10: 0.0054340243 | G10: 0.0029513035 | H10: 0.0052878919 | I10: 0.0057178013 | J10: 30485.7 | K10: 20789.9 | L10: -0.3 | M10: 1956.4 | N10: 411.32562 | O10: 75.196143 | P10: 3280.6 | Q10: 4944.5 | R10: 2490.5 | S10: 470 | T10: 88.394443 | U10: 183 | V10: 2409.698 | W10: 203.5 | X10: 0 | Y10: 0 | Z10: 0 | AA10: 38 | AB10: 119.2 | AC10: -0.901 | AD10: 1.63 | AE10: 2.372 | AF10: 2.6696 | AG10: 0.7 | AH10: 1877.66 | AI10: 319.14 | AJ10: -2750.124 | AK10: -1439.904 | AL10: -181.6 | AM10: -69.64 | AN10: 2051.0759 | AO10: 184.5225 | AP10: 0 | AQ10: 0.213 | AR10: 0 | AS10: 33.62 | AT10: 55.2555 | AU10: 2.745007 | AV10: 3.17264 | AW10: 2.3533203 | AX10: 0.315 | AY10: 1624.5108 | AZ10: 284.7042
A11: 2025 Q3 | B11: projection | C11: 0 | D11: 7.4170933e-06 | E11: 0.0077455121 | F11: 0.0077455121 | G11: 0.0077455121 | H11: 0.0079484627 | I11: 0.0057366284 | J11: 30789.813 | K11: 20995.964 | L11: -0.3 | M11: 1979.7453 | N11: 413.92898 | O11: 75.196143 | P11: 3310.5813 | Q11: 4936.9814 | R11: 2509.6975 | S11: 78.824649 | T11: 103.08351 | U11: 182.67714 | V11: 2384.2466 | W11: 220.14287 | X11: 0 | Y11: 0 | Z11: 0 | AA11: 35.7 | AB11: 120.101 | AC11: -0.901 | AD11: 1.63 | AE11: 2.372 | AF11: -8.306994 | AG11: 0 | AH11: 1917.0818 | AI11: 333.39357 | AJ11: -2804.4338 | AK11: -1457.2437 | AL11: -170.33082 | AM11: -70.075905 | AN11: 2096.7391 | AO11: 187.02965 | AP11: 0 | AQ11: 0.142 | AR11: 0 | AS11: 33.461 | AT11: 50.492075 | AU11: 0.855474 | AV11: 2.58402 | AW11: 0.19286449 | AX11: 0.28035 | AY11: 1663.3734 | AZ11: 288.74353
A12: 2025 Q4 | B12: projection | C12: 0 | D12: 0.0059761162 | E12: 0.0080020266 | F12: 0.0080020266 | G12: 0.0080020266 | H12: 0.0064403633 | I12: 0.0057166677 | J12: 31084.87 | K12: 21194.877 | L12: -0.3 | M12: 2006.7629 | N12: 412.67229 | O12: 75.196143 | P12: 3341.6818 | Q12: 5021.9409 | R12: 2535.4148 | S12: 333.3376 | T12: 109.65876 | U12: 182.58555 | V12: 2376.613 | W12: 223.32468 | X12: 0 | Y12: 0 | Z12: 0 | AA12: 35.7 | AB12: 124.44 | AC12: -2.15 | AD12: 1.671 | AE12: 0.49 | AF12: -8.28246 | AG12: 0 | AH12: 1952.9785 | AI12: 336.60699 | AJ12: -2852.2647 | AK12: -1473.9975 | AL12: -167.46541 | AM12: -70.20209 | AN12: 2133.755 | AO12: 191.3102 | AP12: 0 | AQ12: 0.071 | AR12: 0 | AS12: 33.286 | AT12: 48.391423 | AU12: 0.573855 | AV12: 2.04112 | AW12: -1.6414568 | AX12: 0.250425 | AY12: 1700.7868 | AZ12: 293.76193
A13: 2026 Q1 | B13: projection | C13: 0 | D13: 0.0053360386 | E13: 0.0081899949 | F13: 0.0081899949 | G13: 0.0081899949 | H13: 0.0055705631 | I13: 0.0056799438 | J13: 31389.687 | K13: 21376.266 | L13: -0.24 | M13: 2051.1056 | N13: 415.45334 | O13: 75.196143 | P13: 3373.6674 | Q13: 5030.9373 | R13: 2559.0591 | S13: 331.27795 | T13: 134.70904 | U13: 182.80643 | V13: 2429.8021 | W13: 226.55247 | X13: 0 | Y13: 0 | Z13: 0 | AA13: 35.7 | AB13: 122.29 | AC13: 0 | AD13: 0 | AE13: 0 | AF13: -8.28246 | AG13: 0 | AH13: 1988.4213 | AI13: 341.03339 | AJ13: -2896.3043 | AK13: -1490.9727 | AL13: -164.53467 | AM13: -70.498971 | AN13: 2160.0809 | AO13: 196.542 | AP13: 0 | AQ13: 0 | AR13: 0 | AS13: 33.119 | AT13: 48.72343 | AU13: 0.378236 | AV13: 1.53068 | AW13: -3.3871227 | AX13: 0.222075 | AY13: 1740.6318 | AZ13: 299.28914
... A18: 2027 Q2 | B18: projection | C18: 0 | D18: 0.0054914305 | E18: 0.0074988973 | F18: 0.0074988973 | G18: 0.0074988973 | H18: 0.0050077163 | I18: 0.0054538948 | J18: 32894.354 | K18: 22328.33 | L18: -0.04 | M18: 2142.6243 | N18: 426.9721 | O18: 75.196143 | P18: 3522.338 | Q18: 5336.9703 | R18: 2679.991 | S18: 331.10723 | T18: 123.27491 | U18: 182.18149 | V18: 2546.7536 | W18: 243.40486 | X18: 0 | Y18: 0 | Z18: 0 | AA18: 37.7 | AB18: 122.29 | AC18: 0 | AD18: 0 | AE18: 0 | AF18: -11 | AG18: 0 | AH18: 2143.7597 | AI18: 359.51286 | AJ18: -3096.8635 | AK18: -1565.8192 | AL18: -144.2572 | AM18: -72.472075 | AN18: 2252.6794 | AO18: 214.42702 | AP18: 0 | AQ18: 0 | AR18: 0 | AS18: 33.057 | AT18: 52.057024 | AU18: -0.074613 | AV18: 0.11938 | AW18: -9.3859472 | AX18: 0.1008 | AY18: 1889.361 | AZ18: 317.90085

Sheet AUGUST
A1: date | B1: id | C1: recession | D1: federal_purchases_deflator_growth | E1: consumption_grants_deflator_growth | F1: investment_grants_deflator_growth | G1: state_purchases_deflator_growth | H1: consumption_deflator_growth | I1: real_potential_gdp_growth | J1: gdp | K1: consumption | L1: uncertainty | M1: federal_purchases | N1: consumption_grants | O1: investment_grants | P1: state_purchases | Q1: federal_non_corporate_taxes | R1: state_non_corporate_taxes | S1: federal_corporate_taxes | T1: supply_side_ira | U1: state_corporate_taxes | V1: federal_social_benefits | W1: state_social_benefits | X1: rebate_checks | Y1: rebate_checks_arp | Z1: federal_ui | AA1: state_ui | AB1: federal_subsidies | AC1: federal_aid_to_small_businesses_arp | AD1: federal_other_direct_aid_arp | AE1: federal_other_vulnerable_arp | AF1: federal_student_loans | AG1: state_subsidies | AH1: federal_health_outlays | AI1: state_health_outlays | AJ1: post_mpc_federal_non_corporate_taxes | AK1: post_mpc_state_non_corporate_taxes | AL1: post_mpc_federal_corporate_taxes | AM1: post_mpc_state_corporate_taxes | AN1: post_mpc_federal_social_benefits | AO1: post_mpc_state_social_benefits | AP1: post_mpc_rebate_checks | AQ1: post_mpc_rebate_checks_arp | AR1: post_mpc_federal_ui | AS1: post_mpc_state_ui | AT1: post_mpc_federal_subsidies | AU1: post_mpc_federal_aid_to_small_businesses_arp | AV1: post_mpc_federal_other_vulnerable_arp | AW1: post_mpc_federal_student_loans | AX1: post_mpc_state_subsidies | AY1: post_mpc_federal_health_outlays | AZ1: post_mpc_state_health_outlays
A2: 2023 Q2 | B2: historical | C2: -1 | D2: 0.0086417671 | E2: -0.01151767 | F2: 0.00052868493 | G2: -0.0093193834 | H2: 0.0072242709 | I2: 0.0056240488 | J2: 27453.8 | K2: 18685.7 | L2: 0 | M2: 1741.8 | N2: 433.78172 | O2: 76.022 | P2: 2904.1 | Q2: 4212.5 | R2: 2311.5 | S2: 429.4 | T2: 46.245323 | U2: 162.4 | V2: 2002.924 | W2: 199.5 | X2: 0 | Y2: 0 | Z2: 0 | AA2: 32.7 | AB2: 101.8 | AC2: 12.726 | AD2: 1.416 | AE2: 12 | AF2: 45 | AG2: 0.7 | AH2: 1630.687 | AI2: 282.713 | AJ2: -2566.026 | AK2: -1367.676 | AL2: -143.85 | AM2: -53.296667 | AN2: 1788.6861 | AO2: 199.755 | AP2: 2.1784 | AQ2: 41.153 | AR2: 9.157 | AS2: 23.389 | AT2: 157.63073 | AU2: 14.28301 | AV2: 28.976026 | AW2: 40.95 | AX2: 0.5679 | AY2: 1433.2311 | AZ2: 212.5314
A3: 2023 Q3 | B3: historical | C3: -1 | D3: 0.0093952439 | E3: 0.011822268 | F3: 0.0014644383 | G3: 0.0099439103 | H3: 0.0066648916 | I3: 0.0056687159 | J3: 27967.7 | K3: 18929 | L3: 0 | M3: 1780.9 | N3: 417.68194 | O3: 76.022 | P3: 2975.5 | Q3: 4250.7 | R3: 2350.7 | S3: 451.9 | T3: 62.071265 | U3: 165.9 | V3: 2013.724 | W3: 202.2 | X3: 0 | Y3: 0 | Z3: 0 | AA3: 34.7 | AB3: 104 | AC3: 12.726 | AD3: 1.416 | AE3: 12 | AF3: 2.081508 | AG3: 0.7 | AH3: 1605.884 | AI3: 281.216 | AJ3: -2589.294 | AK3: -1383.726 | AL3: -150.29333 | AM3: -56.11 | AN3: 1807.6761 | AO3: 197.19 | AP3: 0 | AQ3: 41.153 | AR3: 0.67 | AS3: 26.191 | AT3: 134.86568 | AU3: 14.499352 | AV3: 22.99411 | AW3: 32.366302 | AX3: 0.5706 | AY3: 1444.615 | AZ3: 230.55503
A4: 2023 Q4 | B4: historical | C4: -1 | D4: 0.0094402902 | E4: -0.0010665683 | F4: 0.0030075075 | G4: -0.00027768742 | H4: 0.0041080152 | I4: 0.0057213587 | J4: 28297 | K4: 19170.2 | L4: 0 | M4: 1796.2 | N4: 432.29994 | O4: 77.681 | P4: 3019 | Q4: 4287.7 | R4: 2379.2 | S4: 464.8 | T4: 68.31219 | U4: 166.9 | V4: 2019.299 | W4: 204.8 | X4: 0 | Y4: 0 | Z4: 0 | AA4: 35.3 | AB4: 98.9 | AC4: 1.365 | AD4: 1.479 | AE4: 4.222 | AF4: 2.100618 | AG4: 0.7 | AH4: 1647.334 | AI4: 244.166 | AJ4: -2608.23 | AK4: -1398.45 | AL4: -157.41333 | AM4: -58.926667 | AN4: 1811.1895 | AO4: 182.7225 | AP4: 0 | AQ4: 41.153 | AR4: 0.174 | AS4: 28.083 | AT4: 125.27348 | AU4: 14.261254 | AV4: 16.69038 | AW4: 25.07398 | AX4: 0.5733 | AY4: 1461.9746 | AZ4: 236.93287
A5: 2024 Q1 | B5: historical | C5: -1 | D5: 0.0087613516 | E5: 0.010380039 | F5: 0.0058992838 | G5: 0.0095154199 | H5: 0.0084540665 | I5: 0.0057507902 | J5: 28624.1 | K5: 19424.8 | L5: 0 | M5: 1810.3 | N5: 434.70694 | O5: 77.681 | P5: 3070.7 | Q5: 4397.4 | R5: 2395.3 | S5: 459.9 | T5: 78.014538 | U5: 170.4 | V5: 2111.299 | W5: 208.7 | X5: 0 | Y5: 0 | Z5: 0 | AA5: 34.9 | AB5: 96.1 | AC5: 1.365 | AD5: 1.479 | AE5: 4.222 | AF5: 2.58153 | AG5: 0.7 | AH5: 1667.927 | AI5: 286.073 | AJ5: -2614.032 | AK5: -1407.72 | AL5: -163.08 | AM5: -61.836667 | AN5: 1833.1303 | AO5: 183.42 | AP5: 0 | AQ5: 34.1285 | AR5: 0.08 | AS5: 29.385 | AT5: 117.369 | AU5: 14.023156 | AV5: 12.61027 | AW5: 18.306452 | AX5: 0.5418 | AY5: 1474.1622 | AZ5: 246.1878
A6: 2024 Q2 | B6: historical | C6: -1 | D6: 0.0069774818 | E6: 0.0048308027 | F6: 0.00082927412 | G6: 0.004048583 | H6: 0.0062690295 | I6: 0.0058015415 | J6: 29016.7 | K6: 19682.7 | L6: 0 | M6: 1842.2 | N6: 440.59711 | O6: 77.681 | P6: 3100.9 | Q6: 4417.2 | R6: 2439 | S6: 493.4 | T6: 85.438722 | U6: 164 | V6: 2135.399 | W6: 212.2 | X6: 0 | Y6: 0 | Z6: 0 | AA6: 34.9 | AB6: 93.7 | AC6: 1.365 | AD6: 1.479 | AE6: 4.222 | AF6: 2.604045 | AG6: 0.7 | AH6: 1695.257 | AI6: 296.543 | AJ6: -2618.082 | AK6: -1416.024 | AL6: -168.06333 | AM6: -64.18 | AN6: 1862.9372 | AO6: 186.2775 | AP6: 0 | AQ6: 27.388 | AR6: 0.035 | AS6: 30.398 | AT6: 95.488875 | AU6: 13.047051 | AV6: 9.32794 | AW6: 11.957994 | AX6: 0.4005 | AY6: 1488.6905 | AZ6: 249.29955
A7: 2024 Q3 | B7: historical | C7: -1 | D7: 0.0060650111 | E7: 0.0054243399 | F7: 0.0079424916 | G7: 0.0059191982 | H7: 0.003828838 | I7: 0.0057505722 | J7: 29374.9 | K7: 19938.4 | L7: 0 | M7: 1893.4 | N7: 461.92733 | O7: 77.681 | P7: 3141.6 | Q7: 4456.5 | R7: 2477.5 | S7: 493.1 | T7: 79.629003 | U7: 162.6 | V7: 2152.199 | W7: 221.6 | X7: 0 | Y7: 0 | Z7: 0 | AA7: 35.7 | AB7: 92.1 | AC7: 1.365 | AD7: 1.479 | AE7: 4.222 | AF7: 2.626465 | AG7: 0.7 | AH7: 1731.437 | AI7: 291.163 | AJ7: -2616.51 | AK7: -1432.356 | AL7: -173.01667 | AM7: -65.623333 | AN7: 1894.0941 | AO7: 190.6425 | AP7: 0 | AQ7: 20.6475 | AR7: 0.012 | AS7: 31.239 | AT7: 75.1185 | AU7: 8.517842 | AV7: 6.35096 | AW7: 8.1834539 | AX7: 0.4014 | AY7: 1516.9399 | AZ7: 251.53762
A8: 2024 Q4 | B8: historical | C8: -1 | D8: 0.0065983817 | E8: 0.0047344538 | F8: 0.0031771423 | G8: 0.0044210592 | H8: 0.0059072139 | I8: 0.0057438004 | J8: 29723.9 | K8: 20255.5 | L8: 0 | M8: 1924.7 | N8: 463.54133 | O8: 79.275 | P8: 3175 | Q8: 4532.9 | R8: 2519.8 | S8: 512.1 | T8: 71.179167 | U8: 164.2 | V8: 2169.998 | W8: 217.7 | X8: 0 | Y8: 0 | Z8: 0 | AA8: 36.1 | AB8: 93.5 | AC8: -0.901 | AD8: 1.63 | AE8: 2.372 | AF8: 2.649835 | AG8: 0.7 | AH8: 1773.675 | AI8: 289.625 | AJ8: -2624.49 | AK8: -1450.014 | AL8: -178.15667 | AM8: -65.493333 | AN8: 1928.0014 | AO8: 193.545 | AP8: 0 | AQ8: 13.836 | AR8: 0 | AS8: 31.859 | AT8: 65.416275 | AU8: 6.576191 | AV8: 4.56094 | AW8: 6.1234738 | AX8: 0.4023 | AY8: 1545.3666 | AZ8: 261.7659
A9: 2025 Q1 | B9: historical | C9: -1 | D9: 0.013899743 | E9: 0.010246174 | F9: 0.0073455587 | G9: 0.0096788692 | H9: 0.0090216745 | I9: 0.0056201408 | J9: 29962 | K9: 20461.6 | L9: 0 | M9: 1928.4 | N9: 424.555 | O9: 79.275 | P9: 3221.5 | Q9: 4640.7 | R9: 2550.5 | S9: 519.8 | T9: 73.980636 | U9: 174.7 | V9: 2262.298 | W9: 218.6 | X9: 0 | Y9: 0 | Z9: 0 | AA9: 35.8 | AB9: 104.1 | AC9: -0.901 | AD9: 1.63 | AE9: 2.372 | AF9: 2.645442 | AG9: 0.7 | AH9: 1797.33 | AI9: 310.57 | AJ9: -2662.152 | AK9: -1469.628 | AL9: -182.83 | AM9: -65.623333 | AN9: 1961.9761 | AO9: 195.7725 | AP9: 0 | AQ9: 7.0245 | AR9: 0 | AS9: 32.193 | AT9: 61.00965 | AU9: 4.63454 | AV9: 3.85754 | AW9: 4.0318455 | AX9: 0.3861 | AY9: 1574.4823 | AZ9: 267.27772
A10: 2025 Q2 | B10: historical | C10: -1 | D10: 0.017319354 | E10: 0.002308932 | F10: 0.0037082909 | G10: 0.0025864782 | H10: 0.0049840368 | I10: 0.0057178013 | J10: 30353.9 | K10: 20643.9 | L10: -0.3 | M10: 1938.3 | N10: 400.72762 | O10: 75.203 | P10: 3250.7 | Q10: 4871.4 | R10: 2589.6 | S10: 0 | T10: 88.394443 | U10: 0 | V10: 2354.298 | W10: 219.1 | X10: 0 | Y10: 0 | Z10: 0 | AA10: 36.7 | AB10: 116.5 | AC10: -0.901 | AD10: 1.63 | AE10: 2.372 | AF10: 2.6696 | AG10: 0.7 | AH10: 1862.758 | AI10: 303.742 | AJ10: -2721.996 | AK10: -1490.502 | AL10: -168.92667 | AM10: -60.37 | AN10: 2011.2284 | AO10: 197.325 | AP10: 0 | AQ10: 0.213 | AR10: 0 | AS10: 32.596 | AT10: 54.821925 | AU10: 2.745007 | AV10: 3.17264 | AW10: 2.3533203 | AX10: 0.315 | AY10: 1612.17 | AZ10: 268.8975
A11: 2025 Q3 | B11: projection | C11: 0 | D11: 0.006125897 | E11: 0.0077455121 | F11: 0.0077455121 | G11: 0.0077455121 | H11: 0.0061860943 | I11: 0.0057366284 | J11: 30656.699 | K11: 20848.517 | L11: -0.3 | M11: 1963.4582 | N11: 403.22655 | O11: 75.203 | P11: 3280.408 | Q11: 4884.4794 | R11: 2615.3134 | S11: 142.43687 | T11: 103.08351 | U11: 159.08436 | V11: 2341.5871 | W11: 234.74461 | X11: 0 | Y11: 0 | Z11: 0 | AA11: 35.7 | AB11: 117.401 | AC11: -0.901 | AD11: 1.63 | AE11: 2.372 | AF11: -8.306994 | AG11: 0 | AH11: 1899.0896 | AI11: 313.32486 | AJ11: -2774.6495 | AK11: -1510.2676 | AL11: -160.2679 | AM11: -60.369479 | AN11: 2053.8408 | AO11: 200.28254 | AP11: 0 | AQ11: 0.142 | AR11: 0 | AS11: 32.637 | AT11: 50.094049 | AU11: 0.855474 | AV11: 2.58402 | AW11: 0.19286449 | AX11: 0.28035 | AY11: 1649.8918 | AZ11: 273.88392
A12: 2025 Q4 | B12: projection | C12: 0 | D12: 0.0059761162 | E12: 0.0080020266 | F12: 0.0080020266 | G12: 0.0080020266 | H12: 0.0064403633 | I12: 0.0057166677 | J12: 30950.479 | K12: 21046.033 | L12: -0.3 | M12: 1949.8647 | N12: 401.8644 | O12: 75.203 | P12: 3311.2251 | Q12: 4969.1321 | R12: 2642.2018 | S12: 396.55677 | T12: 109.65876 | U12: 159.00461 | V12: 2333.6927 | W12: 238.1762 | X12: 0 | Y12: 0 | Z12: 0 | AA12: 35.7 | AB12: 121.74 | AC12: -2.15 | AD12: 1.671 | AE12: 0.49 | AF12: -8.28246 | AG12: 0 | AH12: 1934.0742 | AI12: 317.97578 | AJ12: -2821.3994 | AK12: -1529.2038 | AL12: -159.92312 | AM12: -60.262966 | AN12: 2090.6721 | AO12: 204.88968 | AP12: 0 | AQ12: 0.071 | AR12: 0 | AS12: 32.626 | AT12: 48.028048 | AU12: 0.573855 | AV12: 2.04112 | AW12: -1.6414568 | AX12: 0.250425 | AY12: 1685.9817 | AZ12: 280.26284
A13: 2026 Q1 | B13: projection | C13: 0 | D13: 0.0053360386 | E13: 0.0081899949 | F13: 0.0081899949 | G13: 0.0081899949 | H13: 0.0055705631 | I13: 0.0056799438 | J13: 31253.979 | K13: 21226.148 | L13: -0.3 | M13: 1975.2258 | N13: 404.53897 | O13: 75.203 | P13: 3342.9191 | Q13: 4978.0341 | R13: 2666.9309 | S13: 394.10649 | T13: 134.70904 | U13: 159.19696 | V13: 2386.8834 | W13: 241.65795 | X13: 0 | Y13: 0 | Z13: 0 | AA13: 35.7 | AB13: 119.59 | AC13: 0 | AD13: 0 | AE13: 0 | AF13: -8.28246 | AG13: 0 | AH13: 1968.2382 | AI13: 324.22669 | AJ13: -2861.8507 | AK13: -1548.5987 | AL13: -158.58334 | AM13: -60.279531 | AN13: 2118.7038 | AO13: 210.07772 | AP13: 0 | AQ13: 0 | AR13: 0 | AS13: 32.634 | AT13: 48.257005 | AU13: 0.378236 | AV13: 1.53068 | AW13: -3.3871227 | AX13: 0.222075 | AY13: 1724.436 | AZ13: 283.3356
... A18: 2027 Q2 | B18: projection | C18: 0 | D18: 0.0054914305 | E18: 0.0074988973 | F18: 0.0074988973 | G18: 0.0074988973 | H18: 0.0050077163 | I18: 0.0054538948 | J18: 32752.141 | K18: 22171.526 | L18: -0.1 | M18: 2044.7153 | N18: 415.5093 | O18: 75.203 | P18: 3490.2347 | Q18: 5280.0709 | R18: 2793.2668 | S18: 392.01857 | T18: 123.27491 | U18: 158.65273 | V18: 2502.7743 | W18: 259.84521 | X18: 0 | Y18: 0 | Z18: 0 | AA18: 37.7 | AB18: 119.59 | AC18: 0 | AD18: 0 | AE18: 0 | AF18: -11 | AG18: 0 | AH18: 2124.1916 | AI18: 341.00413 | AJ18: -3064.0359 | AK18: -1631.894 | AL18: -147.07811 | AM18: -59.169503 | AN18: 2213.3383 | AO18: 228.85494 | AP18: 0 | AQ18: 0 | AR18: 0 | AS18: 33.057 | AT18: 51.094924 | AU18: -0.074613 | AV18: 0.11938 | AW18: -9.3859472 | AX18: 0.1008 | AY18: 1872.3426 | AZ18: 301.66449

Sheet diff
A1: date | B1: id | C1: recession | D1: federal_purchases_deflator_growth | E1: consumption_grants_deflator_growth | F1: investment_grants_deflator_growth | G1: state_purchases_deflator_growth | H1: consumption_deflator_growth | I1: real_potential_gdp_growth | J1: gdp | K1: consumption | L1: uncertainty | M1: federal_purchases | N1: consumption_grants | O1: investment_grants | P1: state_purchases | Q1: federal_non_corporate_taxes | R1: state_non_corporate_taxes | S1: federal_corporate_taxes | T1: supply_side_ira | U1: state_corporate_taxes | V1: federal_social_benefits | W1: state_social_benefits | X1: rebate_checks | Y1: rebate_checks_arp | Z1: federal_ui | AA1: state_ui | AB1: federal_subsidies | AC1: federal_aid_to_small_businesses_arp | AD1: federal_other_direct_aid_arp | AE1: federal_other_vulnerable_arp | AF1: federal_student_loans | AG1: state_subsidies | AH1: federal_health_outlays | AI1: state_health_outlays | AJ1: post_mpc_federal_non_corporate_taxes | AK1: post_mpc_state_non_corporate_taxes | AL1: post_mpc_federal_corporate_taxes | AM1: post_mpc_state_corporate_taxes | AN1: post_mpc_federal_social_benefits | AO1: post_mpc_state_social_benefits | AP1: post_mpc_rebate_checks | AQ1: post_mpc_rebate_checks_arp | AR1: post_mpc_federal_ui | AS1: post_mpc_state_ui | AT1: post_mpc_federal_subsidies | AU1: post_mpc_federal_aid_to_small_businesses_arp | AV1: post_mpc_federal_other_vulnerable_arp | AW1: post_mpc_federal_student_loans | AX1: post_mpc_state_subsidies | AY1: post_mpc_federal_health_outlays | AZ1: post_mpc_state_health_outlays
A2: 2023 Q2 | B2: historical | C2: -1 | D2: ='JUST RAN'!D2-AUGUST!D2 -> -0.0020590491 | E2: ='JUST RAN'!E2-AUGUST!E2 -> 0.0041349386 | F2: ='JUST RAN'!F2-AUGUST!F2 -> 0.0016035596 | G2: ='JUST RAN'!G2-AUGUST!G2 -> 0.0036981861 | H2: ='JUST RAN'!H2-AUGUST!H2 -> 0.00016835997 | I2: ='JUST RAN'!I2-AUGUST!I2 -> 0 | J2: ='JUST RAN'!J2-AUGUST!J2 -> 76.3 | K2: ='JUST RAN'!K2-AUGUST!K2 -> 7.4 | ... AV2: ='JUST RAN'!AV2-AUGUST!AV2 -> 0
A3: 2023 Q3 | B3: historical | C3: -1 | D3: ='JUST RAN'!D3-AUGUST!D3 -> 8.147383e-06 | E3: ='JUST RAN'!E3-AUGUST!E3 -> 0.0049104309 | F3: ='JUST RAN'!F3-AUGUST!F3 -> -0.0011098203 | G3: ='JUST RAN'!G3-AUGUST!G3 -> 0.0037621825 | H3: ='JUST RAN'!H3-AUGUST!H3 -> 6.6117654e-05 | I3: ='JUST RAN'!I3-AUGUST!I3 -> 0 | J3: ='JUST RAN'!J3-AUGUST!J3 -> 107.1 | K3: ='JUST RAN'!K3-AUGUST!K3 -> 32.8 | ... AV3: ='JUST RAN'!AV3-AUGUST!AV3 -> 0
A4: 2023 Q4 | B4: historical | C4: -1 | D4: ='JUST RAN'!D4-AUGUST!D4 -> -0.0024057479 | E4: ='JUST RAN'!E4-AUGUST!E4 -> 0.0017800588 | F4: ='JUST RAN'!F4-AUGUST!F4 -> 0.00026588903 | G4: ='JUST RAN'!G4-AUGUST!G4 -> 0.0014693226 | H4: ='JUST RAN'!H4-AUGUST!H4 -> 0.00041268334 | I4: ='JUST RAN'!I4-AUGUST!I4 -> 0 | J4: ='JUST RAN'!J4-AUGUST!J4 -> 127.7 | K4: ='JUST RAN'!K4-AUGUST!K4 -> 20.4 | ... AV4: ='JUST RAN'!AV4-AUGUST!AV4 -> 0
A5: 2024 Q1 | B5: historical | C5: -1 | D5: ='JUST RAN'!D5-AUGUST!D5 -> 0.001502578 | E5: ='JUST RAN'!E5-AUGUST!E5 -> -0.0015970445 | F5: ='JUST RAN'!F5-AUGUST!F5 -> -0.0014863472 | G5: ='JUST RAN'!G5-AUGUST!G5 -> -0.0015728615 | H5: ='JUST RAN'!H5-AUGUST!H5 -> 0.00039854896 | I5: ='JUST RAN'!I5-AUGUST!I5 -> 0 | J5: ='JUST RAN'!J5-AUGUST!J5 -> 84.1 | K5: ='JUST RAN'!K5-AUGUST!K5 -> 19 | ... AV5: ='JUST RAN'!AV5-AUGUST!AV5 -> 0
A6: 2024 Q2 | B6: historical | C6: -1 | D6: ='JUST RAN'!D6-AUGUST!D6 -> 0.00060556483 | E6: ='JUST RAN'!E6-AUGUST!E6 -> -0.0020114728 | F6: ='JUST RAN'!F6-AUGUST!F6 -> 0.0016481781 | G6: ='JUST RAN'!G6-AUGUST!G6 -> -0.0013010122 | H6: ='JUST RAN'!H6-AUGUST!H6 -> 0.00014906837 | I6: ='JUST RAN'!I6-AUGUST!I6 -> 0 | J6: ='JUST RAN'!J6-AUGUST!J6 -> 130.3 | K6: ='JUST RAN'!K6-AUGUST!K6 -> 73.4 | ... AV6: ='JUST RAN'!AV6-AUGUST!AV6 -> 0
A7: 2024 Q3 | B7: historical | C7: -1 | D7: ='JUST RAN'!D7-AUGUST!D7 -> -6.8507042e-05 | E7: ='JUST RAN'!E7-AUGUST!E7 -> -0.0014976688 | F7: ='JUST RAN'!F7-AUGUST!F7 -> -0.0014319194 | G7: ='JUST RAN'!G7-AUGUST!G7 -> -0.0015166583 | H7: ='JUST RAN'!H7-AUGUST!H7 -> 0.00039289627 | I7: ='JUST RAN'!I7-AUGUST!I7 -> 0 | J7: ='JUST RAN'!J7-AUGUST!J7 -> 136.8 | K7: ='JUST RAN'!K7-AUGUST!K7 -> 94.4 | ... AV7: ='JUST RAN'!AV7-AUGUST!AV7 -> 0
A8: 2024 Q4 | B8: historical | C8: -1 | D8: ='JUST RAN'!D8-AUGUST!D8 -> -0.00062957716 | E8: ='JUST RAN'!E8-AUGUST!E8 -> -0.0014557399 | F8: ='JUST RAN'!F8-AUGUST!F8 -> 0.00034638741 | G8: ='JUST RAN'!G8-AUGUST!G8 -> -0.0010953122 | H8: ='JUST RAN'!H8-AUGUST!H8 -> 0.00033017816 | I8: ='JUST RAN'!I8-AUGUST!I8 -> 0 | J8: ='JUST RAN'!J8-AUGUST!J8 -> 101.3 | K8: ='JUST RAN'!K8-AUGUST!K8 -> 95.8 | ... AV8: ='JUST RAN'!AV8-AUGUST!AV8 -> 0
A9: 2025 Q1 | B9: historical | C9: -1 | D9: ='JUST RAN'!D9-AUGUST!D9 -> 0.00045394116 | E9: ='JUST RAN'!E9-AUGUST!E9 -> -0.00034221504 | F9: ='JUST RAN'!F9-AUGUST!F9 -> -0.00072240576 | G9: ='JUST RAN'!G9-AUGUST!G9 -> -0.00040680989 | H9: ='JUST RAN'!H9-AUGUST!H9 -> -0.00055355426 | I9: ='JUST RAN'!I9-AUGUST!I9 -> 0 | J9: ='JUST RAN'!J9-AUGUST!J9 -> 80.1 | K9: ='JUST RAN'!K9-AUGUST!K9 -> 93.4 | ... AV9: ='JUST RAN'!AV9-AUGUST!AV9 -> 0
A10: 2025 Q2 | B10: historical | C10: -1 | D10: ='JUST RAN'!D10-AUGUST!D10 -> -0.00024406833 | E10: ='JUST RAN'!E10-AUGUST!E10 -> 5.1408191e-05 | F10: ='JUST RAN'!F10-AUGUST!F10 -> 0.0017257334 | G10: ='JUST RAN'!G10-AUGUST!G10 -> 0.00036482532 | H10: ='JUST RAN'!H10-AUGUST!H10 -> 0.00030385517 | I10: ='JUST RAN'!I10-AUGUST!I10 -> 0 | J10: ='JUST RAN'!J10-AUGUST!J10 -> 131.8 | K10: ='JUST RAN'!K10-AUGUST!K10 -> 146 | ... AV10: ='JUST RAN'!AV10-AUGUST!AV10 -> 0
A11: 2025 Q3 | B11: projection | C11: 0 | D11: ='JUST RAN'!D11-AUGUST!D11 -> -0.0061184799 | E11: ='JUST RAN'!E11-AUGUST!E11 -> 0 | F11: ='JUST RAN'!F11-AUGUST!F11 -> 0 | G11: ='JUST RAN'!G11-AUGUST!G11 -> 0 | H11: ='JUST RAN'!H11-AUGUST!H11 -> 0.0017623685 | I11: ='JUST RAN'!I11-AUGUST!I11 -> 0 | J11: ='JUST RAN'!J11-AUGUST!J11 -> 133.11478 | K11: ='JUST RAN'!K11-AUGUST!K11 -> 147.44711 | ... AV11: ='JUST RAN'!AV11-AUGUST!AV11 -> 0
A12: 2025 Q4 | B12: projection | C12: 0 | D12: ='JUST RAN'!D12-AUGUST!D12 -> 0 | E12: ='JUST RAN'!E12-AUGUST!E12 -> 0 | F12: ='JUST RAN'!F12-AUGUST!F12 -> 0 | G12: ='JUST RAN'!G12-AUGUST!G12 -> 0 | H12: ='JUST RAN'!H12-AUGUST!H12 -> 0 | I12: ='JUST RAN'!I12-AUGUST!I12 -> 0 | J12: ='JUST RAN'!J12-AUGUST!J12 -> 134.39041 | K12: ='JUST RAN'!K12-AUGUST!K12 -> 148.84401 | ... AV12: ='JUST RAN'!AV12-AUGUST!AV12 -> 0
A13: 2026 Q1 | B13: projection | C13: 0 | D13: ='JUST RAN'!D13-AUGUST!D13 -> 0 | E13: ='JUST RAN'!E13-AUGUST!E13 -> 0 | F13: ='JUST RAN'!F13-AUGUST!F13 -> 0 | G13: ='JUST RAN'!G13-AUGUST!G13 -> 0 | H13: ='JUST RAN'!H13-AUGUST!H13 -> 0 | I13: ='JUST RAN'!I13-AUGUST!I13 -> 0 | J13: ='JUST RAN'!J13-AUGUST!J13 -> 135.70824 | K13: ='JUST RAN'!K13-AUGUST!K13 -> 150.11784 | ... AV13: ='JUST RAN'!AV13-AUGUST!AV13 -> 0
... A18: 2027 Q2 | B18: projection | C18: 0 | D18: ='JUST RAN'!D18-AUGUST!D18 -> 0 | E18: ='JUST RAN'!E18-AUGUST!E18 -> 0 | F18: ='JUST RAN'!F18-AUGUST!F18 -> 0 | G18: ='JUST RAN'!G18-AUGUST!G18 -> 0 | H18: ='JUST RAN'!H18-AUGUST!H18 -> 0 | I18: ='JUST RAN'!I18-AUGUST!I18 -> 0 | J18: ='JUST RAN'!J18-AUGUST!J18 -> 142.21343 | K18: ='JUST RAN'!K18-AUGUST!K18 -> 156.80384 | ... AV18: ='JUST RAN'!AV18-AUGUST!AV18 -> 0
