Workbook

Sheet FIM Breakdown_old
A1: Table 1: Breakdown of FIM by component
B2: Total | D2: Purchases | J2: Taxes Transfers and Subsidies (includes supply side and uncertainty effects) | L2: Taxes | Q2: Transfers | U2: Uncertainty | W2: Supply Side
D3: Purchases Total | G3: Subcomponents of Federal Purchases | L3: Taxes Total | M3: Subcomponents of Taxes | Q3: Transfers Total | R3: Subcomponents of Transfers | U3: Uncertainty Total | W3: Supply Side Total | X3: Subcomponents of Supply Side
E4: Federal | F4: State and Local | G4: Federal Purchases OBBBA | H4: Federal purchases Other | M4: Taxes OBBBA | N4: Tariffs | O4: Taxes Other | R4: Transfers OBBBA | S4: Transfers Other | U4: Tariff Uncertainty | X4: Shutdown Spillovers | Y4: Student Loans | Z4: IRA/CHIPS | AA4: Supply Side Effects of OBBBA
A5: 2025 Q2 | B5: =D5+L5+Q5+U5+W5 -> -0.59669312 | D5: =E5+F5 -> -0.40608412 | E5: -0.94596317 | F5: 0.53987905 | G5: 0 | H5: =E5-G5 -> -0.94596317 | J5: =L5+Q5+U5+W5 -> -0.190609 | L5: -0.33591118 | M5: 0 | N5: 0 | O5: =L5-M5-N5 -> -0.33591118 | Q5: 0.2818712 | R5: 0 | S5: =Q5-R5 -> 0.2818712 | U5: -0.3 | W5: =X5+Y5+Z5+AA5 -> 0.16343098 | X5: 0 | Y5: -0.023738219 | Z5: 0.1871692 | AA5: 0
A6: 2025 Q3 | B6: =D6+L6+Q6+U6+W6 -> 0.11998802 | D6: =E6+F6 -> -0.025846212 | E6: 0.11078208 | F6: -0.13662829 | G6: 0.26333064 | H6: =E6-G6 -> -0.15254855 | J6: =L6+Q6+U6+W6 -> 0.14583423 | L6: 0.11233031 | M6: 0.36324487 | N6: -0.41325065 | O6: =L6-M6-N6 -> 0.16233609 | Q6: 0.18114458 | R6: -0.011450396 | S6: =Q6-R6 -> 0.19259498 | U6: -0.3 | W6: =X6+Y6+Z6+AA6 -> 0.15235934 | X6: 0 | Y6: -0.029638323 | Z6: 0.18199766 | AA6: 0
A7: 2025 Q4 | B7: =D7+L7+Q7+U7+W7 -> -1.4936004 | D7: =E7+F7 -> -0.73887261 | E7: -0.65524347 | F7: -0.083629139 | G7: 0.14276535 | H7: =E7-G7 -> -0.79800882 | J7: =L7+Q7+U7+W7 -> -0.75472778 | L7: 0.045379711 | M7: 0.24139469 | N7: -0.4970158 | O7: =L7-M7-N7 -> 0.30100082 | Q7: 0.35334347 | R7: -0.030533258 | S7: =Q7-R7 -> 0.38387673 | U7: -0.3 | W7: =X7+Y7+Z7+AA7 -> -0.85345096 | X7: -0.9 | Y7: -0.024548492 | Z7: 0.071097532 | AA7: 0
A8: 2026 Q1 | B8: =D8+L8+Q8+U8+W8 -> 2.0227275 | D8: =E8+F8 -> 0.70673922 | E8: 0.84183311 | F8: -0.13509389 | G8: 0.20092433 | H8: =E8-G8 -> 0.64090877 | J8: =L8+Q8+U8+W8 -> 1.3159883 | L8: 0.2212818 | M8: 0.1974875 | N8: -0.28656035 | O8: =L8-M8-N8 -> 0.31035466 | Q8: 0.14362805 | R8: -0.028154983 | S8: =Q8-R8 -> 0.17178303 | U8: -0.3 | W8: =X8+Y8+Z8+AA8 -> 1.2510785 | X8: 0.9 | Y8: -0.022803876 | Z8: 0.31388233 | AA8: 0.06
A9: 2026 Q2 | B9: =D9+L9+Q9+U9+W9 -> 0.063982591 | D9: =E9+F9 -> -0.17282167 | E9: -0.059218055 | F9: -0.11360361 | G9: 0.12541077 | H9: =E9-G9 -> -0.18462882 | J9: =L9+Q9+U9+W9 -> 0.23680426 | L9: 0.20865971 | M9: 0.19341392 | N9: -0.2400719 | O9: =L9-M9-N9 -> 0.25531769 | Q9: -0.059715243 | R9: -0.026046165 | S9: =Q9-R9 -> -0.033669078 | U9: -0.2 | W9: =X9+Y9+Z9+AA9 -> 0.28785979 | X9: 0 | Y9: -0.020976971 | Z9: 0.24883676 | AA9: 0.06
A10: 2026 Q3 | B10: =D10+L10+Q10+U10+W10 -> -0.091736921 | D10: =E10+F10 -> -0.22708998 | E10: -0.073368862 | F10: -0.15372112 | G10: 0.0700293 | H10: =E10-G10 -> -0.14339816 | J10: =L10+Q10+U10+W10 -> 0.13535306 | L10: 0.055087852 | M10: 0.13390434 | N10: -0.23614384 | O10: =L10-M10-N10 -> 0.15732735 | Q10: 0.16272556 | R10: -0.034076064 | S10: =Q10-R10 -> 0.19680163 | U10: -0.2 | W10: =X10+Y10+Z10+AA10 -> 0.11753964 | X10: 0 | Y10: -0.019015005 | Z10: 0.076554649 | AA10: 0.06
A11: 2026 Q4 | B11: =D11+L11+Q11+U11+W11 -> -0.28654627 | D11: =E11+F11 -> -0.33323664 | E11: -0.19354295 | F11: -0.13969369 | G11: -0.0064345259 | H11: =E11-G11 -> -0.18710842 | J11: =L11+Q11+U11+W11 -> 0.046690367 | L11: -0.033915337 | M11: 0.13098652 | N11: -0.23639649 | O11: =L11-M11-N11 -> 0.071494629 | Q11: 0.28585123 | R11: -0.081458626 | S11: =Q11-R11 -> 0.36730986 | U11: -0.2 | W11: =X11+Y11+Z11+AA11 -> -0.005245526 | X11: 0 | Y11: -0.012025896 | Z11: -0.05321963 | AA11: 0.06
A12: 2027 Q1 | B12: =D12+L12+Q12+U12+W12 -> -0.4501549 | D12: =E12+F12 -> -0.26678026 | E12: -0.10882877 | F12: -0.15795149 | G12: -0.0086757821 | H12: =E12-G12 -> -0.10015299 | J12: =L12+Q12+U12+W12 -> -0.18337463 | L12: -0.3598456 | M12: 0.16495007 | N12: -0.23727438 | O12: =L12-M12-N12 -> -0.28752129 | Q12: 0.42820891 | R12: -0.080731784 | S12: =Q12-R12 -> 0.50894069 | U12: -0.1 | W12: =X12+Y12+Z12+AA12 -> -0.15173794 | X12: 0 | Y12: -0.01149048 | Z12: -0.20024746 | AA12: 0.06
A13: 2027 Q2 | B13: =D13+L13+Q13+U13+W13 -> -0.40695096 | D13: =E13+F13 -> -0.30191172 | E13: -0.15456652 | F13: -0.1473452 | G13: -0.008470458 | H13: =E13-G13 -> -0.14609606 | J13: =L13+Q13+U13+W13 -> -0.10503923 | L13: -0.27777126 | M13: 0.16015426 | N13: -0.23458822 | O13: =L13-M13-N13 -> -0.2033373 | Q13: 0.53339589 | R13: -0.07824496 | S13: =Q13-R13 -> 0.61164085 | U13: -0.1 | W13: =X13+Y13+Z13+AA13 -> -0.26066386 | X13: 0 | Y13: -0.0095126456 | Z13: -0.31115122 | AA13: 0.06
A16: Table 2: Decomposing FIM into effects of OBBBA, other supply side effects, tariffs and tariff uncertainty, and underlying FIM
B17: Total | C17: Underlying FIM | D17: OBBBA | E17: Tariffs and Uncertainty | F17: IRA, CHIPS, Student Loans | G17: Gov shutdown
A18: 2025 Q2 | B18: =B5 -> -0.59669312 | C18: =B18-SUM(D18:G18) -> -0.4601241 | D18: =G5+M5+R5+AA5 -> 0 | E18: =N5+U5 -> -0.3 | F18: =Y5+Z5+AA5 -> 0.16343098
A19: 2025 Q3 | B19: =B6 -> 0.11998802 | C19: =B19-SUM(D19:G19) -> 0.06575422 | D19: =G6+M6+R6+AA6 -> 0.61512511 | E19: =N6+U6 -> -0.71325065 | F19: =Y6+Z6+AA6 -> 0.15235934
A20: 2025 Q4 | B20: =B7 -> -1.4936004 | C20: =B20-SUM(D20:G20) -> 0.4032396 | D20: =G7+M7+R7+AA7 -> 0.35362678 | E20: =N7+U7 -> -0.7970158 | F20: =Y7+Z7+AA7 -> 0.04654904 | G20: -1.5
A21: 2026 Q1 | B21: =B8 -> 2.0227275 | C21: =B21-SUM(D21:G21) -> 0.32795257 | D21: =G8+M8+R8+AA8 -> 0.43025685 | E21: =N8+U8 -> -0.58656035 | F21: =Y8+Z8+AA8 -> 0.35107845 | G21: 1.5
A22: 2026 Q2 | B22: =B9 -> 0.063982591 | C22: =B22-SUM(D22:G22) -> -0.13658382 | D22: =G9+M9+R9+AA9 -> 0.35277852 | E22: =N9+U9 -> -0.4400719 | F22: =Y9+Z9+AA9 -> 0.28785979
A23: 2026 Q3 | B23: =B10 -> -0.091736921 | C23: =B23-SUM(D23:G23) -> -0.0029903041 | D23: =G10+M10+R10+AA10 -> 0.22985758 | E23: =N10+U10 -> -0.43614384 | F23: =Y10+Z10+AA10 -> 0.11753964
A24: 2026 Q4 | B24: =B11 -> -0.28654627 | C24: =B24-SUM(D24:G24) -> 0.052002375 | D24: =G11+M11+R11+AA11 -> 0.10309337 | E24: =N11+U11 -> -0.43639649 | F24: =Y11+Z11+AA11 -> -0.005245526
A25: 2027 Q1 | B25: =B12 -> -0.4501549 | C25: =B25-SUM(D25:G25) -> -0.09668508 | D25: =G12+M12+R12+AA12 -> 0.1355425 | E25: =N12+U12 -> -0.33727438 | F25: =Y12+Z12+AA12 -> -0.15173794
A26: 2027 Q2 | B26: =B13 -> -0.40695096 | C26: =B26-SUM(D26:G26) -> 0.054862288 | D26: =G13+M13+R13+AA13 -> 0.13343884 | E26: =N13+U13 -> -0.33458822 | F26: =Y13+Z13+AA13 -> -0.26066386

Sheet Readme
A1: This file presents data for the Hutchins Center Fiscal Impact Measure Breakdown.
A3: Table 1 breaks down the components of the FIM for the current quarter and our forecast for the next eight quarters. For purchases, it shows much is due to the One Big Beautiful Bill Act, to the government shutdown, and to underlying fiscal policy. For taxes and transfers, it shows how much is due to OBBBA, to tariffs, and to other factors.
A4: Table 2 decomposes FIM inputs into underlying factors (purchases and transfers), the effects of the One Big Beautiful Bill Act, the impacts of tariffs and uncertainty around them, effects of supply-side policies, and effects of the government shutdown that began on Oct. 1, 2025 for the current quarter and eight-quarter forecast.

Sheet Table 1
A1: Table 1: Breakdown of FIM by component
B2: Total | D2: Purchases | K2: Taxes Transfers and Subsidies (includes supply side and uncertainty effects) | M2: Taxes | R2: Transfers | V2: Uncertainty | X2: Supply Side
D3: Purchases Total | G3: Subcomponents of Federal Purchases | M3: Taxes Total | N3: Subcomponents of Taxes | R3: Transfers Total | S3: Subcomponents of Transfers | V3: Uncertainty Total | X3: Supply Side Total | Y3: Subcomponents of Supply Side
E4: Federal | F4: State and Local | G4: Federal Purchases OBBBA | H4: Federal Purchases, Government Shutdown | I4: Federal purchases Other | N4: Taxes OBBBA | O4: Tariffs | P4: Taxes Other | S4: Transfers OBBBA | T4: Transfers Other | V4: Tariff Uncertainty | Y4: Shutdown Spillovers | Z4: Student Loans | AA4: IRA/CHIPS | AB4: Supply Side Effects of OBBBA
A5: 2025 Q2 | B5: =D5+M5+R5+V5+X5 -> -0.59669312 | D5: -0.40608412 | E5: -0.49659071 | F5: 0.090506589 | G5: ='[1]OBBBA Effects'!Q12 -> 0 | H5: 0 | I5: =E5-G5-H5 -> -0.49659071 | K5: =M5+R5+V5+X5 -> -0.190609 | M5: -0.52308038 | N5: ='[1]OBBBA Effects'!AG12 -> 0 | O5: ='[1]Tariff Effects'!D10 -> -0.27793257 | P5: =M5-N5-O5 -> -0.24514781 | R5: 0.4690404 | S5: ='[1]OBBBA Effects'!AF12 -> 0 | T5: =R5-S5 -> 0.4690404 | V5: -0.3 | X5: =Y5+Z5+AA5+AB5 -> 0.16343098 | Y5: 0 | Z5: -0.023738219 | AA5: 0.1871692 | AB5: 0
A6: 2025 Q3 | B6: =D6+M6+R6+V6+X6 -> -0.041287946 | D6: -0.18712218 | E6: 0.0018353324 | F6: -0.18895751 | G6: ='[1]OBBBA Effects'!Q13 -> 0.2585594 | H6: 0 | I6: =E6-G6-H6 -> -0.25672407 | K6: =M6+R6+V6+X6 -> 0.14583423 | M6: -0.00050183295 | N6: ='[1]OBBBA Effects'!AG13 -> 0.36878075 | O6: ='[1]Tariff Effects'!D11 -> -0.40944271 | P6: =M6-N6-O6 -> 0.040160127 | R6: 0.36314224 | S6: ='[1]OBBBA Effects'!AF13 -> -0.029737507 | T6: =R6-S6 -> 0.39287975 | V6: -0.3 | X6: =Y6+Z6+AA6+AB6 -> 0.08319382 | Y6: 0 | Z6: -0.029638323 | AA6: 0.11283214 | AB6: 0
A7: 2025 Q4 | B7: =D7+M7+R7+V7+X7 -> -1.350893 | D7: -0.59616522 | E7: -0.40818665 | F7: -0.18797857 | G7: ='[1]OBBBA Effects'!Q14 -> 0.13072231 | H7: -0.6 | I7: =E7-G7-H7 -> 0.06109104 | K7: =M7+R7+V7+X7 -> -0.75472778 | M7: -0.094973042 | N7: ='[1]OBBBA Effects'!AG14 -> 0.24653238 | O7: ='[1]Tariff Effects'!D12 -> -0.35894856 | P7: =M7-N7-O7 -> 0.017443133 | R7: 0.42444101 | S7: ='[1]OBBBA Effects'!AF14 -> -0.048516192 | T7: =R7-S7 -> 0.4729572 | V7: -0.3 | X7: =Y7+Z7+AA7+AB7 -> -0.78419574 | Y7: -0.9 | Z7: -0.024548492 | AA7: 0.14035275 | AB7: 0
A8: 2026 Q1 | B8: =D8+M8+R8+V8+X8 -> 2.0227275 | D8: 0.70673922 | E8: 0.89353249 | F8: -0.18679327 | G8: ='[1]OBBBA Effects'!Q15 -> 0.22274524 | H8: 0.6 | I8: =E8-G8-H8 -> 0.070787245 | K8: =M8+R8+V8+X8 -> 1.3159883 | M8: -0.092600531 | N8: ='[1]OBBBA Effects'!AG15 -> 0.56778603 | O8: ='[1]Tariff Effects'!D13 -> -0.28507785 | P8: =M8-N8-O8 -> -0.37530871 | R8: 0.45751038 | S8: ='[1]OBBBA Effects'!AF15 -> -0.045972446 | T8: =R8-S8 -> 0.50348282 | V8: -0.3 | X8: =Y8+Z8+AA8+AB8 -> 1.2510785 | Y8: 0.9 | Z8: -0.022803876 | AA8: 0.31388233 | AB8: 0.06
A9: 2026 Q2 | B9: =D9+M9+R9+V9+X9 -> 0.063982591 | D9: -0.17282167 | E9: 0.025063031 | F9: -0.1978847 | G9: ='[1]OBBBA Effects'!Q16 -> 0.12541077 | H9: 0 | I9: =E9-G9-H9 -> -0.10034774 | K9: =M9+R9+V9+X9 -> 0.23680426 | M9: -0.04017705 | N9: ='[1]OBBBA Effects'!AG16 -> 0.55911197 | O9: ='[1]Tariff Effects'!D14 -> -0.23733049 | P9: =M9-N9-O9 -> -0.36195852 | R9: 0.18912152 | S9: ='[1]OBBBA Effects'!AF16 -> -0.04373337 | T9: =R9-S9 -> 0.23285489 | V9: -0.2 | X9: =Y9+Z9+AA9+AB9 -> 0.28785979 | Y9: 0 | Z9: -0.020976971 | AA9: 0.24883676 | AB9: 0.06
A10: 2026 Q3 | B10: =D10+M10+R10+V10+X10 -> -0.091736921 | D10: -0.22708998 | E10: -0.039419277 | F10: -0.1876707 | G10: ='[1]OBBBA Effects'!Q17 -> 0.0700293 | H10: 0 | I10: =E10-G10-H10 -> -0.10944858 | K10: =M10+R10+V10+X10 -> 0.13535306 | M10: -0.021466797 | N10: ='[1]OBBBA Effects'!AG17 -> 0.34286665 | O10: ='[1]Tariff Effects'!D15 -> -0.23316634 | P10: =M10-N10-O10 -> -0.13116711 | R10: 0.23928021 | S10: ='[1]OBBBA Effects'!AF17 -> -0.034118874 | T10: =R10-S10 -> 0.27339909 | V10: -0.2 | X10: =Y10+Z10+AA10+AB10 -> 0.11753964 | Y10: 0 | Z10: -0.019015005 | AA10: 0.076554649 | AB10: 0.06
A11: 2026 Q4 | B11: =D11+M11+R11+V11+X11 -> -0.28654627 | D11: -0.33323664 | E11: -0.13475427 | F11: -0.19848237 | G11: ='[1]OBBBA Effects'!Q18 -> -0.0064345259 | H11: 0 | I11: =E11-G11-H11 -> -0.12831974 | K11: =M11+R11+V11+X11 -> 0.046690367 | M11: 0.019304294 | N11: ='[1]OBBBA Effects'!AG18 -> 0.33784149 | O11: ='[1]Tariff Effects'!D16 -> -0.23056212 | P11: =M11-N11-O11 -> -0.087975079 | R11: 0.2326316 | S11: ='[1]OBBBA Effects'!AF18 -> -0.081669333 | T11: =R11-S11 -> 0.31430093 | V11: -0.2 | X11: =Y11+Z11+AA11+AB11 -> -0.005245526 | Y11: 0 | Z11: -0.012025896 | AA11: -0.05321963 | AB11: 0.06
A12: 2027 Q1 | B12: =D12+M12+R12+V12+X12 -> -0.4501549 | D12: -0.26678026 | E12: -0.064067477 | F12: -0.20271278 | G12: ='[1]OBBBA Effects'!Q19 -> -0.0086757821 | H12: 0 | I12: =E12-G12-H12 -> -0.055391695 | K12: =M12+R12+V12+X12 -> -0.18337463 | M12: -0.09128723 | N12: ='[1]OBBBA Effects'!AG19 -> 0.45231205 | O12: ='[1]Tariff Effects'!D17 -> -0.22860908 | P12: =M12-N12-O12 -> -0.31499021 | R12: 0.22796144 | S12: ='[1]OBBBA Effects'!AF19 -> -0.081020765 | T12: =R12-S12 -> 0.30898221 | V12: -0.1 | X12: =Y12+Z12+AA12+AB12 -> -0.22004885 | Y12: 0 | Z12: -0.01149048 | AA12: -0.26855837 | AB12: 0.06
A13: 2027 Q2 | B13: =D13+M13+R13+V13+X13 -> -0.40695096 | D13: -0.30191172 | E13: -0.11072717 | F13: -0.19118456 | G13: ='[1]OBBBA Effects'!Q20 -> -0.008470458 | H13: 0 | I13: =E13-G13-H13 -> -0.10225671 | K13: =M13+R13+V13+X13 -> -0.10503923 | M13: 0.087458255 | N13: ='[1]OBBBA Effects'!AG20 -> 0.44288484 | O13: ='[1]Tariff Effects'!D18 -> -0.098285195 | P13: =M13-N13-O13 -> -0.25714139 | R13: 0.22224467 | S13: ='[1]OBBBA Effects'!AF20 -> -0.078572555 | T13: =R13-S13 -> 0.30081723 | V13: -0.1 | X13: =Y13+Z13+AA13+AB13 -> -0.31474216 | Y13: 0 | Z13: -0.0095126456 | AA13: -0.36522952 | AB13: 0.06

Sheet Table 2
A1: Table 2: Decomposing FIM into effects of OBBBA, other supply side effects, tariffs and tariff uncertainty, and underlying FIM
D2: Components of the Underlying FIM
B3: Total | C3: Underlying FIM | D3: Underlying FIM Purchases | E3: Underlying FIM Net Transfers | F3: OBBBA | G3: Tariffs and Uncertainty | H3: IRA, CHIPS and Student Loans | I3: Government shutdown
A4: 2025 Q2 | B4: =C4+SUM(F4:I4) -> -0.59669312 | C4: =D4+E4 -> -0.18219153 | D4: ='Table 1'!F5+'Table 1'!I5 -> -0.40608412 | E4: ='Table 1'!P5+'Table 1'!T5 -> 0.22389259 | F4: ='Table 1'!G5+'Table 1'!N5+'Table 1'!S5+'Table 1'!AB5 -> 0 | G4: ='Table 1'!O5+'Table 1'!V5 -> -0.57793257 | H4: ='Table 1'!Z5+'Table 1'!AA5 -> 0.16343098 | I4: ='Table 1'!H5+'Table 1'!Y5 -> 0
A5: 2025 Q3 | B5: =C5+SUM(F5:I5) -> -0.041287946 | C5: =D5+E5 -> -0.012641704 | D5: ='Table 1'!F6+'Table 1'!I6 -> -0.44568158 | E5: ='Table 1'!P6+'Table 1'!T6 -> 0.43303988 | F5: ='Table 1'!G6+'Table 1'!N6+'Table 1'!S6+'Table 1'!AB6 -> 0.59760265 | G5: ='Table 1'!O6+'Table 1'!V6 -> -0.70944271 | H5: ='Table 1'!Z6+'Table 1'!AA6 -> 0.08319382 | I5: ='Table 1'!H6+'Table 1'!Y6 -> 0
A6: 2025 Q4 | B6: =C6+SUM(F6:I6) -> -1.350893 | C6: =D6+E6 -> 0.3635128 | D6: ='Table 1'!F7+'Table 1'!I7 -> -0.12688753 | E6: ='Table 1'!P7+'Table 1'!T7 -> 0.49040033 | F6: ='Table 1'!G7+'Table 1'!N7+'Table 1'!S7+'Table 1'!AB7 -> 0.3287385 | G6: ='Table 1'!O7+'Table 1'!V7 -> -0.65894856 | H6: ='Table 1'!Z7+'Table 1'!AA7 -> 0.11580426 | I6: ='Table 1'!H7+'Table 1'!Y7 -> -1.5
A7: 2026 Q1 | B7: =C7+SUM(F7:I7) -> 2.0227275 | C7: =D7+E7 -> 0.012168094 | D7: ='Table 1'!F8+'Table 1'!I8 -> -0.11600602 | E7: ='Table 1'!P8+'Table 1'!T8 -> 0.12817412 | F7: ='Table 1'!G8+'Table 1'!N8+'Table 1'!S8+'Table 1'!AB8 -> 0.80455883 | G7: ='Table 1'!O8+'Table 1'!V8 -> -0.58507785 | H7: ='Table 1'!Z8+'Table 1'!AA8 -> 0.29107845 | I7: ='Table 1'!H8+'Table 1'!Y8 -> 1.5
A8: 2026 Q2 | B8: =C8+SUM(F8:I8) -> 0.063982591 | C8: =D8+E8 -> -0.42733607 | D8: ='Table 1'!F9+'Table 1'!I9 -> -0.29823244 | E8: ='Table 1'!P9+'Table 1'!T9 -> -0.12910363 | F8: ='Table 1'!G9+'Table 1'!N9+'Table 1'!S9+'Table 1'!AB9 -> 0.70078937 | G8: ='Table 1'!O9+'Table 1'!V9 -> -0.43733049 | H8: ='Table 1'!Z9+'Table 1'!AA9 -> 0.22785979 | I8: ='Table 1'!H9+'Table 1'!Y9 -> 0
A9: 2026 Q3 | B9: =C9+SUM(F9:I9) -> -0.091736921 | C9: =D9+E9 -> -0.15488731 | D9: ='Table 1'!F10+'Table 1'!I10 -> -0.29711928 | E9: ='Table 1'!P10+'Table 1'!T10 -> 0.14223198 | F9: ='Table 1'!G10+'Table 1'!N10+'Table 1'!S10+'Table 1'!AB10 -> 0.43877708 | G9: ='Table 1'!O10+'Table 1'!V10 -> -0.43316634 | H9: ='Table 1'!Z10+'Table 1'!AA10 -> 0.057539643 | I9: ='Table 1'!H10+'Table 1'!Y10 -> 0
A10: 2026 Q4 | B10: =C10+SUM(F10:I10) -> -0.28654627 | C10: =D10+E10 -> -0.10047626 | D10: ='Table 1'!F11+'Table 1'!I11 -> -0.32680211 | E10: ='Table 1'!P11+'Table 1'!T11 -> 0.22632585 | F10: ='Table 1'!G11+'Table 1'!N11+'Table 1'!S11+'Table 1'!AB11 -> 0.30973763 | G10: ='Table 1'!O11+'Table 1'!V11 -> -0.43056212 | H10: ='Table 1'!Z11+'Table 1'!AA11 -> -0.065245526 | I10: ='Table 1'!H11+'Table 1'!Y11 -> 0
A11: 2027 Q1 | B11: =C11+SUM(F11:I11) -> -0.4501549 | C11: =D11+E11 -> -0.26411248 | D11: ='Table 1'!F12+'Table 1'!I12 -> -0.25810448 | E11: ='Table 1'!P12+'Table 1'!T12 -> -0.0060079974 | F11: ='Table 1'!G12+'Table 1'!N12+'Table 1'!S12+'Table 1'!AB12 -> 0.4226155 | G11: ='Table 1'!O12+'Table 1'!V12 -> -0.32860908 | H11: ='Table 1'!Z12+'Table 1'!AA12 -> -0.28004885 | I11: ='Table 1'!H12+'Table 1'!Y12 -> 0
A12: 2027 Q2 | B12: =C12+SUM(F12:I12) -> -0.40695096 | C12: =D12+E12 -> -0.24976543 | D12: ='Table 1'!F13+'Table 1'!I13 -> -0.29344126 | E12: ='Table 1'!P13+'Table 1'!T13 -> 0.043675839 | F12: ='Table 1'!G13+'Table 1'!N13+'Table 1'!S13+'Table 1'!AB13 -> 0.41584183 | G12: ='Table 1'!O13+'Table 1'!V13 -> -0.1982852 | H12: ='Table 1'!Z13+'Table 1'!AA13 -> -0.37474216 | I12: ='Table 1'!H13+'Table 1'!Y13 -> 0

Sheet effects of obbba
D1: federal_non_corporate_taxes | H1: federal_corporate_taxes | L1: federal_health_outlays | P1: state_health_outlays | T1: federal_student_loans | X1: federal_purchases | AB1: federal_social_benefits
D2: Federal Noncorporate Taxes | H2: Federal Corporate Taxes | L2: Medicaid | P2: Medicaid | T2: Student Loans | X2: Federal Purchases | AB2: Social Benefits
A3: date | B3: Total Effect | D3: With OBBBA | E3: Without OBBBA | F3: Effect | H3: With OBBBA | I3: Without OBBBA | J3: Effect | L3: With OBBBA | M3: Without OBBBA | N3: Effect | P3: With OBBBA | Q3: Without OBBBA | R3: Effect | T3: With OBBBA | U3: Without OBBBA | V3: Effect | X3: With OBBBA | Y3: Without OBBBA | Z3: Effect | AB3: With OBBBA | AC3: Without OBBBA | AD3: Effect
A4: 2023 Q2 | B4: =F4+J4+N4+R4+V4+Z4+AD4 -> 0 | D4: 0.40168307 | E4: 0.40168307 | F4: =D4-E4 -> 0 | H4: -0.082194087 | I4: -0.082194087 | J4: =H4-I4 -> 0 | L4: 0.17103649 | M4: 0.17103649 | N4: =L4-M4 -> 0 | P4: 0.10677014 | Q4: 0.10677014 | R4: =P4-Q4 -> 0 | T4: -0.0080992849 | U4: -0.0080992849 | V4: =T4-U4 -> 0 | X4: -0.14802611 | Y4: -0.14802611 | Z4: =X4-Y4 -> 0 | AB4: -0.11030549 | AC4: -0.11030549 | AD4: =AB4-AC4 -> 0
A5: 2023 Q3 | B5: =F5+J5+N5+R5+V5+Z5+AD5 -> 0 | D5: 0.11335746 | E5: 0.11335746 | F5: =D5-E5 -> 0 | H5: -0.05915321 | I5: -0.05915321 | J5: =H5-I5 -> 0 | L5: -0.080930365 | M5: -0.080930365 | N5: =L5-M5 -> 0 | P5: 0.24636772 | Q5: 0.24636772 | R5: =P5-Q5 -> 0 | T5: -0.13797271 | U5: -0.13797271 | V5: =T5-U5 -> 0 | X5: 0.29138773 | Y5: 0.29138773 | Z5: =X5-Y5 -> 0 | AB5: -0.035337896 | AC5: -0.035337896 | AD5: =AB5-AC5 -> 0
A6: 2023 Q4 | B6: =F6+J6+N6+R6+V6+Z6+AD6 -> 0 | D6: 0.084390722 | E6: 0.084390722 | F6: =D6-E6 -> 0 | H6: -0.071699906 | I6: -0.071699906 | J6: =H6-I6 -> 0 | L6: 0.057480661 | M6: 0.057480661 | N6: =L6-M6 -> 0 | P6: 0.073497893 | Q6: 0.073497893 | R6: =P6-Q6 -> 0 | T6: -0.11266828 | U6: -0.11266828 | V6: =T6-U6 -> 0 | X6: 0.070409519 | Y6: 0.070409519 | Z6: =X6-Y6 -> 0 | AB6: -0.20119765 | AC6: -0.20119765 | AD6: =AB6-AC6 -> 0
A7: 2024 Q1 | B7: =F7+J7+N7+R7+V7+Z7+AD7 -> 0 | D7: 0.49002857 | E7: 0.49002857 | F7: =D7-E7 -> 0 | H7: -0.060391934 | I7: -0.060391934 | J7: =H7-I7 -> 0 | L7: -0.13918165 | M7: -0.13918165 | N7: =L7-M7 -> 0 | P7: 0.13055532 | Q7: 0.13055532 | R7: =P7-Q7 -> 0 | T7: -0.10447089 | U7: -0.10447089 | V7: =T7-U7 -> 0 | X7: -0.095656905 | Y7: -0.095656905 | Z7: =X7-Y7 -> 0 | AB7: -0.015431334 | AC7: -0.015431334 | AD7: =AB7-AC7 -> 0
A8: 2024 Q2 | B8: =F8+J8+N8+R8+V8+Z8+AD8 -> 0 | D8: 0.35063464 | E8: 0.35063464 | F8: =D8-E8 -> 0 | H8: -0.046919377 | I8: -0.046919377 | J8: =H8-I8 -> 0 | L8: -0.10798661 | M8: -0.10798661 | N8: =L8-M8 -> 0 | P8: 0.1126516 | Q8: 0.1126516 | R8: =P8-Q8 -> 0 | T8: -0.096103418 | U8: -0.096103418 | V8: =T8-U8 -> 0 | X8: 0.12347864 | Y8: 0.12347864 | Z8: =X8-Y8 -> 0 | AB8: 0.17944505 | AC8: 0.17944505 | AD8: =AB8-AC8 -> 0
A9: 2024 Q3 | B9: =F9+J9+N9+R9+V9+Z9+AD9 -> 0 | D9: 0.26769889 | E9: 0.26769889 | F9: =D9-E9 -> 0 | H9: -0.043703024 | I9: -0.043703024 | J9: =H9-I9 -> 0 | L9: 0.20674712 | M9: 0.20674712 | N9: =L9-M9 -> 0 | P9: 0.044619557 | Q9: 0.044619557 | R9: =P9-Q9 -> 0 | T9: -0.055729673 | U9: -0.055729673 | V9: =T9-U9 -> 0 | X9: 0.4065057 | Y9: 0.4065057 | Z9: =X9-Y9 -> 0 | AB9: 0.26285186 | AC9: 0.26285186 | AD9: =AB9-AC9 -> 0
A10: 2024 Q4 | B10: =F10+J10+N10+R10+V10+Z10+AD10 -> 0 | D10: 0.26578106 | E10: 0.26578106 | F10: =D10-E10 -> 0 | H10: -0.034339266 | I10: -0.034339266 | J10: =H10-I10 -> 0 | L10: 0.14998116 | M10: 0.14998116 | N10: =L10-M10 -> 0 | P10: 0.15091666 | Q10: 0.15091666 | R10: =P10-Q10 -> 0 | T10: -0.030672088 | U10: -0.030672088 | V10: =T10-U10 -> 0 | X10: 0.13387378 | Y10: 0.13387378 | Z10: =X10-Y10 -> 0 | AB10: 0.27225397 | AC10: 0.27225397 | AD10: =AB10-AC10 -> 0
A11: 2025 Q1 | B11: =F11+J11+N11+R11+V11+Z11+AD11 -> 0 | D11: -0.068923508 | E11: -0.068923508 | F11: =D11-E11 -> 0 | H11: -0.0042648201 | I11: -0.0042648201 | J11: =H11-I11 -> 0 | L11: 0.10399977 | M11: 0.10399977 | N11: =L11-M11 -> 0 | P11: 0.002612607 | Q11: 0.002612607 | R11: =P11-Q11 -> 0 | T11: -0.030099483 | U11: -0.030099483 | V11: =T11-U11 -> 0 | X11: -0.51945344 | Y11: -0.51945344 | Z11: =X11-Y11 -> 0 | AB11: 0.18178302 | AC11: 0.18178302 | AD11: =AB11-AC11 -> 0
A12: 2025 Q2 | B12: =F12+J12+N12+R12+V12+Z12+AD12 -> 0 | D12: -0.49360352 | E12: -0.49360352 | F12: =D12-E12 -> 0 | H12: 0.0070579944 | I12: 0.0070579944 | J12: =H12-I12 -> 0 | L12: 0.28501646 | M12: 0.28501646 | N12: =L12-M12 -> 0 | P12: -0.029952741 | Q12: -0.029952741 | R12: =P12-Q12 -> 0 | T12: -0.023738219 | U12: -0.023738219 | V12: =T12-U12 -> 0 | X12: -0.49659071 | Y12: -0.49659071 | Z12: =X12-Y12 -> 0 | AB12: 0.46724311 | AC12: 0.46724311 | AD12: =AB12-AC12 -> 0
A13: 2025 Q3 | B13: =F13+J13+N13+R13+V13+Z13+AD13 -> 0.59760265 | D13: -0.22561765 | E13: -0.41438163 | F13: =D13-E13 -> 0.18876398 | H13: 0.18570532 | I13: 0.0056885468 | J13: =H13-I13 -> 0.18001677 | L13: 0.22450059 | M13: 0.22450059 | N13: =L13-M13 -> 0 | P13: 0.0019343238 | Q13: 0.0019343238 | R13: =P13-Q13 -> 0 | T13: -0.029638323 | U13: 9.9183753e-05 | V13: =T13-U13 -> -0.029737507 | X13: 0.0018353324 | Y13: -0.25672407 | Z13: =X13-Y13 -> 0.2585594 | AB13: 0.26976939 | AC13: 0.26976939 | AD13: =AB13-AC13 -> 0
A14: 2025 Q4 | B14: =F14+J14+N14+R14+V14+Z14+AD14 -> 0.3287385 | D14: -0.18376482 | E14: -0.36899444 | F14: =D14-E14 -> 0.18522961 | H14: 0.065942043 | I14: 0.0046392729 | J14: =H14-I14 -> 0.06130277 | L14: 0.2294708 | M14: 0.2294708 | N14: =L14-M14 -> 0 | P14: 0.020152618 | Q14: 0.020152618 | R14: =P14-Q14 -> 0 | T14: -0.024548492 | U14: 8.8049723e-05 | V14: =T14-U14 -> -0.024636542 | X14: -0.40818665 | Y14: -0.53890896 | Z14: =X14-Y14 -> 0.13072231 | AB14: 0.21821118 | AC14: 0.24209083 | AD14: =AB14-AC14 -> -0.02387965
A15: 2026 Q1 | B15: =F15+J15+N15+R15+V15+Z15+AD15 -> 0.74455883 | D15: -0.15788909 | E15: -0.66605165 | F15: =D15-E15 -> 0.50816256 | H15: 0.063538308 | I15: 0.0039148396 | J15: =H15-I15 -> 0.059623468 | L15: 0.27300491 | M15: 0.27300491 | N15: =L15-M15 -> 0 | P15: 0.029331705 | Q15: 0.029331705 | R15: =P15-Q15 -> 0 | T15: -0.022803876 | U15: -0.00017145975 | V15: =T15-U15 -> -0.022632416 | X15: 0.89353249 | Y15: 0.67078724 | Z15: =X15-Y15 -> 0.22274524 | AB15: 0.15031915 | AC15: 0.17365918 | AD15: =AB15-AC15 -> -0.02334003
... A20: 2027 Q2 | B20: =F20+J20+N20+R20+V20+Z20+AD20 -> 0.35597027 | D20: -0.02983676 | E20: -0.42474115 | F20: =D20-E20 -> 0.39490438 | H20: 0.088515383 | I20: 0.040534928 | J20: =H20-I20 -> 0.047980456 | L20: 0.089169656 | M20: 0.12453101 | N20: =L20-M20 -> -0.035361355 | P20: 0.0013236714 | Q20: 0.018504011 | R20: =P20-Q20 -> -0.017180339 | T20: -0.0095126456 | U20: -0.0052365158 | V20: =T20-U20 -> -0.0042761298 | X20: -0.11072717 | Y20: -0.10225671 | Z20: =X20-Y20 -> -0.008470458 | AB20: 0.12270905 | AC20: 0.14433534 | AD20: =AB20-AC20 -> -0.021626288
