Workbook

Sheet no tariffs
A1: date | B1: id | C1: recession | D1: federal_purchases_contribution | E1: state_purchases_contribution | F1: federal_non_corporate_taxes_contribution | G1: state_non_corporate_taxes_contribution | H1: federal_corporate_taxes_contribution | I1: supply_side_ira_contribution | J1: state_corporate_taxes_contribution | K1: federal_social_benefits_contribution | L1: state_social_benefits_contribution | M1: rebate_checks_contribution | N1: rebate_checks_arp_contribution | O1: federal_ui_contribution | P1: state_ui_contribution | Q1: federal_subsidies_contribution | R1: federal_aid_to_small_businesses_arp_contribution | S1: federal_other_direct_aid_arp_contribution | T1: federal_other_vulnerable_arp_contribution | U1: federal_student_loans_contribution | V1: state_subsidies_contribution | W1: federal_health_outlays_contribution | X1: state_health_outlays_contribution | Y1: federal_contribution | Z1: state_contribution | AA1: taxes_contribution | AB1: transfers_contribution | AC1: consumption_contribution | AD1: fiscal_impact_measure | AE1: fiscal_impact_4q_ma
A2: 2023 Q2 | B2: historical | C2: -1 | D2: -0.14802611 | E2: 0.32935984 | F2: 0.40168307 | G2: 0.18603735 | H2: -0.082194087 | I2: 0.23535829 | J2: -0.041113772 | K2: -0.11030549 | L2: -0.039292217 | M2: -0.25081207 | N2: -0.42408041 | O2: -0.28390642 | P2: 0.020948001 | Q2: -0.36373095 | R2: 0.00050505984 | S2: -0.041864783 | T2: -0.096126642 | U2: -0.0080992849 | V2: -0.0008915333 | W2: 0.17103649 | X2: 0.10677014 | Y2: -0.23313551 | Z2: 0.41446924 | AA2: 0.69855453 | AB2: -1.3262928 | AC2: -0.61796281 | AD2: -0.43662908 | AE2: -0.83627525
A3: 2023 Q3 | B3: historical | C3: -1 | D3: 0.29138773 | E3: 0.20751042 | F3: 0.11335746 | G3: 0.097716049 | H3: -0.05915321 | I3: 0.2310278 | J3: -0.033405652 | K3: -0.035337896 | L3: -0.097526156 | M3: -0.033451247 | N3: -0.0077388778 | O3: -0.13051737 | P3: 0.044718453 | Q3: -0.37795185 | R3: 0.00059502736 | S3: -0.026783451 | T3: -0.096213711 | U3: -0.13797271 | V3: -6.5844159e-05 | W3: -0.080930365 | X3: 0.24636772 | Y3: -0.13834318 | Z3: 0.63724132 | AA3: 0.34932404 | AB3: -0.7341966 | AC3: -0.38219864 | AD3: 0.11669951 | AE3: -0.20616336
A4: 2023 Q4 | B4: historical | C4: -1 | D4: 0.070409519 | E4: 0.33456315 | F4: 0.084390722 | G4: 0.052044238 | H4: -0.071699906 | I4: 0.082750407 | J4: -0.037624014 | K4: -0.20119765 | L4: -0.25248893 | M4: 0 | N4: -0.0062254866 | O4: -0.0074273919 | P4: 0.025176577 | Q4: -0.16467395 | R4: -0.0057101381 | S4: -0.026574551 | T4: -0.096631639 | U4: -0.11266828 | V4: -4.6437541e-05 | W4: 0.057480661 | X4: 0.073497893 | Y4: 0.28189704 | Z4: 0.12307563 | AA4: 0.10992045 | AB4: -0.71934748 | AC4: -0.60859101 | AD4: -0.20361835 | AE4: -0.15496259
A5: 2024 Q1 | B5: historical | C5: -1 | D5: -0.095656905 | E5: 0.096940856 | F5: 0.49002857 | G5: 0.20839114 | H5: -0.060391934 | I5: 0.12732301 | J5: -0.031435769 | K5: -0.015431334 | L5: -0.024236115 | M5: 0 | N5: -0.11167712 | O5: -0.0014130479 | P5: 0.014852718 | Q5: -0.1478768 | R5: -0.0065334558 | S5: -0.037491898 | T5: -0.063307767 | U5: -0.10447089 | V5: -0.0005835965 | W5: -0.13918165 | X5: 0.13055532 | Y5: -0.14198756 | Z5: 0.14327151 | AA5: 0.73267848 | AB5: -0.50768404 | AC5: 0.2289171 | AD5: 0.23020105 | AE5: -0.073336716
A6: 2024 Q2 | B6: historical | C6: -1 | D6: 0.12347864 | E6: 0.051398583 | F6: 0.35063464 | G6: 0.18132833 | H6: -0.046919377 | I6: 0.094528727 | J6: -0.022967964 | K6: 0.17944505 | L6: 0.020341749 | M6: 0 | N6: -0.104668 | O6: -0.00067198841 | P6: 0.01260551 | Q6: -0.34619776 | R6: -0.016772232 | S6: -0.035908571 | T6: -0.050238211 | U6: -0.096103418 | V6: -0.0021619606 | W6: -0.10798661 | X6: 0.1126516 | Y6: 0.19183196 | Z6: -0.016954735 | AA6: 0.55586415 | AB6: -0.43560311 | AC6: 0.12277732 | AD6: 0.29765454 | AE6: 0.11023419
A7: 2024 Q3 | B7: historical | C7: -1 | D7: 0.4065057 | E7: 0.1366917 | F7: 0.26769889 | G7: 0.02149772 | H7: -0.043703024 | I7: -0.0953656 | J7: -0.012505799 | K7: 0.26285186 | L7: 0.049653198 | M7: 0 | N7: -0.10040558 | O7: -0.00033408507 | P7: 0.010455964 | Q7: -0.30976776 | R7: -0.06669009 | S7: -0.034038326 | T7: -0.043936535 | U7: -0.055729673 | V7: -4.4268525e-05 | W7: 0.20674712 | X7: 0.044619557 | Y7: 0.63577579 | Z7: -0.092578392 | AA7: 0.1379591 | AB7: -0.035405605 | AC7: 0.10260463 | AD7: 0.64580203 | AE7: 0.24250982
A8: 2024 Q4 | B8: historical | C8: -1 | D8: 0.13387378 | E8: 0.040840032 | F8: 0.26578106 | G8: 0.029094859 | H8: -0.034339266 | I8: -0.13372901 | J8: 0.01136901 | K8: 0.27225397 | L8: 0.016960521 | M8: 0 | N8: -0.10036427 | O8: -0.0001725724 | P8: 0.0057762572 | Q8: -0.15458604 | R8: -0.029046972 | S8: -0.022294995 | T8: -0.026522516 | U8: -0.030672088 | V8: -5.5553434e-05 | W8: 0.14998116 | X8: 0.15091666 | Y8: 0.15254838 | Z8: 0.022165438 | AA8: 0.13854798 | AB8: 0.23270567 | AC8: 0.370919 | AD8: 0.54563281 | AE8: 0.42982261
A9: 2025 Q1 | B9: historical | C9: -1 | D9: -0.51945344 | E9: -0.036329069 | F9: -0.068923508 | G9: 0.045824279 | H9: -0.0042648201 | I9: 0.0248513 | J9: 0.013575618 | K9: 0.18178302 | L9: -0.0089342835 | M9: 0 | N9: -0.096865949 | O9: 0 | P9: 0.00044613388 | Q9: -0.073745276 | R9: -0.028114584 | S9: -0.014963859 | T9: -0.010608242 | U9: -0.030099483 | V9: -0.00030217362 | W9: 0.10399977 | X9: 0.002612607 | Y9: -1.1699513 | Z9: 0.61416882 | AA9: 0.011102717 | AB9: 0.025525593 | AC9: 0.036625317 | AD9: -0.51915719 | AE9: 0.24248305
A10: 2025 Q2 | B10: historical | C10: -1 | D10: -0.49659071 | E10: 0.090506589 | F10: -0.49360352 | G10: -0.039331912 | H10: 0.0070579944 | I10: 0.1871692 | J10: 0.0019233388 | K10: 0.46724311 | L10: -0.014502786 | M10: 0 | N10: -0.094949895 | O10: 0 | P10: 0.0018247774 | Q10: -0.094999199 | R10: -0.02673731 | S10: -0.013483429 | T10: -0.010020828 | U10: -0.023738219 | V10: -0.0010380446 | W10: 0.28501646 | X10: -0.029952741 | Y10: -0.94596317 | Z10: 0.53987905 | AA10: -0.33591118 | AB10: 0.44530218 | AC10: 0.11095811 | AD10: -0.29512601 | AE10: 0.094287909
A11: 2025 Q3 | B11: projection | C11: 0 | D11: 0.1631113 | E11: -0.18895751 | F11: 0.19077242 | G11: 0.031964415 | H11: 0.18570532 | I11: 0.18199766 | J11: 0.0069886574 | K11: 0.23748379 | L11: -0.00024409454 | M11: 0 | N11: -0.00099896094 | O11: 0 | P11: -0.0083673707 | Q11: -0.074626504 | R11: -0.026048206 | S11: -0.013810384 | T11: -0.0085423386 | U11: -0.029638323 | V11: -0.00052655433 | W11: 0.22450059 | X11: 0.0019343238 | Y11: 0.11078208 | Z11: -0.13662829 | AA11: 0.59609715 | AB11: 0.30124016 | AC11: 0.89543584 | AD11: 0.86958962 | AE11: 0.15023481
A12: 2025 Q4 | B12: projection | C12: 0 | D12: 0.051277427 | E12: -0.18797857 | F12: 0.3159054 | G12: 0.012855036 | H12: 0.065942043 | I12: 0.071097532 | J12: 0.0096981954 | K12: 0.15390503 | L12: 0.026815537 | M12: 0 | N12: -0.00097192311 | O12: 0 | P12: -0.0077753446 | Q12: -0.036283497 | R12: -0.0039026384 | S12: -0.012854849 | T12: -0.0076754748 | U12: -0.024548492 | V12: -0.00044546802 | W12: 0.2294708 | X12: 0.020152618 | Y12: -0.053072004 | Z12: -0.083629139 | AA12: 0.47488034 | AB12: 0.33571051 | AC12: 0.80889993 | AD12: 0.67219878 | AE12: 0.1818763
A13: 2026 Q1 | B13: projection | C13: 0 | D13: 0.29588505 | E13: -0.18679327 | F13: 0.1308187 | G13: -0.005175253 | H13: 0.063538308 | I13: 0.31388233 | J13: 0.0065070205 | K13: 0.054248823 | L13: 0.040643938 | M13: 0 | N13: -0.00094783566 | O13: 0 | P13: -0.0071485208 | Q13: -0.0028042467 | R13: -0.0026676745 | S13: -0.014294821 | T13: -0.0070418372 | U13: -0.022803876 | V13: -0.00041144841 | W13: 0.27300491 | X13: 0.029331705 | Y13: 0.24418567 | Z13: -0.13509389 | AA13: 0.50882703 | AB13: 0.33892734 | AC13: 0.84591824 | AD13: 0.95501002 | AE13: 0.5504181
... A18: 2027 Q2 | B18: projection | C18: 0 | D18: -0.11072717 | E18: -0.19118456 | F18: 0.2044739 | G18: 0.023800283 | H18: 0.088515383 | I18: -0.31115122 | J18: 0.004630489 | K18: -0.0078064572 | L18: 0.010613895 | M18: 0 | N18: 0 | O18: 0 | P18: -0.00081672553 | Q18: 0.0025172322 | R18: -0.00028515852 | S18: -0.0010320556 | T18: -0.0015233461 | U18: -0.0095126456 | V18: -0.00031358356 | W18: 0.089169656 | X18: 0.0013236714 | Y18: -0.15456652 | Z18: -0.1473452 | AA18: 0.01105251 | AB18: 0.082342218 | AC18: 0.093385006 | AD18: -0.20852672 | AE18: -0.081462928

Sheet Sheet3

Sheet Sheet1
A1: date | B1: id | C1: recession | D1: federal_purchases_contribution | E1: state_purchases_contribution | F1: federal_non_corporate_taxes_contribution | G1: state_non_corporate_taxes_contribution | H1: federal_corporate_taxes_contribution | I1: supply_side_ira_contribution | J1: state_corporate_taxes_contribution | K1: federal_social_benefits_contribution | L1: state_social_benefits_contribution | M1: rebate_checks_contribution | N1: rebate_checks_arp_contribution | O1: federal_ui_contribution | P1: state_ui_contribution | Q1: federal_subsidies_contribution | R1: federal_aid_to_small_businesses_arp_contribution | S1: federal_other_direct_aid_arp_contribution | T1: federal_other_vulnerable_arp_contribution | U1: federal_student_loans_contribution | V1: state_subsidies_contribution | W1: federal_health_outlays_contribution | X1: state_health_outlays_contribution | Y1: federal_contribution | Z1: state_contribution | AA1: taxes_contribution | AB1: transfers_contribution | AC1: consumption_contribution | AD1: fiscal_impact_measure | AE1: fiscal_impact_4q_ma
A2: 2023 Q2 | B2: historical | C2: -1 | D2: -0.14802611 | E2: 0.32935984 | F2: 0.40168307 | G2: 0.18603735 | H2: -0.082194087 | I2: 0.23535829 | J2: -0.041113772 | K2: -0.11030549 | L2: -0.039292217 | M2: -0.25081207 | N2: -0.42408041 | O2: -0.28390642 | P2: 0.020948001 | Q2: -0.36373095 | R2: 0.00050505984 | S2: -0.041864783 | T2: -0.096126642 | U2: -0.0080992849 | V2: -0.0008915333 | W2: 0.17103649 | X2: 0.10677014 | Y2: -0.23313551 | Z2: 0.41446924 | AA2: 0.69855453 | AB2: -1.3262928 | AC2: -0.61796281 | AD2: -0.43662908 | AE2: -0.83627525
A3: 2023 Q3 | B3: historical | C3: -1 | D3: 0.29138773 | E3: 0.20751042 | F3: 0.11335746 | G3: 0.097716049 | H3: -0.05915321 | I3: 0.2310278 | J3: -0.033405652 | K3: -0.035337896 | L3: -0.097526156 | M3: -0.033451247 | N3: -0.0077388778 | O3: -0.13051737 | P3: 0.044718453 | Q3: -0.37795185 | R3: 0.00059502736 | S3: -0.026783451 | T3: -0.096213711 | U3: -0.13797271 | V3: -6.5844159e-05 | W3: -0.080930365 | X3: 0.24636772 | Y3: -0.13834318 | Z3: 0.63724132 | AA3: 0.34932404 | AB3: -0.7341966 | AC3: -0.38219864 | AD3: 0.11669951 | AE3: -0.20616336
A4: 2023 Q4 | B4: historical | C4: -1 | D4: 0.070409519 | E4: 0.33456315 | F4: 0.084390722 | G4: 0.052044238 | H4: -0.071699906 | I4: 0.082750407 | J4: -0.037624014 | K4: -0.20119765 | L4: -0.25248893 | M4: 0 | N4: -0.0062254866 | O4: -0.0074273919 | P4: 0.025176577 | Q4: -0.16467395 | R4: -0.0057101381 | S4: -0.026574551 | T4: -0.096631639 | U4: -0.11266828 | V4: -4.6437541e-05 | W4: 0.057480661 | X4: 0.073497893 | Y4: 0.28189704 | Z4: 0.12307563 | AA4: 0.10992045 | AB4: -0.71934748 | AC4: -0.60859101 | AD4: -0.20361835 | AE4: -0.15496259
A5: 2024 Q1 | B5: historical | C5: -1 | D5: -0.095656905 | E5: 0.096940856 | F5: 0.49002857 | G5: 0.20839114 | H5: -0.060391934 | I5: 0.12732301 | J5: -0.031435769 | K5: -0.015431334 | L5: -0.024236115 | M5: 0 | N5: -0.11167712 | O5: -0.0014130479 | P5: 0.014852718 | Q5: -0.1478768 | R5: -0.0065334558 | S5: -0.037491898 | T5: -0.063307767 | U5: -0.10447089 | V5: -0.0005835965 | W5: -0.13918165 | X5: 0.13055532 | Y5: -0.14198756 | Z5: 0.14327151 | AA5: 0.73267848 | AB5: -0.50768404 | AC5: 0.2289171 | AD5: 0.23020105 | AE5: -0.073336716
A6: 2024 Q2 | B6: historical | C6: -1 | D6: 0.12347864 | E6: 0.051398583 | F6: 0.35063464 | G6: 0.18132833 | H6: -0.046919377 | I6: 0.094528727 | J6: -0.022967964 | K6: 0.17944505 | L6: 0.020341749 | M6: 0 | N6: -0.104668 | O6: -0.00067198841 | P6: 0.01260551 | Q6: -0.34619776 | R6: -0.016772232 | S6: -0.035908571 | T6: -0.050238211 | U6: -0.096103418 | V6: -0.0021619606 | W6: -0.10798661 | X6: 0.1126516 | Y6: 0.19183196 | Z6: -0.016954735 | AA6: 0.55586415 | AB6: -0.43560311 | AC6: 0.12277732 | AD6: 0.29765454 | AE6: 0.11023419
A7: 2024 Q3 | B7: historical | C7: -1 | D7: 0.4065057 | E7: 0.1366917 | F7: 0.26769889 | G7: 0.02149772 | H7: -0.043703024 | I7: -0.0953656 | J7: -0.012505799 | K7: 0.26285186 | L7: 0.049653198 | M7: 0 | N7: -0.10040558 | O7: -0.00033408507 | P7: 0.010455964 | Q7: -0.30976776 | R7: -0.06669009 | S7: -0.034038326 | T7: -0.043936535 | U7: -0.055729673 | V7: -4.4268525e-05 | W7: 0.20674712 | X7: 0.044619557 | Y7: 0.63577579 | Z7: -0.092578392 | AA7: 0.1379591 | AB7: -0.035405605 | AC7: 0.10260463 | AD7: 0.64580203 | AE7: 0.24250982
A8: 2024 Q4 | B8: historical | C8: -1 | D8: 0.13387378 | E8: 0.040840032 | F8: 0.26578106 | G8: 0.029094859 | H8: -0.034339266 | I8: -0.13372901 | J8: 0.01136901 | K8: 0.27225397 | L8: 0.016960521 | M8: 0 | N8: -0.10036427 | O8: -0.0001725724 | P8: 0.0057762572 | Q8: -0.15458604 | R8: -0.029046972 | S8: -0.022294995 | T8: -0.026522516 | U8: -0.030672088 | V8: -5.5553434e-05 | W8: 0.14998116 | X8: 0.15091666 | Y8: 0.15254838 | Z8: 0.022165438 | AA8: 0.13854798 | AB8: 0.23270567 | AC8: 0.370919 | AD8: 0.54563281 | AE8: 0.42982261
A9: 2025 Q1 | B9: historical | C9: -1 | D9: -0.51945344 | E9: -0.036329069 | F9: -0.068923508 | G9: 0.045824279 | H9: -0.0042648201 | I9: 0.0248513 | J9: 0.013575618 | K9: 0.18178302 | L9: -0.0089342835 | M9: 0 | N9: -0.096865949 | O9: 0 | P9: 0.00044613388 | Q9: -0.073745276 | R9: -0.028114584 | S9: -0.014963859 | T9: -0.010608242 | U9: -0.030099483 | V9: -0.00030217362 | W9: 0.10399977 | X9: 0.002612607 | Y9: -1.1699513 | Z9: 0.61416882 | AA9: 0.011102717 | AB9: 0.025525593 | AC9: 0.036625317 | AD9: -0.51915719 | AE9: 0.24248305
A10: 2025 Q2 | B10: historical | C10: -1 | D10: -0.49659071 | E10: 0.090506589 | F10: -0.49360352 | G10: -0.039331912 | H10: 0.0070579944 | I10: 0.1871692 | J10: 0.0019233388 | K10: 0.46724311 | L10: -0.014502786 | M10: 0 | N10: -0.094949895 | O10: 0 | P10: 0.0018247774 | Q10: -0.094999199 | R10: -0.02673731 | S10: -0.013483429 | T10: -0.010020828 | U10: -0.023738219 | V10: -0.0010380446 | W10: 0.28501646 | X10: -0.029952741 | Y10: -0.94596317 | Z10: 0.53987905 | AA10: -0.33591118 | AB10: 0.44530218 | AC10: -0.18904189 | AD10: -0.59512601 | AE10: 0.019287909
A11: 2025 Q3 | B11: projection | C11: 0 | D11: 0.1631113 | E11: -0.18895751 | F11: -0.22561765 | G11: 0.031964415 | H11: 0.18570532 | I11: 0.18199766 | J11: 0.0069886574 | K11: 0.23748379 | L11: -0.00024409454 | M11: 0 | N11: -0.00099896094 | O11: 0 | P11: -0.0083673707 | Q11: -0.074626504 | R11: -0.026048206 | S11: -0.013810384 | T11: -0.0085423386 | U11: -0.029638323 | V11: -0.00052655433 | W11: 0.22450059 | X11: 0.0019343238 | Y11: 0.11078208 | Z11: -0.13662829 | AA11: 0.18149619 | AB11: 0.30124016 | AC11: 0.18215783 | AD11: 0.15631162 | AE11: -0.10308469
A12: 2025 Q4 | B12: projection | C12: 0 | D12: 0.051277427 | E12: -0.18797857 | F12: -0.18376482 | G12: 0.012855036 | H12: 0.065942043 | I12: 0.071097532 | J12: 0.0096981954 | K12: 0.15390503 | L12: 0.026815537 | M12: 0 | N12: -0.00097192311 | O12: 0 | P12: -0.0077753446 | Q12: -0.036283497 | R12: -0.0039026384 | S12: -0.012854849 | T12: -0.0076754748 | U12: -0.024548492 | V12: -0.00044546802 | W12: 0.2294708 | X12: 0.020152618 | Y12: -0.053072004 | Z12: -0.083629139 | AA12: -0.023945292 | AB12: 0.33571051 | AC12: 0.011850403 | AD12: -0.12485074 | AE12: -0.27070558
A13: 2026 Q1 | B13: projection | C13: 0 | D13: 0.29588505 | E13: -0.18679327 | F13: -0.15788909 | G13: -0.005175253 | H13: 0.063538308 | I13: 0.31388233 | J13: 0.0065070205 | K13: 0.030623218 | L13: 0.040643938 | M13: 0 | N13: -0.00094783566 | O13: 0 | P13: -0.0071485208 | Q13: -0.0028042467 | R13: -0.0026676745 | S13: -0.014294821 | T13: -0.0070418372 | U13: -0.022803876 | V13: -0.00041144841 | W13: 0.27300491 | X13: 0.029331705 | Y13: 0.24418567 | Z13: -0.13509389 | AA13: 0.2212818 | AB13: 0.31537333 | AC13: 0.29591252 | AD13: 0.4050043 | AE13: -0.039665209
... A18: 2027 Q2 | B18: projection | C18: 0 | D18: -0.11072717 | E18: -0.19118456 | F18: -0.02983676 | G18: 0.023800283 | H18: 0.088515383 | I18: -0.31115122 | J18: 0.004630489 | K18: -0.0073764978 | L18: 0.010613895 | M18: 0 | N18: 0 | O18: 0 | P18: -0.00081672553 | Q18: 0.0025172322 | R18: -0.00028515852 | S18: -0.0010320556 | T18: -0.0015233461 | U18: -0.0095126456 | V18: -0.00031358356 | W18: 0.089169656 | X18: 0.0013236714 | Y18: -0.15456652 | Z18: -0.1473452 | AA18: -0.22374323 | AB18: 0.082771764 | AC18: -0.18077372 | AD18: -0.48268544 | AE18: -0.4185299

Sheet newFIM
A1: date | B1: id | C1: recession | D1: federal_purchases_contribution | E1: state_purchases_contribution | F1: federal_non_corporate_taxes_contribution | G1: state_non_corporate_taxes_contribution | H1: federal_corporate_taxes_contribution | I1: supply_side_ira_contribution | J1: state_corporate_taxes_contribution | K1: federal_social_benefits_contribution | L1: state_social_benefits_contribution | M1: rebate_checks_contribution | N1: rebate_checks_arp_contribution | O1: federal_ui_contribution | P1: state_ui_contribution | Q1: federal_subsidies_contribution | R1: federal_aid_to_small_businesses_arp_contribution | S1: federal_other_direct_aid_arp_contribution | T1: federal_other_vulnerable_arp_contribution | U1: federal_student_loans_contribution | V1: state_subsidies_contribution | W1: federal_health_outlays_contribution | X1: state_health_outlays_contribution | Y1: federal_contribution | Z1: state_contribution | AA1: taxes_contribution | AB1: transfers_contribution | AC1: consumption_contribution | AD1: fiscal_impact_measure | AE1: fiscal_impact_4q_ma
A2: 2023 Q2 | B2: historical | C2: -1 | D2: -0.14802611 | E2: 0.32935984 | F2: 0.40168307 | G2: 0.18603735 | H2: -0.082194087 | I2: 0.23535829 | J2: -0.041113772 | K2: -0.11030549 | L2: -0.039292217 | M2: -0.25081207 | N2: -0.42408041 | O2: -0.28390642 | P2: 0.020948001 | Q2: -0.36373095 | R2: 0.00050505984 | S2: -0.041864783 | T2: -0.096126642 | U2: -0.0080992849 | V2: -0.0008915333 | W2: 0.17103649 | X2: 0.10677014 | Y2: -0.23313551 | Z2: 0.41446924 | AA2: 0.69855453 | AB2: -1.3262928 | AC2: -0.61796281 | AD2: -0.43662908 | AE2: -0.83627525
A3: 2023 Q3 | B3: historical | C3: -1 | D3: 0.29138773 | E3: 0.20751042 | F3: 0.11335746 | G3: 0.097716049 | H3: -0.05915321 | I3: 0.2310278 | J3: -0.033405652 | K3: -0.035337896 | L3: -0.097526156 | M3: -0.033451247 | N3: -0.0077388778 | O3: -0.13051737 | P3: 0.044718453 | Q3: -0.37795185 | R3: 0.00059502736 | S3: -0.026783451 | T3: -0.096213711 | U3: -0.13797271 | V3: -6.5844159e-05 | W3: -0.080930365 | X3: 0.24636772 | Y3: -0.13834318 | Z3: 0.63724132 | AA3: 0.34932404 | AB3: -0.7341966 | AC3: -0.38219864 | AD3: 0.11669951 | AE3: -0.20616336
A4: 2023 Q4 | B4: historical | C4: -1 | D4: 0.070409519 | E4: 0.33456315 | F4: 0.084390722 | G4: 0.052044238 | H4: -0.071699906 | I4: 0.082750407 | J4: -0.037624014 | K4: -0.20119765 | L4: -0.25248893 | M4: 0 | N4: -0.0062254866 | O4: -0.0074273919 | P4: 0.025176577 | Q4: -0.16467395 | R4: -0.0057101381 | S4: -0.026574551 | T4: -0.096631639 | U4: -0.11266828 | V4: -4.6437541e-05 | W4: 0.057480661 | X4: 0.073497893 | Y4: 0.28189704 | Z4: 0.12307563 | AA4: 0.10992045 | AB4: -0.71934748 | AC4: -0.60859101 | AD4: -0.20361835 | AE4: -0.15496259
A5: 2024 Q1 | B5: historical | C5: -1 | D5: -0.095656905 | E5: 0.096940856 | F5: 0.49002857 | G5: 0.20839114 | H5: -0.060391934 | I5: 0.12732301 | J5: -0.031435769 | K5: -0.015431334 | L5: -0.024236115 | M5: 0 | N5: -0.11167712 | O5: -0.0014130479 | P5: 0.014852718 | Q5: -0.1478768 | R5: -0.0065334558 | S5: -0.037491898 | T5: -0.063307767 | U5: -0.10447089 | V5: -0.0005835965 | W5: -0.13918165 | X5: 0.13055532 | Y5: -0.14198756 | Z5: 0.14327151 | AA5: 0.73267848 | AB5: -0.50768404 | AC5: 0.2289171 | AD5: 0.23020105 | AE5: -0.073336716
A6: 2024 Q2 | B6: historical | C6: -1 | D6: 0.12347864 | E6: 0.051398583 | F6: 0.35063464 | G6: 0.18132833 | H6: -0.046919377 | I6: 0.094528727 | J6: -0.022967964 | K6: 0.17944505 | L6: 0.020341749 | M6: 0 | N6: -0.104668 | O6: -0.00067198841 | P6: 0.01260551 | Q6: -0.34619776 | R6: -0.016772232 | S6: -0.035908571 | T6: -0.050238211 | U6: -0.096103418 | V6: -0.0021619606 | W6: -0.10798661 | X6: 0.1126516 | Y6: 0.19183196 | Z6: -0.016954735 | AA6: 0.55586415 | AB6: -0.43560311 | AC6: 0.12277732 | AD6: 0.29765454 | AE6: 0.11023419
A7: 2024 Q3 | B7: historical | C7: -1 | D7: 0.4065057 | E7: 0.1366917 | F7: 0.26769889 | G7: 0.02149772 | H7: -0.043703024 | I7: -0.0953656 | J7: -0.012505799 | K7: 0.26285186 | L7: 0.049653198 | M7: 0 | N7: -0.10040558 | O7: -0.00033408507 | P7: 0.010455964 | Q7: -0.30976776 | R7: -0.06669009 | S7: -0.034038326 | T7: -0.043936535 | U7: -0.055729673 | V7: -4.4268525e-05 | W7: 0.20674712 | X7: 0.044619557 | Y7: 0.63577579 | Z7: -0.092578392 | AA7: 0.1379591 | AB7: -0.035405605 | AC7: 0.10260463 | AD7: 0.64580203 | AE7: 0.24250982
A8: 2024 Q4 | B8: historical | C8: -1 | D8: 0.13387378 | E8: 0.040840032 | F8: 0.26578106 | G8: 0.029094859 | H8: -0.034339266 | I8: -0.13372901 | J8: 0.01136901 | K8: 0.27225397 | L8: 0.016960521 | M8: 0 | N8: -0.10036427 | O8: -0.0001725724 | P8: 0.0057762572 | Q8: -0.15458604 | R8: -0.029046972 | S8: -0.022294995 | T8: -0.026522516 | U8: -0.030672088 | V8: -5.5553434e-05 | W8: 0.14998116 | X8: 0.15091666 | Y8: 0.15254838 | Z8: 0.022165438 | AA8: 0.13854798 | AB8: 0.23270567 | AC8: 0.370919 | AD8: 0.54563281 | AE8: 0.42982261
A9: 2025 Q1 | B9: historical | C9: -1 | D9: -0.51945344 | E9: -0.036329069 | F9: -0.068923508 | G9: 0.045824279 | H9: -0.0042648201 | I9: 0.0248513 | J9: 0.013575618 | K9: 0.18178302 | L9: -0.0089342835 | M9: 0 | N9: -0.096865949 | O9: 0 | P9: 0.00044613388 | Q9: -0.073745276 | R9: -0.028114584 | S9: -0.014963859 | T9: -0.010608242 | U9: -0.030099483 | V9: -0.00030217362 | W9: 0.10399977 | X9: 0.002612607 | Y9: -1.1699513 | Z9: 0.61416882 | AA9: 0.011102717 | AB9: 0.025525593 | AC9: 0.036625317 | AD9: -0.51915719 | AE9: 0.24248305
A10: 2025 Q2 | B10: historical | C10: -1 | D10: -0.49659071 | E10: 0.090506589 | F10: -0.49360352 | G10: -0.039331912 | H10: 0.0070579944 | I10: 0.1871692 | J10: 0.0019233388 | K10: 0.46724311 | L10: -0.014502786 | M10: 0 | N10: -0.094949895 | O10: 0 | P10: 0.0018247774 | Q10: -0.094999199 | R10: -0.02673731 | S10: -0.013483429 | T10: -0.010020828 | U10: -0.023738219 | V10: -0.0010380446 | W10: 0.28501646 | X10: -0.029952741 | Y10: -0.94596317 | Z10: 0.53987905 | AA10: -0.33591118 | AB10: 0.44530218 | AC10: -0.18904189 | AD10: -0.59512601 | AE10: 0.019287909
A11: 2025 Q3 | B11: projection | C11: 0 | D11: 0.1631113 | E11: -0.18895751 | F11: -0.22561765 | G11: 0.031964415 | H11: 0.18570532 | I11: 0.18199766 | J11: 0.0069886574 | K11: 0.23748379 | L11: -0.00024409454 | M11: 0 | N11: -0.00099896094 | O11: 0 | P11: -0.0083673707 | Q11: -0.074626504 | R11: -0.026048206 | S11: -0.013810384 | T11: -0.0085423386 | U11: -0.029638323 | V11: -0.00052655433 | W11: 0.22450059 | X11: 0.0019343238 | Y11: 0.11078208 | Z11: -0.13662829 | AA11: 0.18149619 | AB11: 0.30124016 | AC11: 0.18215783 | AD11: 0.15631162 | AE11: -0.10308469
A12: 2025 Q4 | B12: projection | C12: 0 | D12: 0.051277427 | E12: -0.18797857 | F12: -0.18376482 | G12: 0.012855036 | H12: 0.065942043 | I12: 0.071097532 | J12: 0.0096981954 | K12: 0.15390503 | L12: 0.026815537 | M12: 0 | N12: -0.00097192311 | O12: 0 | P12: -0.0077753446 | Q12: -0.036283497 | R12: -0.0039026384 | S12: -0.012854849 | T12: -0.0076754748 | U12: -0.024548492 | V12: -0.00044546802 | W12: 0.2294708 | X12: 0.020152618 | Y12: -0.053072004 | Z12: -0.083629139 | AA12: -0.023945292 | AB12: 0.33571051 | AC12: 0.011850403 | AD12: -0.12485074 | AE12: -0.27070558
A13: 2026 Q1 | B13: projection | C13: 0 | D13: 0.29588505 | E13: -0.18679327 | F13: -0.15788909 | G13: -0.005175253 | H13: 0.063538308 | I13: 0.31388233 | J13: 0.0065070205 | K13: 0.054248823 | L13: 0.040643938 | M13: 0 | N13: -0.00094783566 | O13: 0 | P13: -0.0071485208 | Q13: -0.0028042467 | R13: -0.0026676745 | S13: -0.014294821 | T13: -0.0070418372 | U13: -0.022803876 | V13: -0.00041144841 | W13: 0.27300491 | X13: 0.029331705 | Y13: 0.24418567 | Z13: -0.13509389 | AA13: 0.2212818 | AB13: 0.33892734 | AC13: 0.31941104 | AD13: 0.42850282 | AE13: -0.033790579
... A18: 2027 Q2 | B18: projection | C18: 0 | D18: -0.11072717 | E18: -0.19118456 | F18: -0.02983676 | G18: 0.023800283 | H18: 0.088515383 | I18: -0.31115122 | J18: 0.004630489 | K18: -0.0078064572 | L18: 0.010613895 | M18: 0 | N18: 0 | O18: 0 | P18: -0.00081672553 | Q18: 0.0025172322 | R18: -0.00028515852 | S18: -0.0010320556 | T18: -0.0015233461 | U18: -0.0095126456 | V18: -0.00031358356 | W18: 0.089169656 | X18: 0.0013236714 | Y18: -0.15456652 | Z18: -0.1473452 | AA18: -0.22374323 | AB18: 0.082342218 | AC18: -0.18120429 | AD18: -0.48311602 | AE18: -0.40753802

Sheet diff2
A1: date | B1: id | C1: recession | D1: federal_purchases_contribution | E1: state_purchases_contribution | F1: federal_non_corporate_taxes_contribution | G1: state_non_corporate_taxes_contribution | H1: federal_corporate_taxes_contribution | I1: supply_side_ira_contribution | J1: state_corporate_taxes_contribution | K1: federal_social_benefits_contribution | L1: state_social_benefits_contribution | M1: rebate_checks_contribution | N1: rebate_checks_arp_contribution | O1: federal_ui_contribution | P1: state_ui_contribution | Q1: federal_subsidies_contribution | R1: federal_aid_to_small_businesses_arp_contribution | S1: federal_other_direct_aid_arp_contribution | T1: federal_other_vulnerable_arp_contribution | U1: federal_student_loans_contribution | V1: state_subsidies_contribution | W1: federal_health_outlays_contribution | X1: state_health_outlays_contribution | Y1: federal_contribution | Z1: state_contribution | AA1: taxes_contribution | AB1: transfers_contribution | AC1: consumption_contribution | AD1: fiscal_impact_measure | AE1: fiscal_impact_4q_ma
A2: 2023 Q2 | B2: historical | C2: -1 | D2: =newFIM!D2-Sheet1!D2 -> 0 | E2: =newFIM!E2-Sheet1!E2 -> 0 | F2: =newFIM!F2-Sheet1!F2 -> 0 | G2: =newFIM!G2-Sheet1!G2 -> 0 | H2: =newFIM!H2-Sheet1!H2 -> 0 | I2: =newFIM!I2-Sheet1!I2 -> 0 | J2: =newFIM!J2-Sheet1!J2 -> 0 | K2: =newFIM!K2-Sheet1!K2 -> 0 | ... AE2: =newFIM!AE2-Sheet1!AE2 -> 0
A3: 2023 Q3 | B3: historical | C3: -1 | D3: =newFIM!D3-Sheet1!D3 -> 0 | E3: =newFIM!E3-Sheet1!E3 -> 0 | F3: =newFIM!F3-Sheet1!F3 -> 0 | G3: =newFIM!G3-Sheet1!G3 -> 0 | H3: =newFIM!H3-Sheet1!H3 -> 0 | I3: =newFIM!I3-Sheet1!I3 -> 0 | J3: =newFIM!J3-Sheet1!J3 -> 0 | K3: =newFIM!K3-Sheet1!K3 -> 0 | ... AE3: =newFIM!AE3-Sheet1!AE3 -> 0
A4: 2023 Q4 | B4: historical | C4: -1 | D4: =newFIM!D4-Sheet1!D4 -> 0 | E4: =newFIM!E4-Sheet1!E4 -> 0 | F4: =newFIM!F4-Sheet1!F4 -> 0 | G4: =newFIM!G4-Sheet1!G4 -> 0 | H4: =newFIM!H4-Sheet1!H4 -> 0 | I4: =newFIM!I4-Sheet1!I4 -> 0 | J4: =newFIM!J4-Sheet1!J4 -> 0 | K4: =newFIM!K4-Sheet1!K4 -> 0 | ... AE4: =newFIM!AE4-Sheet1!AE4 -> 0
A5: 2024 Q1 | B5: historical | C5: -1 | D5: =newFIM!D5-Sheet1!D5 -> 0 | E5: =newFIM!E5-Sheet1!E5 -> 0 | F5: =newFIM!F5-Sheet1!F5 -> 0 | G5: =newFIM!G5-Sheet1!G5 -> 0 | H5: =newFIM!H5-Sheet1!H5 -> 0 | I5: =newFIM!I5-Sheet1!I5 -> 0 | J5: =newFIM!J5-Sheet1!J5 -> 0 | K5: =newFIM!K5-Sheet1!K5 -> 0 | ... AE5: =newFIM!AE5-Sheet1!AE5 -> 0
A6: 2024 Q2 | B6: historical | C6: -1 | D6: =newFIM!D6-Sheet1!D6 -> 0 | E6: =newFIM!E6-Sheet1!E6 -> 0 | F6: =newFIM!F6-Sheet1!F6 -> 0 | G6: =newFIM!G6-Sheet1!G6 -> 0 | H6: =newFIM!H6-Sheet1!H6 -> 0 | I6: =newFIM!I6-Sheet1!I6 -> 0 | J6: =newFIM!J6-Sheet1!J6 -> 0 | K6: =newFIM!K6-Sheet1!K6 -> 0 | ... AE6: =newFIM!AE6-Sheet1!AE6 -> 0
A7: 2024 Q3 | B7: historical | C7: -1 | D7: =newFIM!D7-Sheet1!D7 -> 0 | E7: =newFIM!E7-Sheet1!E7 -> 0 | F7: =newFIM!F7-Sheet1!F7 -> 0 | G7: =newFIM!G7-Sheet1!G7 -> 0 | H7: =newFIM!H7-Sheet1!H7 -> 0 | I7: =newFIM!I7-Sheet1!I7 -> 0 | J7: =newFIM!J7-Sheet1!J7 -> 0 | K7: =newFIM!K7-Sheet1!K7 -> 0 | ... AE7: =newFIM!AE7-Sheet1!AE7 -> 0
A8: 2024 Q4 | B8: historical | C8: -1 | D8: =newFIM!D8-Sheet1!D8 -> 0 | E8: =newFIM!E8-Sheet1!E8 -> 0 | F8: =newFIM!F8-Sheet1!F8 -> 0 | G8: =newFIM!G8-Sheet1!G8 -> 0 | H8: =newFIM!H8-Sheet1!H8 -> 0 | I8: =newFIM!I8-Sheet1!I8 -> 0 | J8: =newFIM!J8-Sheet1!J8 -> 0 | K8: =newFIM!K8-Sheet1!K8 -> 0 | ... AE8: =newFIM!AE8-Sheet1!AE8 -> 0
A9: 2025 Q1 | B9: historical | C9: -1 | D9: =newFIM!D9-Sheet1!D9 -> 0 | E9: =newFIM!E9-Sheet1!E9 -> 0 | F9: =newFIM!F9-Sheet1!F9 -> 0 | G9: =newFIM!G9-Sheet1!G9 -> 0 | H9: =newFIM!H9-Sheet1!H9 -> 0 | I9: =newFIM!I9-Sheet1!I9 -> 0 | J9: =newFIM!J9-Sheet1!J9 -> 0 | K9: =newFIM!K9-Sheet1!K9 -> 0 | ... AE9: =newFIM!AE9-Sheet1!AE9 -> 0
A10: 2025 Q2 | B10: historical | C10: -1 | D10: =newFIM!D10-Sheet1!D10 -> 0 | E10: =newFIM!E10-Sheet1!E10 -> 0 | F10: =newFIM!F10-Sheet1!F10 -> 0 | G10: =newFIM!G10-Sheet1!G10 -> 0 | H10: =newFIM!H10-Sheet1!H10 -> 0 | I10: =newFIM!I10-Sheet1!I10 -> 0 | J10: =newFIM!J10-Sheet1!J10 -> 0 | K10: =newFIM!K10-Sheet1!K10 -> 0 | ... AE10: =newFIM!AE10-Sheet1!AE10 -> 0
A11: 2025 Q3 | B11: projection | C11: 0 | D11: =newFIM!D11-Sheet1!D11 -> 0 | E11: =newFIM!E11-Sheet1!E11 -> 0 | F11: =newFIM!F11-Sheet1!F11 -> 0 | G11: =newFIM!G11-Sheet1!G11 -> 0 | H11: =newFIM!H11-Sheet1!H11 -> 0 | I11: =newFIM!I11-Sheet1!I11 -> 0 | J11: =newFIM!J11-Sheet1!J11 -> 0 | K11: =newFIM!K11-Sheet1!K11 -> 0 | ... AE11: =newFIM!AE11-Sheet1!AE11 -> 0
A12: 2025 Q4 | B12: projection | C12: 0 | D12: =newFIM!D12-Sheet1!D12 -> 0 | E12: =newFIM!E12-Sheet1!E12 -> 0 | F12: =newFIM!F12-Sheet1!F12 -> 0 | G12: =newFIM!G12-Sheet1!G12 -> 0 | H12: =newFIM!H12-Sheet1!H12 -> 0 | I12: =newFIM!I12-Sheet1!I12 -> 0 | J12: =newFIM!J12-Sheet1!J12 -> 0 | K12: =newFIM!K12-Sheet1!K12 -> 0 | ... AE12: =newFIM!AE12-Sheet1!AE12 -> 0
A13: 2026 Q1 | B13: projection | C13: 0 | D13: =newFIM!D13-Sheet1!D13 -> 0 | E13: =newFIM!E13-Sheet1!E13 -> 0 | F13: =newFIM!F13-Sheet1!F13 -> 0 | G13: =newFIM!G13-Sheet1!G13 -> 0 | H13: =newFIM!H13-Sheet1!H13 -> 0 | I13: =newFIM!I13-Sheet1!I13 -> 0 | J13: =newFIM!J13-Sheet1!J13 -> 0 | K13: =newFIM!K13-Sheet1!K13 -> 0.023625605 | ... AE13: =newFIM!AE13-Sheet1!AE13 -> 0.0058746298
... A18: 2027 Q2 | B18: projection | C18: 0 | D18: =newFIM!D18-Sheet1!D18 -> 0 | E18: =newFIM!E18-Sheet1!E18 -> 0 | F18: =newFIM!F18-Sheet1!F18 -> 0 | G18: =newFIM!G18-Sheet1!G18 -> 0 | H18: =newFIM!H18-Sheet1!H18 -> 0 | I18: =newFIM!I18-Sheet1!I18 -> 0 | J18: =newFIM!J18-Sheet1!J18 -> 0 | K18: =newFIM!K18-Sheet1!K18 -> -0.00042995943 | ... AE18: =newFIM!AE18-Sheet1!AE18 -> 0.010991881

Sheet diff
A1: date | B1: id | C1: recession | D1: federal_purchases_contribution | E1: state_purchases_contribution | F1: federal_non_corporate_taxes_contribution | G1: state_non_corporate_taxes_contribution | H1: federal_corporate_taxes_contribution | I1: supply_side_ira_contribution | J1: state_corporate_taxes_contribution | K1: federal_social_benefits_contribution | L1: state_social_benefits_contribution | M1: rebate_checks_contribution | N1: rebate_checks_arp_contribution | O1: federal_ui_contribution | P1: state_ui_contribution | Q1: federal_subsidies_contribution | R1: federal_aid_to_small_businesses_arp_contribution | S1: federal_other_direct_aid_arp_contribution | T1: federal_other_vulnerable_arp_contribution | U1: federal_student_loans_contribution | V1: state_subsidies_contribution | W1: federal_health_outlays_contribution | X1: state_health_outlays_contribution | Y1: federal_contribution | Z1: state_contribution | AA1: taxes_contribution | AB1: transfers_contribution | AC1: consumption_contribution | AD1: fiscal_impact_measure | AE1: fiscal_impact_4q_ma
A2: 2023 Q2 | B2: historical | C2: -1 | D2: ='no tariffs'!D2-Sheet1!D2 -> 0 | E2: ='no tariffs'!E2-Sheet1!E2 -> 0 | F2: ='no tariffs'!F2-Sheet1!F2 -> 0 | G2: ='no tariffs'!G2-Sheet1!G2 -> 0 | H2: ='no tariffs'!H2-Sheet1!H2 -> 0 | I2: ='no tariffs'!I2-Sheet1!I2 -> 0 | J2: ='no tariffs'!J2-Sheet1!J2 -> 0 | K2: ='no tariffs'!K2-Sheet1!K2 -> 0 | ... AE2: ='no tariffs'!AE2-Sheet1!AE2 -> 0
A3: 2023 Q3 | B3: historical | C3: -1 | D3: ='no tariffs'!D3-Sheet1!D3 -> 0 | E3: ='no tariffs'!E3-Sheet1!E3 -> 0 | F3: ='no tariffs'!F3-Sheet1!F3 -> 0 | G3: ='no tariffs'!G3-Sheet1!G3 -> 0 | H3: ='no tariffs'!H3-Sheet1!H3 -> 0 | I3: ='no tariffs'!I3-Sheet1!I3 -> 0 | J3: ='no tariffs'!J3-Sheet1!J3 -> 0 | K3: ='no tariffs'!K3-Sheet1!K3 -> 0 | ... AE3: ='no tariffs'!AE3-Sheet1!AE3 -> 0
A4: 2023 Q4 | B4: historical | C4: -1 | D4: ='no tariffs'!D4-Sheet1!D4 -> 0 | E4: ='no tariffs'!E4-Sheet1!E4 -> 0 | F4: ='no tariffs'!F4-Sheet1!F4 -> 0 | G4: ='no tariffs'!G4-Sheet1!G4 -> 0 | H4: ='no tariffs'!H4-Sheet1!H4 -> 0 | I4: ='no tariffs'!I4-Sheet1!I4 -> 0 | J4: ='no tariffs'!J4-Sheet1!J4 -> 0 | K4: ='no tariffs'!K4-Sheet1!K4 -> 0 | ... AE4: ='no tariffs'!AE4-Sheet1!AE4 -> 0
A5: 2024 Q1 | B5: historical | C5: -1 | D5: ='no tariffs'!D5-Sheet1!D5 -> 0 | E5: ='no tariffs'!E5-Sheet1!E5 -> 0 | F5: ='no tariffs'!F5-Sheet1!F5 -> 0 | G5: ='no tariffs'!G5-Sheet1!G5 -> 0 | H5: ='no tariffs'!H5-Sheet1!H5 -> 0 | I5: ='no tariffs'!I5-Sheet1!I5 -> 0 | J5: ='no tariffs'!J5-Sheet1!J5 -> 0 | K5: ='no tariffs'!K5-Sheet1!K5 -> 0 | ... AE5: ='no tariffs'!AE5-Sheet1!AE5 -> 0
A6: 2024 Q2 | B6: historical | C6: -1 | D6: ='no tariffs'!D6-Sheet1!D6 -> 0 | E6: ='no tariffs'!E6-Sheet1!E6 -> 0 | F6: ='no tariffs'!F6-Sheet1!F6 -> 0 | G6: ='no tariffs'!G6-Sheet1!G6 -> 0 | H6: ='no tariffs'!H6-Sheet1!H6 -> 0 | I6: ='no tariffs'!I6-Sheet1!I6 -> 0 | J6: ='no tariffs'!J6-Sheet1!J6 -> 0 | K6: ='no tariffs'!K6-Sheet1!K6 -> 0 | ... AE6: ='no tariffs'!AE6-Sheet1!AE6 -> 0
A7: 2024 Q3 | B7: historical | C7: -1 | D7: ='no tariffs'!D7-Sheet1!D7 -> 0 | E7: ='no tariffs'!E7-Sheet1!E7 -> 0 | F7: ='no tariffs'!F7-Sheet1!F7 -> 0 | G7: ='no tariffs'!G7-Sheet1!G7 -> 0 | H7: ='no tariffs'!H7-Sheet1!H7 -> 0 | I7: ='no tariffs'!I7-Sheet1!I7 -> 0 | J7: ='no tariffs'!J7-Sheet1!J7 -> 0 | K7: ='no tariffs'!K7-Sheet1!K7 -> 0 | ... AE7: ='no tariffs'!AE7-Sheet1!AE7 -> 0
A8: 2024 Q4 | B8: historical | C8: -1 | D8: ='no tariffs'!D8-Sheet1!D8 -> 0 | E8: ='no tariffs'!E8-Sheet1!E8 -> 0 | F8: ='no tariffs'!F8-Sheet1!F8 -> 0 | G8: ='no tariffs'!G8-Sheet1!G8 -> 0 | H8: ='no tariffs'!H8-Sheet1!H8 -> 0 | I8: ='no tariffs'!I8-Sheet1!I8 -> 0 | J8: ='no tariffs'!J8-Sheet1!J8 -> 0 | K8: ='no tariffs'!K8-Sheet1!K8 -> 0 | ... AE8: ='no tariffs'!AE8-Sheet1!AE8 -> 0
A9: 2025 Q1 | B9: historical | C9: -1 | D9: ='no tariffs'!D9-Sheet1!D9 -> 0 | E9: ='no tariffs'!E9-Sheet1!E9 -> 0 | F9: ='no tariffs'!F9-Sheet1!F9 -> 0 | G9: ='no tariffs'!G9-Sheet1!G9 -> 0 | H9: ='no tariffs'!H9-Sheet1!H9 -> 0 | I9: ='no tariffs'!I9-Sheet1!I9 -> 0 | J9: ='no tariffs'!J9-Sheet1!J9 -> 0 | K9: ='no tariffs'!K9-Sheet1!K9 -> 0 | ... AE9: ='no tariffs'!AE9-Sheet1!AE9 -> 0
A10: 2025 Q2 | B10: historical | C10: -1 | D10: ='no tariffs'!D10-Sheet1!D10 -> 0 | E10: ='no tariffs'!E10-Sheet1!E10 -> 0 | F10: ='no tariffs'!F10-Sheet1!F10 -> 0 | G10: ='no tariffs'!G10-Sheet1!G10 -> 0 | H10: ='no tariffs'!H10-Sheet1!H10 -> 0 | I10: ='no tariffs'!I10-Sheet1!I10 -> 0 | J10: ='no tariffs'!J10-Sheet1!J10 -> 0 | K10: ='no tariffs'!K10-Sheet1!K10 -> 0 | ... AE10: ='no tariffs'!AE10-Sheet1!AE10 -> 0.075
A11: 2025 Q3 | B11: projection | C11: 0 | D11: ='no tariffs'!D11-Sheet1!D11 -> 0 | E11: ='no tariffs'!E11-Sheet1!E11 -> 0 | F11: ='no tariffs'!F11-Sheet1!F11 -> 0.41639006 | G11: ='no tariffs'!G11-Sheet1!G11 -> 0 | H11: ='no tariffs'!H11-Sheet1!H11 -> 0 | I11: ='no tariffs'!I11-Sheet1!I11 -> 0 | J11: ='no tariffs'!J11-Sheet1!J11 -> 0 | K11: ='no tariffs'!K11-Sheet1!K11 -> 0 | ... AE11: ='no tariffs'!AE11-Sheet1!AE11 -> 0.2533195
A12: 2025 Q4 | B12: projection | C12: 0 | D12: ='no tariffs'!D12-Sheet1!D12 -> 0 | E12: ='no tariffs'!E12-Sheet1!E12 -> 0 | F12: ='no tariffs'!F12-Sheet1!F12 -> 0.49967022 | G12: ='no tariffs'!G12-Sheet1!G12 -> 0 | H12: ='no tariffs'!H12-Sheet1!H12 -> 0 | I12: ='no tariffs'!I12-Sheet1!I12 -> 0 | J12: ='no tariffs'!J12-Sheet1!J12 -> 0 | K12: ='no tariffs'!K12-Sheet1!K12 -> 0 | ... AE12: ='no tariffs'!AE12-Sheet1!AE12 -> 0.45258188
A13: 2026 Q1 | B13: projection | C13: 0 | D13: ='no tariffs'!D13-Sheet1!D13 -> 0 | E13: ='no tariffs'!E13-Sheet1!E13 -> 0 | F13: ='no tariffs'!F13-Sheet1!F13 -> 0.28870779 | G13: ='no tariffs'!G13-Sheet1!G13 -> 0 | H13: ='no tariffs'!H13-Sheet1!H13 -> 0 | I13: ='no tariffs'!I13-Sheet1!I13 -> 0 | J13: ='no tariffs'!J13-Sheet1!J13 -> 0 | K13: ='no tariffs'!K13-Sheet1!K13 -> 0.023625605 | ... AE13: ='no tariffs'!AE13-Sheet1!AE13 -> 0.59008331
... A18: 2027 Q2 | B18: projection | C18: 0 | D18: ='no tariffs'!D18-Sheet1!D18 -> 0 | E18: ='no tariffs'!E18-Sheet1!E18 -> 0 | F18: ='no tariffs'!F18-Sheet1!F18 -> 0.23431066 | G18: ='no tariffs'!G18-Sheet1!G18 -> 0 | H18: ='no tariffs'!H18-Sheet1!H18 -> 0 | I18: ='no tariffs'!I18-Sheet1!I18 -> 0 | J18: ='no tariffs'!J18-Sheet1!J18 -> 0 | K18: ='no tariffs'!K18-Sheet1!K18 -> -0.00042995943 | ... AE18: ='no tariffs'!AE18-Sheet1!AE18 -> 0.33706697
