Workbook

Sheet revert
A1: date | B1: id | C1: recession | D1: federal_purchases_deflator_growth | E1: consumption_grants_deflator_growth | F1: investment_grants_deflator_growth | G1: state_purchases_deflator_growth | H1: consumption_deflator_growth | I1: real_potential_gdp_growth | J1: gdp | K1: consumption | L1: uncertainty | M1: federal_purchases | N1: consumption_grants | O1: investment_grants | P1: state_purchases | Q1: federal_non_corporate_taxes | R1: state_non_corporate_taxes | S1: federal_corporate_taxes | T1: supply_side_ira | U1: state_corporate_taxes | V1: federal_social_benefits | W1: state_social_benefits | X1: rebate_checks | Y1: rebate_checks_arp | Z1: federal_ui | AA1: state_ui | AB1: federal_subsidies | AC1: federal_aid_to_small_businesses_arp | AD1: federal_other_direct_aid_arp | AE1: federal_other_vulnerable_arp | AF1: federal_student_loans | AG1: state_subsidies | AH1: federal_health_outlays | AI1: state_health_outlays | AJ1: post_mpc_federal_non_corporate_taxes | AK1: post_mpc_state_non_corporate_taxes | AL1: post_mpc_federal_corporate_taxes | AM1: post_mpc_state_corporate_taxes | AN1: post_mpc_federal_social_benefits | AO1: post_mpc_state_social_benefits | AP1: post_mpc_rebate_checks | AQ1: post_mpc_rebate_checks_arp | AR1: post_mpc_federal_ui | AS1: post_mpc_state_ui | AT1: post_mpc_federal_subsidies | AU1: post_mpc_federal_aid_to_small_businesses_arp | AV1: post_mpc_federal_other_vulnerable_arp | AW1: post_mpc_federal_student_loans | AX1: post_mpc_state_subsidies | AY1: post_mpc_federal_health_outlays | AZ1: post_mpc_state_health_outlays
A2: 2023 Q2 | B2: historical | C2: -1 | D2: 0.006582718 | E2: -0.0073827309 | F2: 0.0021322445 | G2: -0.0056211973 | H2: 0.0073926308 | I2: 0.0056240488 | J2: 27530.1 | K2: 18693.1 | L2: 0 | M2: 1738.8 | N2: 436.07272 | O2: 76.015143 | P2: 2934.6 | Q2: 4210.6 | R2: 2236.1 | S2: 415.5 | T2: 46.245323 | U2: 170.2 | V2: 2006.4269 | W2: 183.8 | X2: 0 | Y2: 0 | Z2: 0 | AA2: 32.8 | AB2: 101.3 | AC2: 12.726 | AD2: 1.416 | AE2: 12 | AF2: 45 | AG2: 0.7 | AH2: 1659.996 | AI2: 267.104 | AJ2: -2564.838 | AK2: -1347.348 | AL2: -144.40667 | AM2: -55.99 | AN2: 1790.1942 | AO2: 188.1225 | AP2: 2.1784 | AQ2: 41.153 | AR2: 9.157 | AS2: 22.948 | AT2: 159.5619 | AU2: 14.28301 | AV2: 28.976026 | AW2: 40.95 | AX2: 0.5679 | AY2: 1444.3544 | AZ2: 210.74558
A3: 2023 Q3 | B3: historical | C3: -1 | D3: 0.0094033912 | E3: 0.016732699 | F3: 0.00035461796 | G3: 0.013706093 | H3: 0.0067310092 | I3: 0.0056687159 | J3: 28074.8 | K3: 18961.8 | L3: 0 | M3: 1784.4 | N3: 417.91594 | O3: 76.015143 | P3: 3005.4 | Q3: 4257.9 | R3: 2270.3 | S3: 428.4 | T3: 62.071265 | U3: 168.5 | V3: 2016.4269 | W3: 185.9 | X3: 0 | Y3: 0 | Z3: 0 | AA3: 34.9 | AB3: 103.5 | AC3: 12.726 | AD3: 1.416 | AE3: 12 | AF3: 2.081508 | AG3: 0.7 | AH3: 1613.65 | AI3: 290.05 | AJ3: -2589.162 | AK3: -1357.608 | AL3: -150.09667 | AM3: -58.886667 | AN3: 1810.0624 | AO3: 184.0275 | AP3: 0 | AQ3: 41.153 | AR3: 0.67 | AS3: 26.182 | AT3: 136.66702 | AU3: 14.499352 | AV3: 22.99411 | AW3: 32.366302 | AX3: 0.5706 | AY3: 1456.9297 | AZ3: 229.62533
A4: 2023 Q4 | B4: historical | C4: -1 | D4: 0.0070345423 | E4: 0.00071349046 | F4: 0.0032733965 | G4: 0.0011916352 | H4: 0.0045206985 | I4: 0.0057213587 | J4: 28424.7 | K4: 19190.6 | L4: 0 | M4: 1812 | N4: 434.04594 | O4: 77.674143 | P4: 3049 | Q4: 4302.2 | R4: 2301.1 | S4: 442.7 | T4: 68.31219 | U4: 172.7 | V4: 2024.999 | W4: 189.5 | X4: 0 | Y4: 0 | Z4: 0 | AA4: 35.5 | AB4: 98 | AC4: 1.365 | AD4: 1.479 | AE4: 4.222 | AF4: 2.100618 | AG4: 0.7 | AH4: 1658.388 | AI4: 252.912 | AJ4: -2609.964 | AK4: -1367.988 | AL4: -156.48667 | AM4: -62.036667 | AN4: 1814.9933 | AO4: 168.84 | AP4: 0 | AQ4: 41.153 | AR4: 0.174 | AS4: 28.155 | AT4: 126.927 | AU4: 14.261254 | AV4: 16.69038 | AW4: 25.07398 | AX4: 0.5733 | AY4: 1475.7446 | AZ4: 236.95538
A5: 2024 Q1 | B5: historical | C5: -1 | D5: 0.01026393 | E5: 0.008782995 | F5: 0.0044129366 | G5: 0.0079425584 | H5: 0.0088526155 | I5: 0.0057507902 | J5: 28708.2 | K5: 19443.8 | L5: 0 | M5: 1834.3 | N5: 437.85294 | O5: 77.674143 | P5: 3097.5 | Q5: 4390.9 | R5: 2325.5 | S5: 472.3 | T5: 78.014538 | U5: 173.2 | V5: 2131.899 | W5: 194.8 | X5: 0 | Y5: 0 | Z5: 0 | AA5: 35.5 | AB5: 95 | AC5: 1.365 | AD5: 1.479 | AE5: 4.222 | AF5: 2.58153 | AG5: 0.7 | AH5: 1680.381 | AI5: 298.119 | AJ5: -2614.512 | AK5: -1373.712 | AL5: -162.89667 | AM5: -65.09 | AN5: 1840.4441 | AO5: 169.65 | AP5: 0 | AQ5: 34.1285 | AR5: 0.08 | AS5: 29.581 | AT5: 118.68525 | AU5: 14.023156 | AV5: 12.61027 | AW5: 18.306452 | AX5: 0.5418 | AY5: 1487.7934 | AZ5: 249.34162
A6: 2024 Q2 | B6: historical | C6: -1 | D6: 0.0075830466 | E6: 0.0028193299 | F6: 0.0024774522 | G6: 0.0027475708 | H6: 0.0064180979 | I6: 0.0058015415 | J6: 29147 | K6: 19756.1 | L6: 0 | M6: 1867.5 | N6: 447.07611 | O6: 77.674143 | P6: 3127.6 | Q6: 4456.6 | R6: 2363.6 | S6: 495.3 | T6: 85.438722 | U6: 170.6 | V6: 2160.999 | W6: 199.2 | X6: 0 | Y6: 0 | Z6: 0 | AA6: 36.1 | AB6: 93 | AC6: 1.365 | AD6: 1.479 | AE6: 4.222 | AF6: 2.604045 | AG6: 0.7 | AH6: 1707.978 | AI6: 314.922 | AJ6: -2622.426 | AK6: -1378.08 | AL6: -168.09667 | AM6: -67.456667 | AN6: 1875.2229 | AO6: 173.115 | AP6: 0 | AQ6: 27.388 | AR6: 0.035 | AS6: 30.805 | AT6: 96.491025 | AU6: 13.047051 | AV6: 9.32794 | AW6: 11.957994 | AX6: 0.4005 | AY6: 1498.5893 | AZ6: 260.10068
A7: 2024 Q3 | B7: historical | C7: -1 | D7: 0.0059965041 | E7: 0.0039266712 | F7: 0.0065105722 | G7: 0.0044025399 | H7: 0.0042217342 | I7: 0.0057505722 | J7: 29511.7 | K7: 20032.8 | L7: 0 | M7: 1917.9 | N7: 468.80533 | O7: 77.674143 | P7: 3169.1 | Q7: 4526.7 | R7: 2400.1 | S7: 490.6 | T7: 79.629003 | U7: 170.1 | V7: 2181.299 | W7: 209 | X7: 0 | Y7: 0 | Z7: 0 | AA7: 37 | AB7: 92.1 | AC7: 1.365 | AD7: 1.479 | AE7: 4.222 | AF7: 2.626465 | AG7: 0.7 | AH7: 1744.359 | AI7: 315.441 | AJ7: -2629.842 | AK7: -1390.32 | AL7: -172.82667 | AM7: -69.003333 | AN7: 1912.3191 | AO7: 178.3125 | AP7: 0 | AQ7: 20.6475 | AR7: 0.012 | AS7: 31.843 | AT7: 75.838725 | AU7: 8.517842 | AV7: 6.35096 | AW7: 8.1834539 | AX7: 0.4014 | AY7: 1527.9988 | AZ7: 265.81365
A8: 2024 Q4 | B8: historical | C8: -1 | D8: 0.0059688045 | E8: 0.0032787138 | F8: 0.0035235298 | G8: 0.003325747 | H8: 0.0062373921 | I8: 0.0057438004 | J8: 29825.2 | K8: 20351.3 | L8: 0 | M8: 1950 | N8: 473.51933 | O8: 79.268143 | P8: 3200.8 | Q8: 4590.3 | R8: 2436.6 | S8: 508.6 | T8: 71.179167 | U8: 174.2 | V8: 2212.098 | W8: 204.3 | X8: 0 | Y8: 0 | Z8: 0 | AA8: 37.3 | AB8: 94 | AC8: -0.901 | AD8: 1.63 | AE8: 2.372 | AF8: 2.649835 | AG8: 0.7 | AH8: 1786.697 | AI8: 314.303 | AJ8: -2642.622 | AK8: -1404.93 | AL8: -177.31333 | AM8: -69.03 | AN8: 1954.4164 | AO8: 181.6425 | AP8: 0 | AQ8: 13.836 | AR8: 0 | AS8: 32.631 | AT8: 65.877975 | AU8: 6.576191 | AV8: 4.56094 | AW8: 6.1234738 | AX8: 0.4023 | AY8: 1556.8684 | AZ8: 279.62662
A9: 2025 Q1 | B9: historical | C9: -1 | D9: 0.014353684 | E9: 0.0099039593 | F9: 0.0066231529 | G9: 0.0092720593 | H9: 0.0084681203 | I9: 0.0056201408 | J9: 30042.1 | K9: 20555 | L9: 0 | M9: 1949.7 | N9: 435.153 | O9: 79.268143 | P9: 3245.8 | Q9: 4710.9 | R9: 2460.1 | S9: 469.2 | T9: 73.980636 | U9: 184.4 | V9: 2312.798 | W9: 203.3 | X9: 0 | Y9: 0 | Z9: 0 | AA9: 37.1 | AB9: 107 | AC9: -0.901 | AD9: 1.63 | AE9: 2.372 | AF9: 2.645442 | AG9: 0.7 | AH9: 1811.332 | AI9: 316.468 | AJ9: -2684.838 | AK9: -1421.406 | AL9: -180.12 | AM9: -69.02 | AN9: 1995.1186 | AO9: 183.555 | AP9: 0 | AQ9: 7.0245 | AR9: 0 | AS9: 33.123 | AT9: 61.47135 | AU9: 4.63454 | AV9: 3.85754 | AW9: 4.0318455 | AX9: 0.3861 | AY9: 1586.3323 | AZ9: 283.75515
A10: 2025 Q2 | B10: historical | C10: -1 | D10: 0.017075286 | E10: 0.0023603402 | F10: 0.0054340243 | G10: 0.0029513035 | H10: 0.0052878919 | I10: 0.0057178013 | J10: 30485.7 | K10: 20789.9 | L10: -0.3 | M10: 1956.4 | N10: 411.32562 | O10: 75.196143 | P10: 3280.6 | Q10: 4944.5 | R10: 2490.5 | S10: 470 | T10: 88.394443 | U10: 183 | V10: 2409.698 | W10: 203.5 | X10: 0 | Y10: 0 | Z10: 0 | AA10: 38 | AB10: 119.2 | AC10: -0.901 | AD10: 1.63 | AE10: 2.372 | AF10: 2.6696 | AG10: 0.7 | AH10: 1877.66 | AI10: 319.14 | AJ10: -2750.124 | AK10: -1439.904 | AL10: -181.6 | AM10: -69.64 | AN10: 2051.0759 | AO10: 184.5225 | AP10: 0 | AQ10: 0.213 | AR10: 0 | AS10: 33.62 | AT10: 55.2555 | AU10: 2.745007 | AV10: 3.17264 | AW10: 2.3533203 | AX10: 0.315 | AY10: 1624.5108 | AZ10: 284.7042
A11: 2025 Q3 | B11: projection | C11: 0 | D11: 7.4170933e-06 | E11: 0.0077455121 | F11: 0.0077455121 | G11: 0.0077455121 | H11: 0.0079484627 | I11: 0.0057366284 | J11: 30789.813 | K11: 20995.964 | L11: -0.3 | M11: 1979.7453 | N11: 413.92898 | O11: 75.196143 | P11: 3310.5813 | Q11: 4936.9814 | R11: 2509.6975 | S11: 78.824649 | T11: 103.08351 | U11: 182.67714 | V11: 2384.2466 | W11: 220.14287 | X11: 0 | Y11: 0 | Z11: 0 | AA11: 35.7 | AB11: 120.101 | AC11: -0.901 | AD11: 1.63 | AE11: 2.372 | AF11: -8.306994 | AG11: 0 | AH11: 1917.0818 | AI11: 333.39357 | AJ11: -2804.4338 | AK11: -1457.2437 | AL11: -170.33082 | AM11: -70.075905 | AN11: 2096.7391 | AO11: 187.02965 | AP11: 0 | AQ11: 0.142 | AR11: 0 | AS11: 33.461 | AT11: 50.492075 | AU11: 0.855474 | AV11: 2.58402 | AW11: 0.19286449 | AX11: 0.28035 | AY11: 1663.3734 | AZ11: 288.74353
A12: 2025 Q4 | B12: projection | C12: 0 | D12: 0.0059761162 | E12: 0.0080020266 | F12: 0.0080020266 | G12: 0.0080020266 | H12: 0.0064403633 | I12: 0.0057166677 | J12: 31084.87 | K12: 21194.877 | L12: -0.3 | M12: 2006.7629 | N12: 412.67229 | O12: 75.196143 | P12: 3341.6818 | Q12: 5021.9409 | R12: 2535.4148 | S12: 333.3376 | T12: 109.65876 | U12: 182.58555 | V12: 2376.613 | W12: 223.32468 | X12: 0 | Y12: 0 | Z12: 0 | AA12: 35.7 | AB12: 124.44 | AC12: -2.15 | AD12: 1.671 | AE12: 0.49 | AF12: -8.28246 | AG12: 0 | AH12: 1952.9785 | AI12: 336.60699 | AJ12: -2852.2647 | AK12: -1473.9975 | AL12: -167.46541 | AM12: -70.20209 | AN12: 2133.755 | AO12: 191.3102 | AP12: 0 | AQ12: 0.071 | AR12: 0 | AS12: 33.286 | AT12: 48.391423 | AU12: 0.573855 | AV12: 2.04112 | AW12: -1.6414568 | AX12: 0.250425 | AY12: 1700.7868 | AZ12: 293.76193
A13: 2026 Q1 | B13: projection | C13: 0 | D13: 0.0053360386 | E13: 0.0081899949 | F13: 0.0081899949 | G13: 0.0081899949 | H13: 0.0055705631 | I13: 0.0056799438 | J13: 31389.687 | K13: 21376.266 | L13: -0.24 | M13: 2051.1056 | N13: 415.45334 | O13: 75.196143 | P13: 3373.6674 | Q13: 5030.9373 | R13: 2559.0591 | S13: 331.27795 | T13: 134.70904 | U13: 182.80643 | V13: 2429.8021 | W13: 226.55247 | X13: 0 | Y13: 0 | Z13: 0 | AA13: 35.7 | AB13: 122.29 | AC13: 0 | AD13: 0 | AE13: 0 | AF13: -8.28246 | AG13: 0 | AH13: 1988.4213 | AI13: 341.03339 | AJ13: -2896.3043 | AK13: -1490.9727 | AL13: -164.53467 | AM13: -70.498971 | AN13: 2160.0809 | AO13: 196.542 | AP13: 0 | AQ13: 0 | AR13: 0 | AS13: 33.119 | AT13: 48.72343 | AU13: 0.378236 | AV13: 1.53068 | AW13: -3.3871227 | AX13: 0.222075 | AY13: 1740.6318 | AZ13: 299.28914
... A18: 2027 Q2 | B18: projection | C18: 0 | D18: 0.0054914305 | E18: 0.0074988973 | F18: 0.0074988973 | G18: 0.0074988973 | H18: 0.0050077163 | I18: 0.0054538948 | J18: 32894.354 | K18: 22328.33 | L18: -0.04 | M18: 2142.6243 | N18: 426.9721 | O18: 75.196143 | P18: 3522.338 | Q18: 5336.9703 | R18: 2679.991 | S18: 331.10723 | T18: 123.27491 | U18: 182.18149 | V18: 2546.7536 | W18: 243.40486 | X18: 0 | Y18: 0 | Z18: 0 | AA18: 37.7 | AB18: 122.29 | AC18: 0 | AD18: 0 | AE18: 0 | AF18: -11 | AG18: 0 | AH18: 2143.7597 | AI18: 359.51286 | AJ18: -3096.8635 | AK18: -1565.8192 | AL18: -144.2572 | AM18: -72.472075 | AN18: 2252.6794 | AO18: 214.42702 | AP18: 0 | AQ18: 0 | AR18: 0 | AS18: 33.057 | AT18: 52.057024 | AU18: -0.074613 | AV18: 0.11938 | AW18: -9.3859472 | AX18: 0.1008 | AY18: 1889.361 | AZ18: 317.90085

Sheet just ran
A2: 2023 Q2 | B2: historical | C2: -1 | D2: 0.006582718 | E2: -0.0073827309 | F2: 0.0021322445 | G2: -0.0056211973 | H2: 0.0073926308 | I2: 0.0056240488 | J2: 27530.1 | K2: 18693.1 | L2: 0 | M2: 1738.8 | N2: 436.07272 | O2: 76.015143 | P2: 2934.6 | Q2: 4210.6 | R2: 2236.1 | S2: 415.5 | T2: 46.245323 | U2: 170.2 | V2: 2006.4269 | W2: 183.8 | X2: 0 | Y2: 0 | Z2: 0 | AA2: 32.8 | AB2: 101.3 | AC2: 12.726 | AD2: 1.416 | AE2: 12 | AF2: 45 | AG2: 0.7 | AH2: 1659.996 | AI2: 267.104 | AJ2: -2564.838 | AK2: -1347.348 | AL2: -144.40667 | AM2: -55.99 | AN2: 1790.1942 | AO2: 188.1225 | AP2: 2.1784 | AQ2: 41.153 | AR2: 9.157 | AS2: 22.948 | AT2: 159.5619 | AU2: 14.28301 | AV2: 28.976026 | AW2: 40.95 | AX2: 0.5679 | AY2: 1444.3544 | AZ2: 210.74558
A3: 2023 Q3 | B3: historical | C3: -1 | D3: 0.0094033912 | E3: 0.016732699 | F3: 0.00035461796 | G3: 0.013706093 | H3: 0.0067310092 | I3: 0.0056687159 | J3: 28074.8 | K3: 18961.8 | L3: 0 | M3: 1784.4 | N3: 417.91594 | O3: 76.015143 | P3: 3005.4 | Q3: 4257.9 | R3: 2270.3 | S3: 428.4 | T3: 62.071265 | U3: 168.5 | V3: 2016.4269 | W3: 185.9 | X3: 0 | Y3: 0 | Z3: 0 | AA3: 34.9 | AB3: 103.5 | AC3: 12.726 | AD3: 1.416 | AE3: 12 | AF3: 2.081508 | AG3: 0.7 | AH3: 1613.65 | AI3: 290.05 | AJ3: -2589.162 | AK3: -1357.608 | AL3: -150.09667 | AM3: -58.886667 | AN3: 1810.0624 | AO3: 184.0275 | AP3: 0 | AQ3: 41.153 | AR3: 0.67 | AS3: 26.182 | AT3: 136.66702 | AU3: 14.499352 | AV3: 22.99411 | AW3: 32.366302 | AX3: 0.5706 | AY3: 1456.9297 | AZ3: 229.62533
A4: 2023 Q4 | B4: historical | C4: -1 | D4: 0.0070345423 | E4: 0.00071349046 | F4: 0.0032733965 | G4: 0.0011916352 | H4: 0.0045206985 | I4: 0.0057213587 | J4: 28424.7 | K4: 19190.6 | L4: 0 | M4: 1812 | N4: 434.04594 | O4: 77.674143 | P4: 3049 | Q4: 4302.2 | R4: 2301.1 | S4: 442.7 | T4: 68.31219 | U4: 172.7 | V4: 2024.999 | W4: 189.5 | X4: 0 | Y4: 0 | Z4: 0 | AA4: 35.5 | AB4: 98 | AC4: 1.365 | AD4: 1.479 | AE4: 4.222 | AF4: 2.100618 | AG4: 0.7 | AH4: 1658.388 | AI4: 252.912 | AJ4: -2609.964 | AK4: -1367.988 | AL4: -156.48667 | AM4: -62.036667 | AN4: 1814.9933 | AO4: 168.84 | AP4: 0 | AQ4: 41.153 | AR4: 0.174 | AS4: 28.155 | AT4: 126.927 | AU4: 14.261254 | AV4: 16.69038 | AW4: 25.07398 | AX4: 0.5733 | AY4: 1475.7446 | AZ4: 236.95538
A5: 2024 Q1 | B5: historical | C5: -1 | D5: 0.01026393 | E5: 0.008782995 | F5: 0.0044129366 | G5: 0.0079425584 | H5: 0.0088526155 | I5: 0.0057507902 | J5: 28708.2 | K5: 19443.8 | L5: 0 | M5: 1834.3 | N5: 437.85294 | O5: 77.674143 | P5: 3097.5 | Q5: 4390.9 | R5: 2325.5 | S5: 472.3 | T5: 78.014538 | U5: 173.2 | V5: 2131.899 | W5: 194.8 | X5: 0 | Y5: 0 | Z5: 0 | AA5: 35.5 | AB5: 95 | AC5: 1.365 | AD5: 1.479 | AE5: 4.222 | AF5: 2.58153 | AG5: 0.7 | AH5: 1680.381 | AI5: 298.119 | AJ5: -2614.512 | AK5: -1373.712 | AL5: -162.89667 | AM5: -65.09 | AN5: 1840.4441 | AO5: 169.65 | AP5: 0 | AQ5: 34.1285 | AR5: 0.08 | AS5: 29.581 | AT5: 118.68525 | AU5: 14.023156 | AV5: 12.61027 | AW5: 18.306452 | AX5: 0.5418 | AY5: 1487.7934 | AZ5: 249.34162
A6: 2024 Q2 | B6: historical | C6: -1 | D6: 0.0075830466 | E6: 0.0028193299 | F6: 0.0024774522 | G6: 0.0027475708 | H6: 0.0064180979 | I6: 0.0058015415 | J6: 29147 | K6: 19756.1 | L6: 0 | M6: 1867.5 | N6: 447.07611 | O6: 77.674143 | P6: 3127.6 | Q6: 4456.6 | R6: 2363.6 | S6: 495.3 | T6: 85.438722 | U6: 170.6 | V6: 2160.999 | W6: 199.2 | X6: 0 | Y6: 0 | Z6: 0 | AA6: 36.1 | AB6: 93 | AC6: 1.365 | AD6: 1.479 | AE6: 4.222 | AF6: 2.604045 | AG6: 0.7 | AH6: 1707.978 | AI6: 314.922 | AJ6: -2622.426 | AK6: -1378.08 | AL6: -168.09667 | AM6: -67.456667 | AN6: 1875.2229 | AO6: 173.115 | AP6: 0 | AQ6: 27.388 | AR6: 0.035 | AS6: 30.805 | AT6: 96.491025 | AU6: 13.047051 | AV6: 9.32794 | AW6: 11.957994 | AX6: 0.4005 | AY6: 1498.5893 | AZ6: 260.10068
A7: 2024 Q3 | B7: historical | C7: -1 | D7: 0.0059965041 | E7: 0.0039266712 | F7: 0.0065105722 | G7: 0.0044025399 | H7: 0.0042217342 | I7: 0.0057505722 | J7: 29511.7 | K7: 20032.8 | L7: 0 | M7: 1917.9 | N7: 468.80533 | O7: 77.674143 | P7: 3169.1 | Q7: 4526.7 | R7: 2400.1 | S7: 490.6 | T7: 79.629003 | U7: 170.1 | V7: 2181.299 | W7: 209 | X7: 0 | Y7: 0 | Z7: 0 | AA7: 37 | AB7: 92.1 | AC7: 1.365 | AD7: 1.479 | AE7: 4.222 | AF7: 2.626465 | AG7: 0.7 | AH7: 1744.359 | AI7: 315.441 | AJ7: -2629.842 | AK7: -1390.32 | AL7: -172.82667 | AM7: -69.003333 | AN7: 1912.3191 | AO7: 178.3125 | AP7: 0 | AQ7: 20.6475 | AR7: 0.012 | AS7: 31.843 | AT7: 75.838725 | AU7: 8.517842 | AV7: 6.35096 | AW7: 8.1834539 | AX7: 0.4014 | AY7: 1527.9988 | AZ7: 265.81365
A8: 2024 Q4 | B8: historical | C8: -1 | D8: 0.0059688045 | E8: 0.0032787138 | F8: 0.0035235298 | G8: 0.003325747 | H8: 0.0062373921 | I8: 0.0057438004 | J8: 29825.2 | K8: 20351.3 | L8: 0 | M8: 1950 | N8: 473.51933 | O8: 79.268143 | P8: 3200.8 | Q8: 4590.3 | R8: 2436.6 | S8: 508.6 | T8: 71.179167 | U8: 174.2 | V8: 2212.098 | W8: 204.3 | X8: 0 | Y8: 0 | Z8: 0 | AA8: 37.3 | AB8: 94 | AC8: -0.901 | AD8: 1.63 | AE8: 2.372 | AF8: 2.649835 | AG8: 0.7 | AH8: 1786.697 | AI8: 314.303 | AJ8: -2642.622 | AK8: -1404.93 | AL8: -177.31333 | AM8: -69.03 | AN8: 1954.4164 | AO8: 181.6425 | AP8: 0 | AQ8: 13.836 | AR8: 0 | AS8: 32.631 | AT8: 65.877975 | AU8: 6.576191 | AV8: 4.56094 | AW8: 6.1234738 | AX8: 0.4023 | AY8: 1556.8684 | AZ8: 279.62662
A9: 2025 Q1 | B9: historical | C9: -1 | D9: 0.014353684 | E9: 0.0099039593 | F9: 0.0066231529 | G9: 0.0092720593 | H9: 0.0084681203 | I9: 0.0056201408 | J9: 30042.1 | K9: 20555 | L9: 0 | M9: 1949.7 | N9: 435.153 | O9: 79.268143 | P9: 3245.8 | Q9: 4710.9 | R9: 2460.1 | S9: 469.2 | T9: 73.980636 | U9: 184.4 | V9: 2312.798 | W9: 203.3 | X9: 0 | Y9: 0 | Z9: 0 | AA9: 37.1 | AB9: 107 | AC9: -0.901 | AD9: 1.63 | AE9: 2.372 | AF9: 2.645442 | AG9: 0.7 | AH9: 1811.332 | AI9: 316.468 | AJ9: -2684.838 | AK9: -1421.406 | AL9: -180.12 | AM9: -69.02 | AN9: 1995.1186 | AO9: 183.555 | AP9: 0 | AQ9: 7.0245 | AR9: 0 | AS9: 33.123 | AT9: 61.47135 | AU9: 4.63454 | AV9: 3.85754 | AW9: 4.0318455 | AX9: 0.3861 | AY9: 1586.3323 | AZ9: 283.75515
A10: 2025 Q2 | B10: historical | C10: -1 | D10: 0.017075286 | E10: 0.0023603402 | F10: 0.0054340243 | G10: 0.0029513035 | H10: 0.0052878919 | I10: 0.0057178013 | J10: 30485.7 | K10: 20789.9 | L10: -0.3 | M10: 1956.4 | N10: 411.32562 | O10: 75.196143 | P10: 3280.6 | Q10: 4944.5 | R10: 2490.5 | S10: 470 | T10: 88.394443 | U10: 183 | V10: 2409.698 | W10: 203.5 | X10: 0 | Y10: 0 | Z10: 0 | AA10: 38 | AB10: 119.2 | AC10: -0.901 | AD10: 1.63 | AE10: 2.372 | AF10: 2.6696 | AG10: 0.7 | AH10: 1877.66 | AI10: 319.14 | AJ10: -2750.124 | AK10: -1439.904 | AL10: -181.6 | AM10: -69.64 | AN10: 2051.0759 | AO10: 184.5225 | AP10: 0 | AQ10: 0.213 | AR10: 0 | AS10: 33.62 | AT10: 55.2555 | AU10: 2.745007 | AV10: 3.17264 | AW10: 2.3533203 | AX10: 0.315 | AY10: 1624.5108 | AZ10: 284.7042
A11: 2025 Q3 | B11: projection | C11: 0 | D11: 7.4170933e-06 | E11: 0.0077455121 | F11: 0.0077455121 | G11: 0.0077455121 | H11: 0.0079484627 | I11: 0.0057366284 | J11: 30789.813 | K11: 20995.964 | L11: -0.3 | M11: 1979.7453 | N11: 413.92898 | O11: 75.196143 | P11: 3310.5813 | Q11: 4936.9814 | R11: 2509.6975 | S11: 78.824649 | T11: 103.08351 | U11: 182.67714 | V11: 2384.2466 | W11: 220.14287 | X11: 0 | Y11: 0 | Z11: 0 | AA11: 35.7 | AB11: 120.101 | AC11: -0.901 | AD11: 1.63 | AE11: 2.372 | AF11: -8.306994 | AG11: 0 | AH11: 1917.0818 | AI11: 333.39357 | AJ11: -2804.4338 | AK11: -1457.2437 | AL11: -170.33082 | AM11: -70.075905 | AN11: 2096.7391 | AO11: 187.02965 | AP11: 0 | AQ11: 0.142 | AR11: 0 | AS11: 33.461 | AT11: 50.492075 | AU11: 0.855474 | AV11: 2.58402 | AW11: 0.19286449 | AX11: 0.28035 | AY11: 1663.3734 | AZ11: 288.74353
A12: 2025 Q4 | B12: projection | C12: 0 | D12: 0.0059761162 | E12: 0.0080020266 | F12: 0.0080020266 | G12: 0.0080020266 | H12: 0.0064403633 | I12: 0.0057166677 | J12: 31084.87 | K12: 21194.877 | L12: -0.3 | M12: 2006.7629 | N12: 412.67229 | O12: 75.196143 | P12: 3341.6818 | Q12: 5021.9409 | R12: 2535.4148 | S12: 333.3376 | T12: 109.65876 | U12: 182.58555 | V12: 2376.613 | W12: 223.32468 | X12: 0 | Y12: 0 | Z12: 0 | AA12: 35.7 | AB12: 124.44 | AC12: -2.15 | AD12: 1.671 | AE12: 0.49 | AF12: -8.28246 | AG12: 0 | AH12: 1952.9785 | AI12: 336.60699 | AJ12: -2852.2647 | AK12: -1473.9975 | AL12: -167.46541 | AM12: -70.20209 | AN12: 2133.755 | AO12: 191.3102 | AP12: 0 | AQ12: 0.071 | AR12: 0 | AS12: 33.286 | AT12: 48.391423 | AU12: 0.573855 | AV12: 2.04112 | AW12: -1.6414568 | AX12: 0.250425 | AY12: 1700.7868 | AZ12: 293.76193
A13: 2026 Q1 | B13: projection | C13: 0 | D13: 0.0053360386 | E13: 0.0081899949 | F13: 0.0081899949 | G13: 0.0081899949 | H13: 0.0055705631 | I13: 0.0056799438 | J13: 31389.687 | K13: 21376.266 | L13: -0.24 | M13: 2051.1056 | N13: 415.45334 | O13: 75.196143 | P13: 3373.6674 | Q13: 5030.9373 | R13: 2559.0591 | S13: 331.27795 | T13: 134.70904 | U13: 182.80643 | V13: 2429.8021 | W13: 226.55247 | X13: 0 | Y13: 0 | Z13: 0 | AA13: 35.7 | AB13: 122.29 | AC13: 0 | AD13: 0 | AE13: 0 | AF13: -8.28246 | AG13: 0 | AH13: 1988.4213 | AI13: 341.03339 | AJ13: -2896.3043 | AK13: -1490.9727 | AL13: -164.53467 | AM13: -70.498971 | AN13: 2160.0809 | AO13: 196.542 | AP13: 0 | AQ13: 0 | AR13: 0 | AS13: 33.119 | AT13: 48.72343 | AU13: 0.378236 | AV13: 1.53068 | AW13: -3.3871227 | AX13: 0.222075 | AY13: 1740.6318 | AZ13: 299.28914
... A18: 2027 Q2 | B18: projection | C18: 0 | D18: 0.0054914305 | E18: 0.0074988973 | F18: 0.0074988973 | G18: 0.0074988973 | H18: 0.0050077163 | I18: 0.0054538948 | J18: 32894.354 | K18: 22328.33 | L18: -0.04 | M18: 2142.6243 | N18: 426.9721 | O18: 75.196143 | P18: 3522.338 | Q18: 5336.9703 | R18: 2679.991 | S18: 331.10723 | T18: 123.27491 | U18: 182.18149 | V18: 2546.7536 | W18: 243.40486 | X18: 0 | Y18: 0 | Z18: 0 | AA18: 37.7 | AB18: 122.29 | AC18: 0 | AD18: 0 | AE18: 0 | AF18: -11 | AG18: 0 | AH18: 2143.7597 | AI18: 359.51286 | AJ18: -3096.8635 | AK18: -1565.8192 | AL18: -144.2572 | AM18: -72.472075 | AN18: 2252.6794 | AO18: 214.42702 | AP18: 0 | AQ18: 0 | AR18: 0 | AS18: 33.057 | AT18: 52.057024 | AU18: -0.074613 | AV18: 0.11938 | AW18: -9.3859472 | AX18: 0.1008 | AY18: 1889.361 | AZ18: 317.90085

Sheet revert-pub
A1: date | B1: id | C1: recession | D1: federal_purchases_deflator_growth | E1: consumption_grants_deflator_growth | F1: investment_grants_deflator_growth | G1: state_purchases_deflator_growth | H1: consumption_deflator_growth | I1: real_potential_gdp_growth | J1: gdp | K1: consumption | L1: uncertainty | M1: federal_purchases | N1: consumption_grants | O1: investment_grants | P1: state_purchases | Q1: federal_non_corporate_taxes | R1: state_non_corporate_taxes | S1: federal_corporate_taxes | T1: supply_side_ira | U1: state_corporate_taxes | V1: federal_social_benefits | W1: state_social_benefits | X1: rebate_checks | Y1: rebate_checks_arp | Z1: federal_ui | AA1: state_ui | AB1: federal_subsidies | AC1: federal_aid_to_small_businesses_arp | AD1: federal_other_direct_aid_arp | AE1: federal_other_vulnerable_arp | AF1: federal_student_loans | AG1: state_subsidies | AH1: federal_health_outlays | AI1: state_health_outlays | AJ1: post_mpc_federal_non_corporate_taxes | AK1: post_mpc_state_non_corporate_taxes | AL1: post_mpc_federal_corporate_taxes | AM1: post_mpc_state_corporate_taxes | AN1: post_mpc_federal_social_benefits | AO1: post_mpc_state_social_benefits | AP1: post_mpc_rebate_checks | AQ1: post_mpc_rebate_checks_arp | AR1: post_mpc_federal_ui | AS1: post_mpc_state_ui | AT1: post_mpc_federal_subsidies | AU1: post_mpc_federal_aid_to_small_businesses_arp | AV1: post_mpc_federal_other_vulnerable_arp | AW1: post_mpc_federal_student_loans | AX1: post_mpc_state_subsidies | AY1: post_mpc_federal_health_outlays | AZ1: post_mpc_state_health_outlays
C2: =revert!D2-published!D2 -> 0 | D2: =revert!E2-published!E2 -> 0 | E2: =revert!F2-published!F2 -> 0 | F2: =revert!G2-published!G2 -> 0 | G2: =revert!H2-published!H2 -> 0 | H2: =revert!I2-published!I2 -> 0 | I2: =revert!J2-published!J2 -> 0 | J2: =revert!K2-published!K2 -> 0 | ... AR2: =revert!AS2-published!AS2 -> 0 | AS2: =revert!AT2-'just ran'!AT2 -> 0 | AT2: =revert!AU2-'just ran'!AU2 -> 0
C3: =revert!D3-published!D3 -> 0 | D3: =revert!E3-published!E3 -> 0 | E3: =revert!F3-published!F3 -> 0 | F3: =revert!G3-published!G3 -> 0 | G3: =revert!H3-published!H3 -> 0 | H3: =revert!I3-published!I3 -> 0 | I3: =revert!J3-published!J3 -> 0 | J3: =revert!K3-published!K3 -> 0 | ... AR3: =revert!AS3-published!AS3 -> 0 | AS3: =revert!AT3-'just ran'!AT3 -> 0 | AT3: =revert!AU3-'just ran'!AU3 -> 0
C4: =revert!D4-published!D4 -> 0 | D4: =revert!E4-published!E4 -> 0 | E4: =revert!F4-published!F4 -> 0 | F4: =revert!G4-published!G4 -> 0 | G4: =revert!H4-published!H4 -> 0 | H4: =revert!I4-published!I4 -> 0 | I4: =revert!J4-published!J4 -> 0 | J4: =revert!K4-published!K4 -> 0 | ... AR4: =revert!AS4-published!AS4 -> 0 | AS4: =revert!AT4-'just ran'!AT4 -> 0 | AT4: =revert!AU4-'just ran'!AU4 -> 0
C5: =revert!D5-published!D5 -> 0 | D5: =revert!E5-published!E5 -> 0 | E5: =revert!F5-published!F5 -> 0 | F5: =revert!G5-published!G5 -> 0 | G5: =revert!H5-published!H5 -> 0 | H5: =revert!I5-published!I5 -> 0 | I5: =revert!J5-published!J5 -> 0 | J5: =revert!K5-published!K5 -> 0 | ... AR5: =revert!AS5-published!AS5 -> 0 | AS5: =revert!AT5-'just ran'!AT5 -> 0 | AT5: =revert!AU5-'just ran'!AU5 -> 0
C6: =revert!D6-published!D6 -> 0 | D6: =revert!E6-published!E6 -> 0 | E6: =revert!F6-published!F6 -> 0 | F6: =revert!G6-published!G6 -> 0 | G6: =revert!H6-published!H6 -> 0 | H6: =revert!I6-published!I6 -> 0 | I6: =revert!J6-published!J6 -> 0 | J6: =revert!K6-published!K6 -> 0 | ... AR6: =revert!AS6-published!AS6 -> 0 | AS6: =revert!AT6-'just ran'!AT6 -> 0 | AT6: =revert!AU6-'just ran'!AU6 -> 0
C7: =revert!D7-published!D7 -> 0 | D7: =revert!E7-published!E7 -> 0 | E7: =revert!F7-published!F7 -> 0 | F7: =revert!G7-published!G7 -> 0 | G7: =revert!H7-published!H7 -> 0 | H7: =revert!I7-published!I7 -> 0 | I7: =revert!J7-published!J7 -> 0 | J7: =revert!K7-published!K7 -> 0 | ... AR7: =revert!AS7-published!AS7 -> 0 | AS7: =revert!AT7-'just ran'!AT7 -> 0 | AT7: =revert!AU7-'just ran'!AU7 -> 0
C8: =revert!D8-published!D8 -> 0 | D8: =revert!E8-published!E8 -> 0 | E8: =revert!F8-published!F8 -> 0 | F8: =revert!G8-published!G8 -> 0 | G8: =revert!H8-published!H8 -> 0 | H8: =revert!I8-published!I8 -> 0 | I8: =revert!J8-published!J8 -> 0 | J8: =revert!K8-published!K8 -> 0 | ... AR8: =revert!AS8-published!AS8 -> 0 | AS8: =revert!AT8-'just ran'!AT8 -> 0 | AT8: =revert!AU8-'just ran'!AU8 -> 0
C9: =revert!D9-published!D9 -> 0 | D9: =revert!E9-published!E9 -> 0 | E9: =revert!F9-published!F9 -> 0 | F9: =revert!G9-published!G9 -> 0 | G9: =revert!H9-published!H9 -> 0 | H9: =revert!I9-published!I9 -> 0 | I9: =revert!J9-published!J9 -> 0 | J9: =revert!K9-published!K9 -> 0 | ... AR9: =revert!AS9-published!AS9 -> 0 | AS9: =revert!AT9-'just ran'!AT9 -> 0 | AT9: =revert!AU9-'just ran'!AU9 -> 0
C10: =revert!D10-published!D10 -> 0 | D10: =revert!E10-published!E10 -> 0 | E10: =revert!F10-published!F10 -> 0 | F10: =revert!G10-published!G10 -> 0 | G10: =revert!H10-published!H10 -> 0 | H10: =revert!I10-published!I10 -> 0 | I10: =revert!J10-published!J10 -> 0 | J10: =revert!K10-published!K10 -> 0 | ... AR10: =revert!AS10-published!AS10 -> 0 | AS10: =revert!AT10-'just ran'!AT10 -> 0 | AT10: =revert!AU10-'just ran'!AU10 -> 0
C11: =revert!D11-published!D11 -> 0 | D11: =revert!E11-published!E11 -> 0 | E11: =revert!F11-published!F11 -> 0 | F11: =revert!G11-published!G11 -> 0 | G11: =revert!H11-published!H11 -> 0 | H11: =revert!I11-published!I11 -> 0 | I11: =revert!J11-published!J11 -> 0 | J11: =revert!K11-published!K11 -> 0 | ... AR11: =revert!AS11-published!AS11 -> 0 | AS11: =revert!AT11-'just ran'!AT11 -> 0 | AT11: =revert!AU11-'just ran'!AU11 -> 0
C12: =revert!D12-published!D12 -> 0 | D12: =revert!E12-published!E12 -> 0 | E12: =revert!F12-published!F12 -> 0 | F12: =revert!G12-published!G12 -> 0 | G12: =revert!H12-published!H12 -> 0 | H12: =revert!I12-published!I12 -> 0 | I12: =revert!J12-published!J12 -> 0 | J12: =revert!K12-published!K12 -> 0 | ... AR12: =revert!AS12-published!AS12 -> 0 | AS12: =revert!AT12-'just ran'!AT12 -> 0 | AT12: =revert!AU12-'just ran'!AU12 -> 0
C13: =revert!D13-published!D13 -> 0 | D13: =revert!E13-published!E13 -> 0 | E13: =revert!F13-published!F13 -> 0 | F13: =revert!G13-published!G13 -> 0 | G13: =revert!H13-published!H13 -> 0 | H13: =revert!I13-published!I13 -> 0 | I13: =revert!J13-published!J13 -> 0 | J13: =revert!K13-published!K13 -> 0 | ... AR13: =revert!AS13-published!AS13 -> 0 | AS13: =revert!AT13-'just ran'!AT13 -> 0 | AT13: =revert!AU13-'just ran'!AU13 -> 0
... C21: =revert!D21-published!D21 -> 0 | D21: =revert!E21-published!E21 -> 0 | E21: =revert!F21-published!F21 -> 0 | F21: =revert!G21-published!G21 -> 0 | G21: =revert!H21-published!H21 -> 0 | H21: =revert!I21-published!I21 -> 0 | I21: =revert!J21-published!J21 -> 0 | J21: =revert!K21-published!K21 -> 0 | ... AR21: =revert!AS21-published!AS21 -> 0 | AS21: =revert!AT21-'just ran'!AT21 -> 0 | AT21: =revert!AU21-'just ran'!AU21 -> 0

Sheet published
A1: date | B1: id | C1: recession | D1: federal_purchases_deflator_growth | E1: consumption_grants_deflator_growth | F1: investment_grants_deflator_growth | G1: state_purchases_deflator_growth | H1: consumption_deflator_growth | I1: real_potential_gdp_growth | J1: gdp | K1: consumption | L1: uncertainty | M1: federal_purchases | N1: consumption_grants | O1: investment_grants | P1: state_purchases | Q1: federal_non_corporate_taxes | R1: state_non_corporate_taxes | S1: federal_corporate_taxes | T1: supply_side_ira | U1: state_corporate_taxes | V1: federal_social_benefits | W1: state_social_benefits | X1: rebate_checks | Y1: rebate_checks_arp | Z1: federal_ui | AA1: state_ui | AB1: federal_subsidies | AC1: federal_aid_to_small_businesses_arp | AD1: federal_other_direct_aid_arp | AE1: federal_other_vulnerable_arp | AF1: federal_student_loans | AG1: state_subsidies | AH1: federal_health_outlays | AI1: state_health_outlays | AJ1: post_mpc_federal_non_corporate_taxes | AK1: post_mpc_state_non_corporate_taxes | AL1: post_mpc_federal_corporate_taxes | AM1: post_mpc_state_corporate_taxes | AN1: post_mpc_federal_social_benefits | AO1: post_mpc_state_social_benefits | AP1: post_mpc_rebate_checks | AQ1: post_mpc_rebate_checks_arp | AR1: post_mpc_federal_ui | AS1: post_mpc_state_ui | AT1: post_mpc_federal_subsidies | AU1: post_mpc_federal_aid_to_small_businesses_arp | AV1: post_mpc_federal_other_vulnerable_arp | AW1: post_mpc_federal_student_loans | AX1: post_mpc_state_subsidies | AY1: post_mpc_federal_health_outlays | AZ1: post_mpc_state_health_outlays
A2: 2023 Q2 | B2: historical | C2: -1 | D2: 0.006582718 | E2: -0.0073827309 | F2: 0.0021322445 | G2: -0.0056211973 | H2: 0.0073926308 | I2: 0.0056240488 | J2: 27530.1 | K2: 18693.1 | L2: 0 | M2: 1738.8 | N2: 436.07272 | O2: 76.015143 | P2: 2934.6 | Q2: 4210.6 | R2: 2236.1 | S2: 429.4 | T2: 46.245323 | U2: 170.2 | V2: 2006.4269 | W2: 183.8 | X2: 0 | Y2: 0 | Z2: 0 | AA2: 32.8 | AB2: 101.3 | AC2: 12.726 | AD2: 1.416 | AE2: 12 | AF2: 45 | AG2: 0.7 | AH2: 1659.996 | AI2: 267.104 | AJ2: -2564.838 | AK2: -1347.348 | AL2: -143.85 | AM2: -55.99 | AN2: 1790.1942 | AO2: 188.1225 | AP2: 2.1784 | AQ2: 41.153 | AR2: 9.157 | AS2: 22.948 | AT2: 159.5619 | AU2: 14.28301 | AV2: 28.976026 | AW2: 40.95 | AX2: 0.5679 | AY2: 1444.3544 | AZ2: 210.74558
A3: 2023 Q3 | B3: historical | C3: -1 | D3: 0.0094033912 | E3: 0.016732699 | F3: 0.00035461796 | G3: 0.013706093 | H3: 0.0067310092 | I3: 0.0056687159 | J3: 28074.8 | K3: 18961.8 | L3: 0 | M3: 1784.4 | N3: 417.91594 | O3: 76.015143 | P3: 3005.4 | Q3: 4257.9 | R3: 2270.3 | S3: 451.9 | T3: 62.071265 | U3: 168.5 | V3: 2016.4269 | W3: 185.9 | X3: 0 | Y3: 0 | Z3: 0 | AA3: 34.9 | AB3: 103.5 | AC3: 12.726 | AD3: 1.416 | AE3: 12 | AF3: 2.081508 | AG3: 0.7 | AH3: 1613.65 | AI3: 290.05 | AJ3: -2589.162 | AK3: -1357.608 | AL3: -150.29333 | AM3: -58.886667 | AN3: 1810.0624 | AO3: 184.0275 | AP3: 0 | AQ3: 41.153 | AR3: 0.67 | AS3: 26.182 | AT3: 136.66702 | AU3: 14.499352 | AV3: 22.99411 | AW3: 32.366302 | AX3: 0.5706 | AY3: 1456.9297 | AZ3: 229.62533
A4: 2023 Q4 | B4: historical | C4: -1 | D4: 0.0070345423 | E4: 0.00071349046 | F4: 0.0032733965 | G4: 0.0011916352 | H4: 0.0045206985 | I4: 0.0057213587 | J4: 28424.7 | K4: 19190.6 | L4: 0 | M4: 1812 | N4: 434.04594 | O4: 77.674143 | P4: 3049 | Q4: 4302.2 | R4: 2301.1 | S4: 464.8 | T4: 68.31219 | U4: 172.7 | V4: 2024.999 | W4: 189.5 | X4: 0 | Y4: 0 | Z4: 0 | AA4: 35.5 | AB4: 98 | AC4: 1.365 | AD4: 1.479 | AE4: 4.222 | AF4: 2.100618 | AG4: 0.7 | AH4: 1658.388 | AI4: 252.912 | AJ4: -2609.964 | AK4: -1367.988 | AL4: -157.41333 | AM4: -62.036667 | AN4: 1814.9933 | AO4: 168.84 | AP4: 0 | AQ4: 41.153 | AR4: 0.174 | AS4: 28.155 | AT4: 126.927 | AU4: 14.261254 | AV4: 16.69038 | AW4: 25.07398 | AX4: 0.5733 | AY4: 1475.7446 | AZ4: 236.95538
A5: 2024 Q1 | B5: historical | C5: -1 | D5: 0.01026393 | E5: 0.008782995 | F5: 0.0044129366 | G5: 0.0079425584 | H5: 0.0088526155 | I5: 0.0057507902 | J5: 28708.2 | K5: 19443.8 | L5: 0 | M5: 1834.3 | N5: 437.85294 | O5: 77.674143 | P5: 3097.5 | Q5: 4390.9 | R5: 2325.5 | S5: 459.9 | T5: 78.014538 | U5: 173.2 | V5: 2131.899 | W5: 194.8 | X5: 0 | Y5: 0 | Z5: 0 | AA5: 35.5 | AB5: 95 | AC5: 1.365 | AD5: 1.479 | AE5: 4.222 | AF5: 2.58153 | AG5: 0.7 | AH5: 1680.381 | AI5: 298.119 | AJ5: -2614.512 | AK5: -1373.712 | AL5: -163.08 | AM5: -65.09 | AN5: 1840.4441 | AO5: 169.65 | AP5: 0 | AQ5: 34.1285 | AR5: 0.08 | AS5: 29.581 | AT5: 118.68525 | AU5: 14.023156 | AV5: 12.61027 | AW5: 18.306452 | AX5: 0.5418 | AY5: 1487.7934 | AZ5: 249.34162
A6: 2024 Q2 | B6: historical | C6: -1 | D6: 0.0075830466 | E6: 0.0028193299 | F6: 0.0024774522 | G6: 0.0027475708 | H6: 0.0064180979 | I6: 0.0058015415 | J6: 29147 | K6: 19756.1 | L6: 0 | M6: 1867.5 | N6: 447.07611 | O6: 77.674143 | P6: 3127.6 | Q6: 4456.6 | R6: 2363.6 | S6: 493.4 | T6: 85.438722 | U6: 170.6 | V6: 2160.999 | W6: 199.2 | X6: 0 | Y6: 0 | Z6: 0 | AA6: 36.1 | AB6: 93 | AC6: 1.365 | AD6: 1.479 | AE6: 4.222 | AF6: 2.604045 | AG6: 0.7 | AH6: 1707.978 | AI6: 314.922 | AJ6: -2622.426 | AK6: -1378.08 | AL6: -168.06333 | AM6: -67.456667 | AN6: 1875.2229 | AO6: 173.115 | AP6: 0 | AQ6: 27.388 | AR6: 0.035 | AS6: 30.805 | AT6: 96.491025 | AU6: 13.047051 | AV6: 9.32794 | AW6: 11.957994 | AX6: 0.4005 | AY6: 1498.5893 | AZ6: 260.10068
A7: 2024 Q3 | B7: historical | C7: -1 | D7: 0.0059965041 | E7: 0.0039266712 | F7: 0.0065105722 | G7: 0.0044025399 | H7: 0.0042217342 | I7: 0.0057505722 | J7: 29511.7 | K7: 20032.8 | L7: 0 | M7: 1917.9 | N7: 468.80533 | O7: 77.674143 | P7: 3169.1 | Q7: 4526.7 | R7: 2400.1 | S7: 493.1 | T7: 79.629003 | U7: 170.1 | V7: 2181.299 | W7: 209 | X7: 0 | Y7: 0 | Z7: 0 | AA7: 37 | AB7: 92.1 | AC7: 1.365 | AD7: 1.479 | AE7: 4.222 | AF7: 2.626465 | AG7: 0.7 | AH7: 1744.359 | AI7: 315.441 | AJ7: -2629.842 | AK7: -1390.32 | AL7: -173.01667 | AM7: -69.003333 | AN7: 1912.3191 | AO7: 178.3125 | AP7: 0 | AQ7: 20.6475 | AR7: 0.012 | AS7: 31.843 | AT7: 75.838725 | AU7: 8.517842 | AV7: 6.35096 | AW7: 8.1834539 | AX7: 0.4014 | AY7: 1527.9988 | AZ7: 265.81365
A8: 2024 Q4 | B8: historical | C8: -1 | D8: 0.0059688045 | E8: 0.0032787138 | F8: 0.0035235298 | G8: 0.003325747 | H8: 0.0062373921 | I8: 0.0057438004 | J8: 29825.2 | K8: 20351.3 | L8: 0 | M8: 1950 | N8: 473.51933 | O8: 79.268143 | P8: 3200.8 | Q8: 4590.3 | R8: 2436.6 | S8: 512.1 | T8: 71.179167 | U8: 174.2 | V8: 2212.098 | W8: 204.3 | X8: 0 | Y8: 0 | Z8: 0 | AA8: 37.3 | AB8: 94 | AC8: -0.901 | AD8: 1.63 | AE8: 2.372 | AF8: 2.649835 | AG8: 0.7 | AH8: 1786.697 | AI8: 314.303 | AJ8: -2642.622 | AK8: -1404.93 | AL8: -178.15667 | AM8: -69.03 | AN8: 1954.4164 | AO8: 181.6425 | AP8: 0 | AQ8: 13.836 | AR8: 0 | AS8: 32.631 | AT8: 65.877975 | AU8: 6.576191 | AV8: 4.56094 | AW8: 6.1234738 | AX8: 0.4023 | AY8: 1556.8684 | AZ8: 279.62662
A9: 2025 Q1 | B9: historical | C9: -1 | D9: 0.014353684 | E9: 0.0099039593 | F9: 0.0066231529 | G9: 0.0092720593 | H9: 0.0084681203 | I9: 0.0056201408 | J9: 30042.1 | K9: 20555 | L9: 0 | M9: 1949.7 | N9: 435.153 | O9: 79.268143 | P9: 3245.8 | Q9: 4710.9 | R9: 2460.1 | S9: 519.8 | T9: 73.980636 | U9: 184.4 | V9: 2312.798 | W9: 203.3 | X9: 0 | Y9: 0 | Z9: 0 | AA9: 37.1 | AB9: 107 | AC9: -0.901 | AD9: 1.63 | AE9: 2.372 | AF9: 2.645442 | AG9: 0.7 | AH9: 1811.332 | AI9: 316.468 | AJ9: -2684.838 | AK9: -1421.406 | AL9: -182.83 | AM9: -69.02 | AN9: 1995.1186 | AO9: 183.555 | AP9: 0 | AQ9: 7.0245 | AR9: 0 | AS9: 33.123 | AT9: 61.47135 | AU9: 4.63454 | AV9: 3.85754 | AW9: 4.0318455 | AX9: 0.3861 | AY9: 1586.3323 | AZ9: 283.75515
A10: 2025 Q2 | B10: historical | C10: -1 | D10: 0.017075286 | E10: 0.0023603402 | F10: 0.0054340243 | G10: 0.0029513035 | H10: 0.0052878919 | I10: 0.0057178013 | J10: 30485.7 | K10: 20789.9 | L10: -0.3 | M10: 1956.4 | N10: 411.32562 | O10: 75.196143 | P10: 3280.6 | Q10: 4944.5 | R10: 2490.5 | S10: 532.1 | T10: 88.394443 | U10: 183 | V10: 2409.698 | W10: 203.5 | X10: 0 | Y10: 0 | Z10: 0 | AA10: 38 | AB10: 119.2 | AC10: -0.901 | AD10: 1.63 | AE10: 2.372 | AF10: 2.6696 | AG10: 0.7 | AH10: 1877.66 | AI10: 319.14 | AJ10: -2750.124 | AK10: -1439.904 | AL10: -186.66333 | AM10: -69.64 | AN10: 2051.0759 | AO10: 184.5225 | AP10: 0 | AQ10: 0.213 | AR10: 0 | AS10: 33.62 | AT10: 55.2555 | AU10: 2.745007 | AV10: 3.17264 | AW10: 2.3533203 | AX10: 0.315 | AY10: 1624.5108 | AZ10: 284.7042
A11: 2025 Q3 | B11: projection | C11: 0 | D11: 7.4170933e-06 | E11: 0.0077455121 | F11: 0.0077455121 | G11: 0.0077455121 | H11: 0.0079484627 | I11: 0.0057366284 | J11: 30789.813 | K11: 20995.964 | L11: -0.3 | M11: 1979.7453 | N11: 413.92898 | O11: 75.196143 | P11: 3310.5813 | Q11: 4936.9814 | R11: 2509.6975 | S11: 78.824649 | T11: 103.08351 | U11: 182.67714 | V11: 2384.2466 | W11: 220.14287 | X11: 0 | Y11: 0 | Z11: 0 | AA11: 35.7 | AB11: 120.101 | AC11: -0.901 | AD11: 1.63 | AE11: 2.372 | AF11: -8.306994 | AG11: 0 | AH11: 1917.0818 | AI11: 333.39357 | AJ11: -2804.4338 | AK11: -1457.2437 | AL11: -175.88415 | AM11: -70.075905 | AN11: 2096.7391 | AO11: 187.02965 | AP11: 0 | AQ11: 0.142 | AR11: 0 | AS11: 33.461 | AT11: 50.492075 | AU11: 0.855474 | AV11: 2.58402 | AW11: 0.19286449 | AX11: 0.28035 | AY11: 1663.3734 | AZ11: 288.74353
A12: 2025 Q4 | B12: projection | C12: 0 | D12: 0.0059761162 | E12: 0.0080020266 | F12: 0.0080020266 | G12: 0.0080020266 | H12: 0.0064403633 | I12: 0.0057166677 | J12: 31084.87 | K12: 21194.877 | L12: -0.3 | M12: 2006.7629 | N12: 412.67229 | O12: 75.196143 | P12: 3341.6818 | Q12: 5021.9409 | R12: 2535.4148 | S12: 333.3376 | T12: 109.65876 | U12: 182.58555 | V12: 2376.613 | W12: 223.32468 | X12: 0 | Y12: 0 | Z12: 0 | AA12: 35.7 | AB12: 124.44 | AC12: -2.15 | AD12: 1.671 | AE12: 0.49 | AF12: -8.28246 | AG12: 0 | AH12: 1952.9785 | AI12: 336.60699 | AJ12: -2852.2647 | AK12: -1473.9975 | AL12: -173.43208 | AM12: -70.20209 | AN12: 2133.755 | AO12: 191.3102 | AP12: 0 | AQ12: 0.071 | AR12: 0 | AS12: 33.286 | AT12: 48.391423 | AU12: 0.573855 | AV12: 2.04112 | AW12: -1.6414568 | AX12: 0.250425 | AY12: 1700.7868 | AZ12: 293.76193
A13: 2026 Q1 | B13: projection | C13: 0 | D13: 0.0053360386 | E13: 0.0081899949 | F13: 0.0081899949 | G13: 0.0081899949 | H13: 0.0055705631 | I13: 0.0056799438 | J13: 31389.687 | K13: 21376.266 | L13: -0.24 | M13: 2051.1056 | N13: 415.45334 | O13: 75.196143 | P13: 3373.6674 | Q13: 5030.9373 | R13: 2559.0591 | S13: 331.27795 | T13: 134.70904 | U13: 182.80643 | V13: 2429.8021 | W13: 226.55247 | X13: 0 | Y13: 0 | Z13: 0 | AA13: 35.7 | AB13: 122.29 | AC13: 0 | AD13: 0 | AE13: 0 | AF13: -8.28246 | AG13: 0 | AH13: 1988.4213 | AI13: 341.03339 | AJ13: -2896.3043 | AK13: -1490.9727 | AL13: -169.99801 | AM13: -70.498971 | AN13: 2160.0809 | AO13: 196.542 | AP13: 0 | AQ13: 0 | AR13: 0 | AS13: 33.119 | AT13: 48.72343 | AU13: 0.378236 | AV13: 1.53068 | AW13: -3.3871227 | AX13: 0.222075 | AY13: 1740.6318 | AZ13: 299.28914
... A18: 2027 Q2 | B18: projection | C18: 0 | D18: 0.0054914305 | E18: 0.0074988973 | F18: 0.0074988973 | G18: 0.0074988973 | H18: 0.0050077163 | I18: 0.0054538948 | J18: 32894.354 | K18: 22328.33 | L18: -0.04 | M18: 2142.6243 | N18: 426.9721 | O18: 75.196143 | P18: 3522.338 | Q18: 5336.9703 | R18: 2679.991 | S18: 331.10723 | T18: 123.27491 | U18: 182.18149 | V18: 2546.7536 | W18: 243.40486 | X18: 0 | Y18: 0 | Z18: 0 | AA18: 37.7 | AB18: 122.29 | AC18: 0 | AD18: 0 | AE18: 0 | AF18: -11 | AG18: 0 | AH18: 2143.7597 | AI18: 359.51286 | AJ18: -3096.8635 | AK18: -1565.8192 | AL18: -148.21387 | AM18: -72.472075 | AN18: 2252.6794 | AO18: 214.42702 | AP18: 0 | AQ18: 0 | AR18: 0 | AS18: 33.057 | AT18: 52.057024 | AU18: -0.074613 | AV18: 0.11938 | AW18: -9.3859472 | AX18: 0.1008 | AY18: 1889.361 | AZ18: 317.90085

Sheet diff
A1: date | B1: id | C1: recession | D1: federal_purchases_deflator_growth | E1: consumption_grants_deflator_growth | F1: investment_grants_deflator_growth | G1: state_purchases_deflator_growth | H1: consumption_deflator_growth | I1: real_potential_gdp_growth | J1: gdp | K1: consumption | L1: uncertainty | M1: federal_purchases | N1: consumption_grants | O1: investment_grants | P1: state_purchases | Q1: federal_non_corporate_taxes | R1: state_non_corporate_taxes | S1: federal_corporate_taxes | T1: supply_side_ira | U1: state_corporate_taxes | V1: federal_social_benefits | W1: state_social_benefits | X1: rebate_checks | Y1: rebate_checks_arp | Z1: federal_ui | AA1: state_ui | AB1: federal_subsidies | AC1: federal_aid_to_small_businesses_arp | AD1: federal_other_direct_aid_arp | AE1: federal_other_vulnerable_arp | AF1: federal_student_loans | AG1: state_subsidies | AH1: federal_health_outlays | AI1: state_health_outlays | AJ1: post_mpc_federal_non_corporate_taxes | AK1: post_mpc_state_non_corporate_taxes | AL1: post_mpc_federal_corporate_taxes | AM1: post_mpc_state_corporate_taxes | AN1: post_mpc_federal_social_benefits | AO1: post_mpc_state_social_benefits | AP1: post_mpc_rebate_checks | AQ1: post_mpc_rebate_checks_arp | AR1: post_mpc_federal_ui | AS1: post_mpc_state_ui | AT1: post_mpc_federal_subsidies | AU1: post_mpc_federal_aid_to_small_businesses_arp | AV1: post_mpc_federal_other_vulnerable_arp | AW1: post_mpc_federal_student_loans | AX1: post_mpc_state_subsidies | AY1: post_mpc_federal_health_outlays | AZ1: post_mpc_state_health_outlays
A2: 2023 Q2 | B2: historical | C2: -1 | D2: =revert!D2-published!D2 -> 0 | E2: =revert!E2-published!E2 -> 0 | F2: =revert!F2-published!F2 -> 0 | G2: =revert!G2-published!G2 -> 0 | H2: =revert!H2-published!H2 -> 0 | I2: =revert!I2-published!I2 -> 0 | J2: =revert!J2-published!J2 -> 0 | K2: =revert!K2-published!K2 -> 0 | ... AX2: =revert!AX2-published!AX2 -> 0
A3: 2023 Q3 | B3: historical | C3: -1 | D3: =revert!D3-published!D3 -> 0 | E3: =revert!E3-published!E3 -> 0 | F3: =revert!F3-published!F3 -> 0 | G3: =revert!G3-published!G3 -> 0 | H3: =revert!H3-published!H3 -> 0 | I3: =revert!I3-published!I3 -> 0 | J3: =revert!J3-published!J3 -> 0 | K3: =revert!K3-published!K3 -> 0 | ... AX3: =revert!AX3-published!AX3 -> 0
A4: 2023 Q4 | B4: historical | C4: -1 | D4: =revert!D4-published!D4 -> 0 | E4: =revert!E4-published!E4 -> 0 | F4: =revert!F4-published!F4 -> 0 | G4: =revert!G4-published!G4 -> 0 | H4: =revert!H4-published!H4 -> 0 | I4: =revert!I4-published!I4 -> 0 | J4: =revert!J4-published!J4 -> 0 | K4: =revert!K4-published!K4 -> 0 | ... AX4: =revert!AX4-published!AX4 -> 0
A5: 2024 Q1 | B5: historical | C5: -1 | D5: =revert!D5-published!D5 -> 0 | E5: =revert!E5-published!E5 -> 0 | F5: =revert!F5-published!F5 -> 0 | G5: =revert!G5-published!G5 -> 0 | H5: =revert!H5-published!H5 -> 0 | I5: =revert!I5-published!I5 -> 0 | J5: =revert!J5-published!J5 -> 0 | K5: =revert!K5-published!K5 -> 0 | ... AX5: =revert!AX5-published!AX5 -> 0
A6: 2024 Q2 | B6: historical | C6: -1 | D6: =revert!D6-published!D6 -> 0 | E6: =revert!E6-published!E6 -> 0 | F6: =revert!F6-published!F6 -> 0 | G6: =revert!G6-published!G6 -> 0 | H6: =revert!H6-published!H6 -> 0 | I6: =revert!I6-published!I6 -> 0 | J6: =revert!J6-published!J6 -> 0 | K6: =revert!K6-published!K6 -> 0 | ... AX6: =revert!AX6-published!AX6 -> 0
A7: 2024 Q3 | B7: historical | C7: -1 | D7: =revert!D7-published!D7 -> 0 | E7: =revert!E7-published!E7 -> 0 | F7: =revert!F7-published!F7 -> 0 | G7: =revert!G7-published!G7 -> 0 | H7: =revert!H7-published!H7 -> 0 | I7: =revert!I7-published!I7 -> 0 | J7: =revert!J7-published!J7 -> 0 | K7: =revert!K7-published!K7 -> 0 | ... AX7: =revert!AX7-published!AX7 -> 0
A8: 2024 Q4 | B8: historical | C8: -1 | D8: =revert!D8-published!D8 -> 0 | E8: =revert!E8-published!E8 -> 0 | F8: =revert!F8-published!F8 -> 0 | G8: =revert!G8-published!G8 -> 0 | H8: =revert!H8-published!H8 -> 0 | I8: =revert!I8-published!I8 -> 0 | J8: =revert!J8-published!J8 -> 0 | K8: =revert!K8-published!K8 -> 0 | ... AX8: =revert!AX8-published!AX8 -> 0
A9: 2025 Q1 | B9: historical | C9: -1 | D9: =revert!D9-published!D9 -> 0 | E9: =revert!E9-published!E9 -> 0 | F9: =revert!F9-published!F9 -> 0 | G9: =revert!G9-published!G9 -> 0 | H9: =revert!H9-published!H9 -> 0 | I9: =revert!I9-published!I9 -> 0 | J9: =revert!J9-published!J9 -> 0 | K9: =revert!K9-published!K9 -> 0 | ... AX9: =revert!AX9-published!AX9 -> 0
A10: 2025 Q2 | B10: historical | C10: -1 | D10: =revert!D10-published!D10 -> 0 | E10: =revert!E10-published!E10 -> 0 | F10: =revert!F10-published!F10 -> 0 | G10: =revert!G10-published!G10 -> 0 | H10: =revert!H10-published!H10 -> 0 | I10: =revert!I10-published!I10 -> 0 | J10: =revert!J10-published!J10 -> 0 | K10: =revert!K10-published!K10 -> 0 | ... AX10: =revert!AX10-published!AX10 -> 0
A11: 2025 Q3 | B11: projection | C11: 0 | D11: =revert!D11-published!D11 -> 0 | E11: =revert!E11-published!E11 -> 0 | F11: =revert!F11-published!F11 -> 0 | G11: =revert!G11-published!G11 -> 0 | H11: =revert!H11-published!H11 -> 0 | I11: =revert!I11-published!I11 -> 0 | J11: =revert!J11-published!J11 -> 0 | K11: =revert!K11-published!K11 -> 0 | ... AX11: =revert!AX11-published!AX11 -> 0
A12: 2025 Q4 | B12: projection | C12: 0 | D12: =revert!D12-published!D12 -> 0 | E12: =revert!E12-published!E12 -> 0 | F12: =revert!F12-published!F12 -> 0 | G12: =revert!G12-published!G12 -> 0 | H12: =revert!H12-published!H12 -> 0 | I12: =revert!I12-published!I12 -> 0 | J12: =revert!J12-published!J12 -> 0 | K12: =revert!K12-published!K12 -> 0 | ... AX12: =revert!AX12-published!AX12 -> 0
A13: 2026 Q1 | B13: projection | C13: 0 | D13: =revert!D13-published!D13 -> 0 | E13: =revert!E13-published!E13 -> 0 | F13: =revert!F13-published!F13 -> 0 | G13: =revert!G13-published!G13 -> 0 | H13: =revert!H13-published!H13 -> 0 | I13: =revert!I13-published!I13 -> 0 | J13: =revert!J13-published!J13 -> 0 | K13: =revert!K13-published!K13 -> 0 | ... AX13: =revert!AX13-published!AX13 -> 0
... A18: 2027 Q2 | B18: projection | C18: 0 | D18: =revert!D18-published!D18 -> 0 | E18: =revert!E18-published!E18 -> 0 | F18: =revert!F18-published!F18 -> 0 | G18: =revert!G18-published!G18 -> 0 | H18: =revert!H18-published!H18 -> 0 | I18: =revert!I18-published!I18 -> 0 | J18: =revert!J18-published!J18 -> 0 | K18: =revert!K18-published!K18 -> 0 | ... AX18: =revert!AX18-published!AX18 -> 0
