Workbook

Sheet without tariffs
A1: date | B1: id | C1: recession | D1: federal_purchases_contribution | E1: state_purchases_contribution | F1: federal_non_corporate_taxes_contribution | G1: state_non_corporate_taxes_contribution | H1: federal_corporate_taxes_contribution | I1: supply_side_ira_contribution | J1: state_corporate_taxes_contribution | K1: federal_social_benefits_contribution | L1: state_social_benefits_contribution | M1: rebate_checks_contribution | N1: rebate_checks_arp_contribution | O1: federal_ui_contribution | P1: state_ui_contribution | Q1: federal_subsidies_contribution | R1: federal_aid_to_small_businesses_arp_contribution | S1: federal_other_direct_aid_arp_contribution | T1: federal_other_vulnerable_arp_contribution | U1: federal_student_loans_contribution | V1: state_subsidies_contribution | W1: federal_health_outlays_contribution | X1: state_health_outlays_contribution | Y1: federal_contribution | Z1: state_contribution | AA1: taxes_contribution | AB1: taxes less ira | AC1: transfers_contribution | AD1: consumption_contribution | AE1: fiscal_impact_measure | AF1: fiscal_impact_4q_ma | AG1: fiscal_impact_4q_ma
A2: 2023 Q3 | B2: historical | C2: -1 | D2: 0.29138773 | E2: 0.20751042 | F2: 0.11335746 | G2: 0.097716049 | H2: -0.05915321 | I2: 0.2310278 | J2: -0.033405652 | K2: -0.035337896 | L2: -0.097526156 | M2: -0.033451247 | N2: -0.0077388778 | O2: -0.13051737 | P2: 0.044718453 | Q2: -0.37795185 | R2: 0.00059502736 | S2: -0.026783451 | T2: -0.096213711 | U2: -0.13797271 | V2: -6.5844159e-05 | W2: -0.080930365 | X2: 0.24636772 | Y2: -0.13834318 | Z2: 0.63724132 | AA2: 0.34932404 | AB2: =AA2-I2 -> 0.11829624 | AC2: -0.7341966 | AD2: -0.38219864 | AE2: 0.11669951 | AF2: -0.20616336 | AG2: -0.83627525
A3: 2023 Q4 | B3: historical | C3: -1 | D3: 0.070409519 | E3: 0.33456315 | F3: 0.084390722 | G3: 0.052044238 | H3: -0.071699906 | I3: 0.082750407 | J3: -0.037624014 | K3: -0.20119765 | L3: -0.25248893 | M3: 0 | N3: -0.0062254866 | O3: -0.0074273919 | P3: 0.025176577 | Q3: -0.16467395 | R3: -0.0057101381 | S3: -0.026574551 | T3: -0.096631639 | U3: -0.11266828 | V3: -4.6437541e-05 | W3: 0.057480661 | X3: 0.073497893 | Y3: 0.28189704 | Z3: 0.12307563 | AA3: 0.10992045 | AB3: =AA3-I3 -> 0.027170039 | AC3: -0.71934748 | AD3: -0.60859101 | AE3: -0.20361835 | AF3: -0.15496259 | AG3: -0.20616336
A4: 2024 Q1 | B4: historical | C4: -1 | D4: -0.095656905 | E4: 0.096940856 | F4: 0.49002857 | G4: 0.20839114 | H4: -0.060391934 | I4: 0.12732301 | J4: -0.031435769 | K4: -0.015431334 | L4: -0.024236115 | M4: 0 | N4: -0.11167712 | O4: -0.0014130479 | P4: 0.014852718 | Q4: -0.1478768 | R4: -0.0065334558 | S4: -0.037491898 | T4: -0.063307767 | U4: -0.10447089 | V4: -0.0005835965 | W4: -0.13918165 | X4: 0.13055532 | Y4: -0.14198756 | Z4: 0.14327151 | AA4: 0.73267848 | AB4: =AA4-I4 -> 0.60535547 | AC4: -0.50768404 | AD4: 0.2289171 | AE4: 0.23020105 | AF4: -0.073336716 | AG4: -0.15496259
A5: 2024 Q2 | B5: historical | C5: -1 | D5: 0.12347864 | E5: 0.051398583 | F5: 0.35063464 | G5: 0.18132833 | H5: -0.046919377 | I5: 0.094528727 | J5: -0.022967964 | K5: 0.17944505 | L5: 0.020341749 | M5: 0 | N5: -0.104668 | O5: -0.00067198841 | P5: 0.01260551 | Q5: -0.34619776 | R5: -0.016772232 | S5: -0.035908571 | T5: -0.050238211 | U5: -0.096103418 | V5: -0.0021619606 | W5: -0.10798661 | X5: 0.1126516 | Y5: 0.19183196 | Z5: -0.016954735 | AA5: 0.55586415 | AB5: =AA5-I5 -> 0.46133543 | AC5: -0.43560311 | AD5: 0.12277732 | AE5: 0.29765454 | AF5: 0.11023419 | AG5: -0.073336716
A6: 2024 Q3 | B6: historical | C6: -1 | D6: 0.4065057 | E6: 0.1366917 | F6: 0.26769889 | G6: 0.02149772 | H6: -0.043703024 | I6: -0.0953656 | J6: -0.012505799 | K6: 0.26285186 | L6: 0.049653198 | M6: 0 | N6: -0.10040558 | O6: -0.00033408507 | P6: 0.010455964 | Q6: -0.30976776 | R6: -0.06669009 | S6: -0.034038326 | T6: -0.043936535 | U6: -0.055729673 | V6: -4.4268525e-05 | W6: 0.20674712 | X6: 0.044619557 | Y6: 0.63577579 | Z6: -0.092578392 | AA6: 0.1379591 | AB6: =AA6-I6 -> 0.2333247 | AC6: -0.035405605 | AD6: 0.10260463 | AE6: 0.64580203 | AF6: 0.24250982 | AG6: 0.11023419
A7: 2024 Q4 | B7: historical | C7: -1 | D7: 0.13387378 | E7: 0.040840032 | F7: 0.26578106 | G7: 0.029094859 | H7: -0.034339266 | I7: -0.13372901 | J7: 0.01136901 | K7: 0.27225397 | L7: 0.016960521 | M7: 0 | N7: -0.10036427 | O7: -0.0001725724 | P7: 0.0057762572 | Q7: -0.15458604 | R7: -0.029046972 | S7: -0.022294995 | T7: -0.026522516 | U7: -0.030672088 | V7: -5.5553434e-05 | W7: 0.14998116 | X7: 0.15091666 | Y7: 0.15254838 | Z7: 0.022165438 | AA7: 0.13854798 | AB7: =AA7-I7 -> 0.27227699 | AC7: 0.23270567 | AD7: 0.370919 | AE7: 0.54563281 | AF7: 0.42982261 | AG7: 0.24250982
A8: 2025 Q1 | B8: historical | C8: -1 | D8: -0.51945344 | E8: -0.036329069 | F8: -0.068923508 | G8: 0.045824279 | H8: -0.0042648201 | I8: 0.0248513 | J8: 0.013575618 | K8: 0.18178302 | L8: -0.0089342835 | M8: 0 | N8: -0.096865949 | O8: 0 | P8: 0.00044613388 | Q8: -0.073745276 | R8: -0.028114584 | S8: -0.014963859 | T8: -0.010608242 | U8: -0.030099483 | V8: -0.00030217362 | W8: 0.10399977 | X8: 0.002612607 | Y8: -1.1699513 | Z8: 0.61416882 | AA8: 0.011102717 | AB8: =AA8-I8 -> -0.013748583 | AC8: 0.025525593 | AD8: 0.036625317 | AE8: -0.51915719 | AF8: 0.24248305 | AG8: 0.42982261
A9: 2025 Q2 | B9: historical | C9: -1 | D9: -0.49659071 | E9: 0.090506589 | F9: -0.21567095 | G9: -0.039331912 | H9: 0.0070579944 | I9: 0.1871692 | J9: 0.0019233388 | K9: 0.46724311 | L9: -0.014502786 | M9: 0 | N9: -0.094949895 | O9: 0 | P9: 0.0018247774 | Q9: -0.094999199 | R9: -0.02673731 | S9: -0.013483429 | T9: -0.010020828 | U9: -0.023738219 | V9: -0.0010380446 | W9: 0.28501646 | X9: -0.029952741 | Y9: -0.94596317 | Z9: 0.53987905 | AA9: -0.058434892 | AB9: =AA9-I9 -> -0.24560409 | AC9: 0.44530218 | AD9: 0.087140033 | AE9: -0.31894409 | AF9: 0.088333391 | AG9: 0.24248305
A10: 2025 Q3 | B10: projection | C10: 0 | D10: 0.0018353324 | E10: -0.18895751 | F10: 0.18382506 | G10: 0.031964415 | H10: 0.18570532 | I10: 0.11283214 | J10: 0.0069886574 | K10: 0.26976939 | L10: -0.00024409454 | M10: 0 | N10: -0.00099896094 | O10: 0 | P10: -0.0083673707 | Q10: -0.074626504 | R10: -0.026048206 | S10: -0.013810384 | T10: -0.0085423386 | U10: -0.029638323 | V10: -0.00052655433 | W10: 0.22450059 | X10: 0.0019343238 | Y10: -0.050493883 | Z10: -0.13662829 | AA10: 0.52031284 | AB10: =AA10-I10 -> 0.4074807 | AC10: 0.33350392 | AD10: 0.55197941 | AE10: 0.36485724 | AF10: 0.018097192 | AG10: 0.019287909
A11: 2025 Q4 | B11: projection | C11: 0 | D11: -0.40818665 | E11: -0.18797857 | F11: 0.17518374 | G11: 0.012855036 | H11: 0.065942043 | I11: 0.14035275 | J11: 0.0096981954 | K11: 0.21821118 | L11: 0.026815537 | M11: 0 | N11: -0.00097192311 | O11: 0 | P11: -0.0077753446 | Q11: -0.036283497 | R11: -0.0039026384 | S11: -0.012854849 | T11: -0.0076754748 | U11: -0.024548492 | V11: -0.00044546802 | W11: 0.2294708 | X11: 0.020152618 | Y11: -0.51253608 | Z11: -0.083629139 | AA11: 0.40345847 | AB11: =AA11-I11 -> 0.26310572 | AC11: 0.39989251 | AD11: -0.39836025 | AE11: -0.99452548 | AF11: -0.36694238 | AG11: 0.024972698
A12: 2026 Q1 | B12: projection | C12: 0 | D12: 0.89353249 | E12: -0.18679327 | F12: 0.12718877 | G12: -0.005175253 | H12: 0.063538308 | I12: 0.31388233 | J12: 0.0065070205 | K12: 0.15031915 | L12: 0.040643938 | M12: 0 | N12: -0.00094783566 | O12: 0 | P12: -0.0071485208 | Q12: -0.0028042467 | R12: -0.0026676745 | S12: -0.014294821 | T12: -0.0070418372 | U12: -0.022803876 | V12: -0.00041144841 | W12: 0.27300491 | X12: 0.029331705 | Y12: 0.84183311 | Z12: -0.13509389 | AA12: 0.50521173 | AB12: =AA12-I12 -> 0.1913294 | AC12: 0.4347065 | AD12: 1.5975796 | AE12: 2.3043188 | AF12: 0.33892661 | AG12: -0.25099063
A13: 2026 Q2 | B13: projection | C13: 0 | D13: 0.025063031 | E13: -0.1978847 | F13: 0.12873595 | G13: 0.0026035747 | H13: 0.061199869 | I13: 0.24883676 | J13: 0.0044335969 | K13: -0.05194057 | L13: 0.049423687 | M13: 0 | N13: 0 | O13: 0 | P13: -0.0076631957 | Q13: -9.3948559e-05 | R13: -0.0022399329 | S13: -0.0098355115 | T13: -0.0064655128 | U13: -0.020976971 | V13: -0.00038246576 | W13: 0.18660834 | X13: 0.031639762 | Y13: -0.059218055 | Z13: -0.11360361 | AA13: 0.44519114 | AB13: =AA13-I13 -> 0.19635438 | AC13: 0.16814455 | AD13: 0.47253997 | AE13: 0.2997183 | AF13: 0.49359221 | AG13: 0.53024779
... A18: 2027 Q3 | B18: projection | C18: 0 | D18: -6.6560279 | E18: -10.942086 | F18: 7.3010291 | G18: 3.978959 | H18: 0.22227763 | I18: -1.4415114 | J18: 0.080037867 | K18: -7.6863132 | L18: -0.68416151 | M18: 0 | N18: 0 | O18: 0 | P18: -0.094203067 | Q18: -0.073165979 | R18: -0.00027956108 | S18: -0.0010162159 | T18: -0.0012591917 | U18: 0.025599195 | V18: -0.0002486507 | W18: -6.2228499 | X18: -1.0286535 | Y18: -8.2160054 | Z18: -9.3821084 | AA18: 9.9637411 | AB18: =AA18-I18 -> 11.405253 | AC18: -16.555741 | AD18: -4.8417513 | AE18: -22.439865 | AF18: -5.75632 | AG18: 0.071675439

Sheet with tariffs
A1: date | B1: id | C1: recession | D1: federal_purchases_contribution | E1: state_purchases_contribution | F1: federal_non_corporate_taxes_contribution | G1: state_non_corporate_taxes_contribution | H1: federal_corporate_taxes_contribution | I1: supply_side_ira_contribution | J1: state_corporate_taxes_contribution | K1: federal_social_benefits_contribution | L1: state_social_benefits_contribution | M1: rebate_checks_contribution | N1: rebate_checks_arp_contribution | O1: federal_ui_contribution | P1: state_ui_contribution | Q1: federal_subsidies_contribution | R1: federal_aid_to_small_businesses_arp_contribution | S1: federal_other_direct_aid_arp_contribution | T1: federal_other_vulnerable_arp_contribution | U1: federal_student_loans_contribution | V1: state_subsidies_contribution | W1: federal_health_outlays_contribution | X1: state_health_outlays_contribution | Y1: federal_contribution | Z1: state_contribution | AA1: taxes_contribution | AB1: taxes less ira | AC1: transfers_contribution | AD1: consumption_contribution | AE1: fiscal_impact_measure | AF1: fiscal_impact_4q_ma
A2: 2023 Q2 | B2: historical | C2: -1 | D2: -0.14802611 | E2: 0.32935984 | F2: 0.40168307 | G2: 0.18603735 | H2: -0.082194087 | I2: 0.23535829 | J2: -0.041113772 | K2: -0.11030549 | L2: -0.039292217 | M2: -0.25081207 | N2: -0.42408041 | O2: -0.28390642 | P2: 0.020948001 | Q2: -0.36373095 | R2: 0.00050505984 | S2: -0.041864783 | T2: -0.096126642 | U2: -0.0080992849 | V2: -0.0008915333 | W2: 0.17103649 | X2: 0.10677014 | Y2: -0.23313551 | Z2: 0.41446924 | AA2: 0.69855453 | AB2: =AA2-I2 -> 0.46319624 | AC2: -1.3262928 | AD2: -0.61796281 | AE2: -0.43662908 | AF2: -0.83627525
A3: 2023 Q3 | B3: historical | C3: -1 | D3: 0.29138773 | E3: 0.20751042 | F3: 0.11335746 | G3: 0.097716049 | H3: -0.05915321 | I3: 0.2310278 | J3: -0.033405652 | K3: -0.035337896 | L3: -0.097526156 | M3: -0.033451247 | N3: -0.0077388778 | O3: -0.13051737 | P3: 0.044718453 | Q3: -0.37795185 | R3: 0.00059502736 | S3: -0.026783451 | T3: -0.096213711 | U3: -0.13797271 | V3: -6.5844159e-05 | W3: -0.080930365 | X3: 0.24636772 | Y3: -0.13834318 | Z3: 0.63724132 | AA3: 0.34932404 | AB3: =AA3-I3 -> 0.11829624 | AC3: -0.7341966 | AD3: -0.38219864 | AE3: 0.11669951 | AF3: -0.20616336
A4: 2023 Q4 | B4: historical | C4: -1 | D4: 0.070409519 | E4: 0.33456315 | F4: 0.084390722 | G4: 0.052044238 | H4: -0.071699906 | I4: 0.082750407 | J4: -0.037624014 | K4: -0.20119765 | L4: -0.25248893 | M4: 0 | N4: -0.0062254866 | O4: -0.0074273919 | P4: 0.025176577 | Q4: -0.16467395 | R4: -0.0057101381 | S4: -0.026574551 | T4: -0.096631639 | U4: -0.11266828 | V4: -4.6437541e-05 | W4: 0.057480661 | X4: 0.073497893 | Y4: 0.28189704 | Z4: 0.12307563 | AA4: 0.10992045 | AB4: =AA4-I4 -> 0.027170039 | AC4: -0.71934748 | AD4: -0.60859101 | AE4: -0.20361835 | AF4: -0.15496259
A5: 2024 Q1 | B5: historical | C5: -1 | D5: -0.095656905 | E5: 0.096940856 | F5: 0.49002857 | G5: 0.20839114 | H5: -0.060391934 | I5: 0.12732301 | J5: -0.031435769 | K5: -0.015431334 | L5: -0.024236115 | M5: 0 | N5: -0.11167712 | O5: -0.0014130479 | P5: 0.014852718 | Q5: -0.1478768 | R5: -0.0065334558 | S5: -0.037491898 | T5: -0.063307767 | U5: -0.10447089 | V5: -0.0005835965 | W5: -0.13918165 | X5: 0.13055532 | Y5: -0.14198756 | Z5: 0.14327151 | AA5: 0.73267848 | AB5: =AA5-I5 -> 0.60535547 | AC5: -0.50768404 | AD5: 0.2289171 | AE5: 0.23020105 | AF5: -0.073336716
A6: 2024 Q2 | B6: historical | C6: -1 | D6: 0.12347864 | E6: 0.051398583 | F6: 0.35063464 | G6: 0.18132833 | H6: -0.046919377 | I6: 0.094528727 | J6: -0.022967964 | K6: 0.17944505 | L6: 0.020341749 | M6: 0 | N6: -0.104668 | O6: -0.00067198841 | P6: 0.01260551 | Q6: -0.34619776 | R6: -0.016772232 | S6: -0.035908571 | T6: -0.050238211 | U6: -0.096103418 | V6: -0.0021619606 | W6: -0.10798661 | X6: 0.1126516 | Y6: 0.19183196 | Z6: -0.016954735 | AA6: 0.55586415 | AB6: =AA6-I6 -> 0.46133543 | AC6: -0.43560311 | AD6: 0.12277732 | AE6: 0.29765454 | AF6: 0.11023419
A7: 2024 Q3 | B7: historical | C7: -1 | D7: 0.4065057 | E7: 0.1366917 | F7: 0.26769889 | G7: 0.02149772 | H7: -0.043703024 | I7: -0.0953656 | J7: -0.012505799 | K7: 0.26285186 | L7: 0.049653198 | M7: 0 | N7: -0.10040558 | O7: -0.00033408507 | P7: 0.010455964 | Q7: -0.30976776 | R7: -0.06669009 | S7: -0.034038326 | T7: -0.043936535 | U7: -0.055729673 | V7: -4.4268525e-05 | W7: 0.20674712 | X7: 0.044619557 | Y7: 0.63577579 | Z7: -0.092578392 | AA7: 0.1379591 | AB7: =AA7-I7 -> 0.2333247 | AC7: -0.035405605 | AD7: 0.10260463 | AE7: 0.64580203 | AF7: 0.24250982
A8: 2024 Q4 | B8: historical | C8: -1 | D8: 0.13387378 | E8: 0.040840032 | F8: 0.26578106 | G8: 0.029094859 | H8: -0.034339266 | I8: -0.13372901 | J8: 0.01136901 | K8: 0.27225397 | L8: 0.016960521 | M8: 0 | N8: -0.10036427 | O8: -0.0001725724 | P8: 0.0057762572 | Q8: -0.15458604 | R8: -0.029046972 | S8: -0.022294995 | T8: -0.026522516 | U8: -0.030672088 | V8: -5.5553434e-05 | W8: 0.14998116 | X8: 0.15091666 | Y8: 0.15254838 | Z8: 0.022165438 | AA8: 0.13854798 | AB8: =AA8-I8 -> 0.27227699 | AC8: 0.23270567 | AD8: 0.370919 | AE8: 0.54563281 | AF8: 0.42982261
A9: 2025 Q1 | B9: historical | C9: -1 | D9: -0.51945344 | E9: -0.036329069 | F9: -0.068923508 | G9: 0.045824279 | H9: -0.0042648201 | I9: 0.0248513 | J9: 0.013575618 | K9: 0.18178302 | L9: -0.0089342835 | M9: 0 | N9: -0.096865949 | O9: 0 | P9: 0.00044613388 | Q9: -0.073745276 | R9: -0.028114584 | S9: -0.014963859 | T9: -0.010608242 | U9: -0.030099483 | V9: -0.00030217362 | W9: 0.10399977 | X9: 0.002612607 | Y9: -1.1699513 | Z9: 0.61416882 | AA9: 0.011102717 | AB9: =AA9-I9 -> -0.013748583 | AC9: 0.025525593 | AD9: 0.036625317 | AE9: -0.51915719 | AF9: 0.24248305
A10: 2025 Q2 | B10: historical | C10: -1 | D10: -0.49659071 | E10: 0.090506589 | F10: -0.49360352 | G10: -0.039331912 | H10: 0.0070579944 | I10: 0.1871692 | J10: 0.0019233388 | K10: 0.46724311 | L10: -0.014502786 | M10: 0 | N10: -0.094949895 | O10: 0 | P10: 0.0018247774 | Q10: -0.094999199 | R10: -0.02673731 | S10: -0.013483429 | T10: -0.010020828 | U10: -0.023738219 | V10: -0.0010380446 | W10: 0.28501646 | X10: -0.029952741 | Y10: -0.94596317 | Z10: 0.53987905 | AA10: -0.33591118 | AB10: =AA10-I10 -> -0.52308038 | AC10: 0.44530218 | AD10: -0.18904189 | AE10: -0.59512601 | AF10: 0.019287909
A11: 2025 Q3 | B11: projection | C11: 0 | D11: 0.0018353324 | E11: -0.18895751 | F11: -0.22561765 | G11: 0.031964415 | H11: 0.18570532 | I11: 0.11283214 | J11: 0.0069886574 | K11: 0.26976939 | L11: -0.00024409454 | M11: 0 | N11: -0.00099896094 | O11: 0 | P11: -0.0083673707 | Q11: -0.074626504 | R11: -0.026048206 | S11: -0.013810384 | T11: -0.0085423386 | U11: -0.029638323 | V11: -0.00052655433 | W11: 0.22450059 | X11: 0.0019343238 | Y11: -0.050493883 | Z11: -0.13662829 | AA11: 0.11233031 | AB11: =AA11-I11 -> -0.00050183295 | AC11: 0.33350392 | AD11: 0.14543785 | AE11: -0.041684325 | AF11: -0.15258368
A12: 2025 Q4 | B12: projection | C12: 0 | D12: -0.40818665 | E12: -0.18797857 | F12: -0.18376482 | G12: 0.012855036 | H12: 0.065942043 | I12: 0.14035275 | J12: 0.0096981954 | K12: 0.21821118 | L12: 0.026815537 | M12: 0 | N12: -0.00097192311 | O12: 0 | P12: -0.0077753446 | Q12: -0.036283497 | R12: -0.0039026384 | S12: -0.012854849 | T12: -0.0076754748 | U12: -0.024548492 | V12: -0.00044546802 | W12: 0.2294708 | X12: 0.020152618 | Y12: -0.51253608 | Z12: -0.083629139 | AA12: 0.045379711 | AB12: =AA12-I12 -> -0.094973042 | AC12: 0.39989251 | AD12: -0.75492013 | AE12: -1.3510854 | AF12: -0.62676322
A13: 2026 Q1 | B13: projection | C13: 0 | D13: 0.89353249 | E13: -0.18679327 | F13: -0.15788909 | G13: -0.005175253 | H13: 0.063538308 | I13: 0.31388233 | J13: 0.0065070205 | K13: 0.15031915 | L13: 0.040643938 | M13: 0 | N13: -0.00094783566 | O13: 0 | P13: -0.0071485208 | Q13: -0.0028042467 | R13: -0.0026676745 | S13: -0.014294821 | T13: -0.0070418372 | U13: -0.022803876 | V13: -0.00041144841 | W13: 0.27300491 | X13: 0.029331705 | Y13: 0.84183311 | Z13: -0.13509389 | AA13: 0.2212818 | AB13: =AA13-I13 -> -0.092600531 | AC13: 0.4347065 | AD13: 1.3149645 | AE13: 2.0217037 | AF13: 0.008452003
... A18: 2027 Q2 | B18: projection | C18: 0 | D18: -0.11072717 | E18: -0.19118456 | F18: -0.02983676 | G18: 0.023800283 | H18: 0.088515383 | I18: -0.36522952 | J18: 0.004630489 | K18: 0.12270905 | L18: 0.010613895 | M18: 0 | N18: 0 | O18: 0 | P18: -0.00081672553 | Q18: 0.0025172322 | R18: -0.00028515852 | S18: -0.0010320556 | T18: -0.0015233461 | U18: -0.0095126456 | V18: -0.00031358356 | W18: 0.089169656 | X18: 0.0013236714 | Y18: -0.15456652 | Z18: -0.1473452 | AA18: -0.27777126 | AB18: =AA18-I18 -> 0.087458255 | AC18: 0.21273203 | AD18: -0.10440821 | AE18: -0.40631993 | AF18: -0.30849496

Sheet diff
A1: date | B1: id | C1: recession | D1: federal_purchases_contribution | E1: state_purchases_contribution | F1: federal_non_corporate_taxes_contribution | G1: state_non_corporate_taxes_contribution | H1: federal_corporate_taxes_contribution | I1: supply_side_ira_contribution | J1: state_corporate_taxes_contribution | K1: federal_social_benefits_contribution | L1: state_social_benefits_contribution | M1: rebate_checks_contribution | N1: rebate_checks_arp_contribution | O1: federal_ui_contribution | P1: state_ui_contribution | Q1: federal_subsidies_contribution | R1: federal_aid_to_small_businesses_arp_contribution | S1: federal_other_direct_aid_arp_contribution | T1: federal_other_vulnerable_arp_contribution | U1: federal_student_loans_contribution | V1: state_subsidies_contribution | W1: federal_health_outlays_contribution | X1: state_health_outlays_contribution | Y1: federal_contribution | Z1: state_contribution | AA1: taxes_contribution | AB1: taxes less ira | AC1: transfers_contribution | AD1: consumption_contribution | AE1: fiscal_impact_measure | AF1: fiscal_impact_4q_ma
A2: 2023 Q2 | B2: historical | C2: -1 | D2: ='with tariffs'!D2-'without tariffs'!D2 -> -0.43941384 | E2: ='with tariffs'!E2-'without tariffs'!E2 -> 0.12184942 | F2: ='with tariffs'!F2-'without tariffs'!F2 -> 0.28832561 | G2: ='with tariffs'!G2-'without tariffs'!G2 -> 0.088321296 | H2: ='with tariffs'!H2-'without tariffs'!H2 -> -0.023040877 | I2: ='with tariffs'!I2-'without tariffs'!I2 -> 0.0043304873 | J2: ='with tariffs'!J2-'without tariffs'!J2 -> -0.0077081198 | K2: ='with tariffs'!K2-'without tariffs'!K2 -> -0.074967594 | ... AA2: ='with tariffs'!AA2-'without tariffs'!AA2 -> 0.34923049 | AB2: ='with tariffs'!AB2-'without tariffs'!AC2 -> 1.1973928 | AC2: ='with tariffs'!AC2-'without tariffs'!AD2 -> -0.94409415 | AD2: ='with tariffs'!AD2-'without tariffs'!AE2 -> -0.73466232 | AE2: ='with tariffs'!AE2-'without tariffs'!AF2 -> -0.23046572 | AF2: ='with tariffs'!AF2-'without tariffs'!AG2 -> 0
A3: 2023 Q3 | B3: historical | C3: -1 | D3: ='with tariffs'!D3-'without tariffs'!D3 -> 0.22097821 | E3: ='with tariffs'!E3-'without tariffs'!E3 -> -0.12705273 | F3: ='with tariffs'!F3-'without tariffs'!F3 -> 0.028966735 | G3: ='with tariffs'!G3-'without tariffs'!G3 -> 0.045671811 | H3: ='with tariffs'!H3-'without tariffs'!H3 -> 0.012546696 | I3: ='with tariffs'!I3-'without tariffs'!I3 -> 0.1482774 | J3: ='with tariffs'!J3-'without tariffs'!J3 -> 0.004218362 | K3: ='with tariffs'!K3-'without tariffs'!K3 -> 0.16585976 | ... AA3: ='with tariffs'!AA3-'without tariffs'!AA3 -> 0.2394036 | AB3: ='with tariffs'!AB3-'without tariffs'!AC3 -> 0.83764372 | AC3: ='with tariffs'!AC3-'without tariffs'!AD3 -> -0.12560558 | AD3: ='with tariffs'!AD3-'without tariffs'!AE3 -> -0.17858029 | AE3: ='with tariffs'!AE3-'without tariffs'!AF3 -> 0.2716621 | AF3: ='with tariffs'!AF3-'without tariffs'!AG3 -> 0
A4: 2023 Q4 | B4: historical | C4: -1 | D4: ='with tariffs'!D4-'without tariffs'!D4 -> 0.16606642 | E4: ='with tariffs'!E4-'without tariffs'!E4 -> 0.23762229 | F4: ='with tariffs'!F4-'without tariffs'!F4 -> -0.40563785 | G4: ='with tariffs'!G4-'without tariffs'!G4 -> -0.1563469 | H4: ='with tariffs'!H4-'without tariffs'!H4 -> -0.011307972 | I4: ='with tariffs'!I4-'without tariffs'!I4 -> -0.0445726 | J4: ='with tariffs'!J4-'without tariffs'!J4 -> -0.0061882454 | K4: ='with tariffs'!K4-'without tariffs'!K4 -> -0.18576632 | ... AA4: ='with tariffs'!AA4-'without tariffs'!AA4 -> -0.62275803 | AB4: ='with tariffs'!AB4-'without tariffs'!AC4 -> 0.53485408 | AC4: ='with tariffs'!AC4-'without tariffs'!AD4 -> -0.94826458 | AD4: ='with tariffs'!AD4-'without tariffs'!AE4 -> -0.83879207 | AE4: ='with tariffs'!AE4-'without tariffs'!AF4 -> -0.13028163 | AF4: ='with tariffs'!AF4-'without tariffs'!AG4 -> 0
A5: 2024 Q1 | B5: historical | C5: -1 | D5: ='with tariffs'!D5-'without tariffs'!D5 -> -0.21913555 | E5: ='with tariffs'!E5-'without tariffs'!E5 -> 0.045542273 | F5: ='with tariffs'!F5-'without tariffs'!F5 -> 0.13939393 | G5: ='with tariffs'!G5-'without tariffs'!G5 -> 0.027062802 | H5: ='with tariffs'!H5-'without tariffs'!H5 -> -0.013472557 | I5: ='with tariffs'!I5-'without tariffs'!I5 -> 0.032794281 | J5: ='with tariffs'!J5-'without tariffs'!J5 -> -0.0084678052 | K5: ='with tariffs'!K5-'without tariffs'!K5 -> -0.19487639 | ... AA5: ='with tariffs'!AA5-'without tariffs'!AA5 -> 0.17681432 | AB5: ='with tariffs'!AB5-'without tariffs'!AC5 -> 1.0409586 | AC5: ='with tariffs'!AC5-'without tariffs'!AD5 -> -0.63046136 | AD5: ='with tariffs'!AD5-'without tariffs'!AE5 -> -0.068737442 | AE5: ='with tariffs'!AE5-'without tariffs'!AF5 -> 0.11996686 | AF5: ='with tariffs'!AF5-'without tariffs'!AG5 -> 0
A6: 2024 Q2 | B6: historical | C6: -1 | D6: ='with tariffs'!D6-'without tariffs'!D6 -> -0.28302706 | E6: ='with tariffs'!E6-'without tariffs'!E6 -> -0.085293116 | F6: ='with tariffs'!F6-'without tariffs'!F6 -> 0.082935746 | G6: ='with tariffs'!G6-'without tariffs'!G6 -> 0.15983061 | H6: ='with tariffs'!H6-'without tariffs'!H6 -> -0.0032163529 | I6: ='with tariffs'!I6-'without tariffs'!I6 -> 0.18989433 | J6: ='with tariffs'!J6-'without tariffs'!J6 -> -0.010462164 | K6: ='with tariffs'!K6-'without tariffs'!K6 -> -0.083406808 | ... AA6: ='with tariffs'!AA6-'without tariffs'!AA6 -> 0.41790505 | AB6: ='with tariffs'!AB6-'without tariffs'!AC6 -> 0.49674103 | AC6: ='with tariffs'!AC6-'without tariffs'!AD6 -> -0.53820774 | AD6: ='with tariffs'!AD6-'without tariffs'!AE6 -> -0.52302471 | AE6: ='with tariffs'!AE6-'without tariffs'!AF6 -> 0.055144725 | AF6: ='with tariffs'!AF6-'without tariffs'!AG6 -> 0
A7: 2024 Q3 | B7: historical | C7: -1 | D7: ='with tariffs'!D7-'without tariffs'!D7 -> 0.27263192 | E7: ='with tariffs'!E7-'without tariffs'!E7 -> 0.095851666 | F7: ='with tariffs'!F7-'without tariffs'!F7 -> 0.0019178288 | G7: ='with tariffs'!G7-'without tariffs'!G7 -> -0.0075971391 | H7: ='with tariffs'!H7-'without tariffs'!H7 -> -0.0093637575 | I7: ='with tariffs'!I7-'without tariffs'!I7 -> 0.03836341 | J7: ='with tariffs'!J7-'without tariffs'!J7 -> -0.02387481 | K7: ='with tariffs'!K7-'without tariffs'!K7 -> -0.0094021089 | ... AA7: ='with tariffs'!AA7-'without tariffs'!AA7 -> -0.00058888027 | AB7: ='with tariffs'!AB7-'without tariffs'!AC7 -> 0.00061902999 | AC7: ='with tariffs'!AC7-'without tariffs'!AD7 -> -0.4063246 | AD7: ='with tariffs'!AD7-'without tariffs'!AE7 -> -0.44302818 | AE7: ='with tariffs'!AE7-'without tariffs'!AF7 -> 0.21597942 | AF7: ='with tariffs'!AF7-'without tariffs'!AG7 -> 0
A8: 2024 Q4 | B8: historical | C8: -1 | D8: ='with tariffs'!D8-'without tariffs'!D8 -> 0.65332722 | E8: ='with tariffs'!E8-'without tariffs'!E8 -> 0.077169101 | F8: ='with tariffs'!F8-'without tariffs'!F8 -> 0.33470457 | G8: ='with tariffs'!G8-'without tariffs'!G8 -> -0.01672942 | H8: ='with tariffs'!H8-'without tariffs'!H8 -> -0.030074446 | I8: ='with tariffs'!I8-'without tariffs'!I8 -> -0.15858031 | J8: ='with tariffs'!J8-'without tariffs'!J8 -> -0.0022066081 | K8: ='with tariffs'!K8-'without tariffs'!K8 -> 0.090470948 | ... AA8: ='with tariffs'!AA8-'without tariffs'!AA8 -> 0.12744527 | AB8: ='with tariffs'!AB8-'without tariffs'!AC8 -> 0.2467514 | AC8: ='with tariffs'!AC8-'without tariffs'!AD8 -> 0.19608036 | AD8: ='with tariffs'!AD8-'without tariffs'!AE8 -> 0.89007619 | AE8: ='with tariffs'!AE8-'without tariffs'!AF8 -> 0.30314976 | AF8: ='with tariffs'!AF8-'without tariffs'!AG8 -> 0
A9: 2025 Q1 | B9: historical | C9: -1 | D9: ='with tariffs'!D9-'without tariffs'!D9 -> -0.022862734 | E9: ='with tariffs'!E9-'without tariffs'!E9 -> -0.12683566 | F9: ='with tariffs'!F9-'without tariffs'!F9 -> 0.14674744 | G9: ='with tariffs'!G9-'without tariffs'!G9 -> 0.085156191 | H9: ='with tariffs'!H9-'without tariffs'!H9 -> -0.011322815 | I9: ='with tariffs'!I9-'without tariffs'!I9 -> -0.1623179 | J9: ='with tariffs'!J9-'without tariffs'!J9 -> 0.011652279 | K9: ='with tariffs'!K9-'without tariffs'!K9 -> -0.28546009 | ... AA9: ='with tariffs'!AA9-'without tariffs'!AA9 -> 0.069537609 | AB9: ='with tariffs'!AB9-'without tariffs'!AC9 -> -0.45905076 | AC9: ='with tariffs'!AC9-'without tariffs'!AD9 -> -0.06161444 | AD9: ='with tariffs'!AD9-'without tariffs'!AE9 -> 0.3555694 | AE9: ='with tariffs'!AE9-'without tariffs'!AF9 -> -0.60749059 | AF9: ='with tariffs'!AF9-'without tariffs'!AG9 -> 0
A10: 2025 Q2 | B10: historical | C10: -1 | D10: ='with tariffs'!D10-'without tariffs'!D10 -> -0.49842604 | E10: ='with tariffs'!E10-'without tariffs'!E10 -> 0.2794641 | F10: ='with tariffs'!F10-'without tariffs'!F10 -> -0.67742858 | G10: ='with tariffs'!G10-'without tariffs'!G10 -> -0.071296327 | H10: ='with tariffs'!H10-'without tariffs'!H10 -> -0.17864732 | I10: ='with tariffs'!I10-'without tariffs'!I10 -> 0.074337056 | J10: ='with tariffs'!J10-'without tariffs'!J10 -> -0.0050653186 | K10: ='with tariffs'!K10-'without tariffs'!K10 -> 0.19747372 | ... AA10: ='with tariffs'!AA10-'without tariffs'!AA10 -> -0.85622402 | AB10: ='with tariffs'!AB10-'without tariffs'!AC10 -> -0.8565843 | AC10: ='with tariffs'!AC10-'without tariffs'!AD10 -> -0.10667723 | AD10: ='with tariffs'!AD10-'without tariffs'!AE10 -> -0.55389913 | AE10: ='with tariffs'!AE10-'without tariffs'!AF10 -> -0.61322321 | AF10: ='with tariffs'!AF10-'without tariffs'!AG10 -> 0
A11: 2025 Q3 | B11: projection | C11: 0 | D11: ='with tariffs'!D11-'without tariffs'!D11 -> 0.41002199 | E11: ='with tariffs'!E11-'without tariffs'!E11 -> -0.00097893931 | F11: ='with tariffs'!F11-'without tariffs'!F11 -> -0.40080138 | G11: ='with tariffs'!G11-'without tariffs'!G11 -> 0.019109379 | H11: ='with tariffs'!H11-'without tariffs'!H11 -> 0.11976328 | I11: ='with tariffs'!I11-'without tariffs'!I11 -> -0.02752061 | J11: ='with tariffs'!J11-'without tariffs'!J11 -> -0.0027095381 | K11: ='with tariffs'!K11-'without tariffs'!K11 -> 0.051558206 | ... AA11: ='with tariffs'!AA11-'without tariffs'!AA11 -> -0.29112816 | AB11: ='with tariffs'!AB11-'without tariffs'!AC11 -> -0.40039435 | AC11: ='with tariffs'!AC11-'without tariffs'!AD11 -> 0.73186417 | AD11: ='with tariffs'!AD11-'without tariffs'!AE11 -> 1.1399633 | AE11: ='with tariffs'!AE11-'without tariffs'!AF11 -> 0.32525805 | AF11: ='with tariffs'!AF11-'without tariffs'!AG11 -> -0.17755638
A12: 2025 Q4 | B12: projection | C12: 0 | D12: ='with tariffs'!D12-'without tariffs'!D12 -> -1.3017191 | E12: ='with tariffs'!E12-'without tariffs'!E12 -> -0.0011853025 | F12: ='with tariffs'!F12-'without tariffs'!F12 -> -0.31095359 | G12: ='with tariffs'!G12-'without tariffs'!G12 -> 0.018030289 | H12: ='with tariffs'!H12-'without tariffs'!H12 -> 0.0024037351 | I12: ='with tariffs'!I12-'without tariffs'!I12 -> -0.17352958 | J12: ='with tariffs'!J12-'without tariffs'!J12 -> 0.0031911749 | K12: ='with tariffs'!K12-'without tariffs'!K12 -> 0.067892036 | ... AA12: ='with tariffs'!AA12-'without tariffs'!AA12 -> -0.45983202 | AB12: ='with tariffs'!AB12-'without tariffs'!AC12 -> -0.52967954 | AC12: ='with tariffs'!AC12-'without tariffs'!AD12 -> -1.197687 | AD12: ='with tariffs'!AD12-'without tariffs'!AE12 -> -3.0592389 | AE12: ='with tariffs'!AE12-'without tariffs'!AF12 -> -1.690012 | AF12: ='with tariffs'!AF12-'without tariffs'!AG12 -> -0.37577259
A13: 2026 Q1 | B13: projection | C13: 0 | D13: ='with tariffs'!D13-'without tariffs'!D13 -> 0.86846946 | E13: ='with tariffs'!E13-'without tariffs'!E13 -> 0.011091431 | F13: ='with tariffs'!F13-'without tariffs'!F13 -> -0.28662504 | G13: ='with tariffs'!G13-'without tariffs'!G13 -> -0.0077788276 | H13: ='with tariffs'!H13-'without tariffs'!H13 -> 0.002338439 | I13: ='with tariffs'!I13-'without tariffs'!I13 -> 0.065045569 | J13: ='with tariffs'!J13-'without tariffs'!J13 -> 0.0020734236 | K13: ='with tariffs'!K13-'without tariffs'!K13 -> 0.20225972 | ... AA13: ='with tariffs'!AA13-'without tariffs'!AA13 -> -0.22390934 | AB13: ='with tariffs'!AB13-'without tariffs'!AC13 -> -0.26074508 | AC13: ='with tariffs'!AC13-'without tariffs'!AD13 -> -0.037833466 | AD13: ='with tariffs'!AD13-'without tariffs'!AE13 -> 1.0152462 | AE13: ='with tariffs'!AE13-'without tariffs'!AF13 -> 1.5281115 | AF13: ='with tariffs'!AF13-'without tariffs'!AG13 -> -0.52179578
... A18: 2027 Q2 | B18: projection | C18: 0 | D18: ='with tariffs'!D18-'without tariffs'!D18 -> 6.5453007 | E18: ='with tariffs'!E18-'without tariffs'!E18 -> 10.750901 | F18: ='with tariffs'!F18-'without tariffs'!F18 -> -7.3308658 | G18: ='with tariffs'!G18-'without tariffs'!G18 -> -3.9551587 | H18: ='with tariffs'!H18-'without tariffs'!H18 -> -0.13376225 | I18: ='with tariffs'!I18-'without tariffs'!I18 -> 1.0762819 | J18: ='with tariffs'!J18-'without tariffs'!J18 -> -0.075407377 | K18: ='with tariffs'!K18-'without tariffs'!K18 -> 7.8090223 | ... AA18: ='with tariffs'!AA18-'without tariffs'!AA18 -> -10.241512 | AB18: ='with tariffs'!AB18-'without tariffs'!AC18 -> 16.643199 | AC18: ='with tariffs'!AC18-'without tariffs'!AD18 -> 5.0544833 | AD18: ='with tariffs'!AD18-'without tariffs'!AE18 -> 22.335457 | AE18: ='with tariffs'!AE18-'without tariffs'!AF18 -> 5.35 | AF18: ='with tariffs'!AF18-'without tariffs'!AG18 -> -0.3801704
