Workbook

Sheet 01-13
A1: date | B1: id | C1: recession | D1: federal_purchases_deflator_growth | E1: consumption_grants_deflator_growth | F1: investment_grants_deflator_growth | G1: state_purchases_deflator_growth | H1: consumption_deflator_growth | I1: real_potential_gdp_growth | J1: gdp | K1: consumption | L1: uncertainty | M1: federal_purchases | N1: consumption_grants | O1: investment_grants | P1: state_purchases | Q1: federal_non_corporate_taxes | R1: state_non_corporate_taxes | S1: federal_corporate_taxes | T1: supply_side_ira | U1: state_corporate_taxes | V1: federal_social_benefits | W1: state_social_benefits | X1: rebate_checks | Y1: rebate_checks_arp | Z1: federal_ui | AA1: state_ui | AB1: federal_subsidies | AC1: federal_aid_to_small_businesses_arp | AD1: federal_other_direct_aid_arp | AE1: federal_other_vulnerable_arp | AF1: federal_student_loans | AG1: state_subsidies | AH1: federal_health_outlays | AI1: state_health_outlays | AJ1: post_mpc_federal_non_corporate_taxes | AK1: post_mpc_state_non_corporate_taxes | AL1: post_mpc_federal_corporate_taxes | AM1: post_mpc_state_corporate_taxes | AN1: post_mpc_federal_social_benefits | AO1: post_mpc_state_social_benefits | AP1: post_mpc_rebate_checks | AQ1: post_mpc_rebate_checks_arp | AR1: post_mpc_federal_ui | AS1: post_mpc_state_ui | AT1: post_mpc_federal_subsidies | AU1: post_mpc_federal_aid_to_small_businesses_arp | AV1: post_mpc_federal_other_vulnerable_arp | AW1: post_mpc_federal_student_loans | AX1: post_mpc_state_subsidies | AY1: post_mpc_federal_health_outlays | AZ1: post_mpc_state_health_outlays
A2: 2023 Q2 | B2: historical | C2: -1 | D2: 0.006582718 | E2: -0.0073827309 | F2: 0.0021322445 | G2: -0.0056211973 | H2: 0.0073926308 | I2: 0.0056240488 | J2: 27530.1 | K2: 18693.1 | L2: 0 | M2: 1738.8 | N2: 436.07272 | O2: 76.015143 | P2: 2934.6 | Q2: 4210.6 | R2: 2236.1 | S2: 415.5 | T2: 46.245323 | U2: 170.2 | V2: 2006.4269 | W2: 183.8 | X2: 0 | Y2: 0 | Z2: 0 | AA2: 32.8 | AB2: 101.3 | AC2: 12.726 | AD2: 1.416 | AE2: 12 | AF2: 45 | AG2: 0.7 | AH2: 1659.996 | AI2: 267.104 | AJ2: -2564.838 | AK2: -1347.348 | AL2: -144.40667 | AM2: -55.99 | AN2: 1790.1942 | AO2: 188.1225 | AP2: 2.1784 | AQ2: 41.153 | AR2: 9.157 | AS2: 22.948 | AT2: 159.5619 | AU2: 14.28301 | AV2: 28.976026 | AW2: 40.95 | AX2: 0.5679 | AY2: 1444.3544 | AZ2: 210.74558
A3: 2023 Q3 | B3: historical | C3: -1 | D3: 0.0094033912 | E3: 0.016732699 | F3: 0.00035461796 | G3: 0.013706093 | H3: 0.0067310092 | I3: 0.0056687159 | J3: 28074.8 | K3: 18961.8 | L3: 0 | M3: 1784.4 | N3: 417.91594 | O3: 76.015143 | P3: 3005.4 | Q3: 4257.9 | R3: 2270.3 | S3: 428.4 | T3: 62.071265 | U3: 168.5 | V3: 2016.4269 | W3: 185.9 | X3: 0 | Y3: 0 | Z3: 0 | AA3: 34.9 | AB3: 103.5 | AC3: 12.726 | AD3: 1.416 | AE3: 12 | AF3: 2.081508 | AG3: 0.7 | AH3: 1613.65 | AI3: 290.05 | AJ3: -2589.162 | AK3: -1357.608 | AL3: -150.09667 | AM3: -58.886667 | AN3: 1810.0624 | AO3: 184.0275 | AP3: 0 | AQ3: 41.153 | AR3: 0.67 | AS3: 26.182 | AT3: 136.66702 | AU3: 14.499352 | AV3: 22.99411 | AW3: 32.366302 | AX3: 0.5706 | AY3: 1456.9297 | AZ3: 229.62533
A4: 2023 Q4 | B4: historical | C4: -1 | D4: 0.0070345423 | E4: 0.00071349046 | F4: 0.0032733965 | G4: 0.0011916352 | H4: 0.0045206985 | I4: 0.0057213587 | J4: 28424.7 | K4: 19190.6 | L4: 0 | M4: 1812 | N4: 434.04594 | O4: 77.674143 | P4: 3049 | Q4: 4302.2 | R4: 2301.1 | S4: 442.7 | T4: 68.31219 | U4: 172.7 | V4: 2024.999 | W4: 189.5 | X4: 0 | Y4: 0 | Z4: 0 | AA4: 35.5 | AB4: 98 | AC4: 1.365 | AD4: 1.479 | AE4: 4.222 | AF4: 2.100618 | AG4: 0.7 | AH4: 1658.388 | AI4: 252.912 | AJ4: -2609.964 | AK4: -1367.988 | AL4: -156.48667 | AM4: -62.036667 | AN4: 1814.9933 | AO4: 168.84 | AP4: 0 | AQ4: 41.153 | AR4: 0.174 | AS4: 28.155 | AT4: 126.927 | AU4: 14.261254 | AV4: 16.69038 | AW4: 25.07398 | AX4: 0.5733 | AY4: 1475.7446 | AZ4: 236.95538
A5: 2024 Q1 | B5: historical | C5: -1 | D5: 0.01026393 | E5: 0.008782995 | F5: 0.0044129366 | G5: 0.0079425584 | H5: 0.0088526155 | I5: 0.0057507902 | J5: 28708.2 | K5: 19443.8 | L5: 0 | M5: 1834.3 | N5: 437.85294 | O5: 77.674143 | P5: 3097.5 | Q5: 4390.9 | R5: 2325.5 | S5: 472.3 | T5: 78.014538 | U5: 173.2 | V5: 2131.899 | W5: 194.8 | X5: 0 | Y5: 0 | Z5: 0 | AA5: 35.5 | AB5: 95 | AC5: 1.365 | AD5: 1.479 | AE5: 4.222 | AF5: 2.58153 | AG5: 0.7 | AH5: 1680.381 | AI5: 298.119 | AJ5: -2614.512 | AK5: -1373.712 | AL5: -162.89667 | AM5: -65.09 | AN5: 1840.4441 | AO5: 169.65 | AP5: 0 | AQ5: 34.1285 | AR5: 0.08 | AS5: 29.581 | AT5: 118.68525 | AU5: 14.023156 | AV5: 12.61027 | AW5: 18.306452 | AX5: 0.5418 | AY5: 1487.7934 | AZ5: 249.34162
A6: 2024 Q2 | B6: historical | C6: -1 | D6: 0.0075830466 | E6: 0.0028193299 | F6: 0.0024774522 | G6: 0.0027475708 | H6: 0.0064180979 | I6: 0.0058015415 | J6: 29147 | K6: 19756.1 | L6: 0 | M6: 1867.5 | N6: 447.07611 | O6: 77.674143 | P6: 3127.6 | Q6: 4456.6 | R6: 2363.6 | S6: 495.3 | T6: 85.438722 | U6: 170.6 | V6: 2160.999 | W6: 199.2 | X6: 0 | Y6: 0 | Z6: 0 | AA6: 36.1 | AB6: 93 | AC6: 1.365 | AD6: 1.479 | AE6: 4.222 | AF6: 2.604045 | AG6: 0.7 | AH6: 1707.978 | AI6: 314.922 | AJ6: -2622.426 | AK6: -1378.08 | AL6: -168.09667 | AM6: -67.456667 | AN6: 1875.2229 | AO6: 173.115 | AP6: 0 | AQ6: 27.388 | AR6: 0.035 | AS6: 30.805 | AT6: 96.491025 | AU6: 13.047051 | AV6: 9.32794 | AW6: 11.957994 | AX6: 0.4005 | AY6: 1498.5893 | AZ6: 260.10068
A7: 2024 Q3 | B7: historical | C7: -1 | D7: 0.0059965041 | E7: 0.0039266712 | F7: 0.0065105722 | G7: 0.0044025399 | H7: 0.0042217342 | I7: 0.0057505722 | J7: 29511.7 | K7: 20032.8 | L7: 0 | M7: 1917.9 | N7: 468.80533 | O7: 77.674143 | P7: 3169.1 | Q7: 4526.7 | R7: 2400.1 | S7: 490.6 | T7: 79.629003 | U7: 170.1 | V7: 2181.299 | W7: 209 | X7: 0 | Y7: 0 | Z7: 0 | AA7: 37 | AB7: 92.1 | AC7: 1.365 | AD7: 1.479 | AE7: 4.222 | AF7: 2.626465 | AG7: 0.7 | AH7: 1744.359 | AI7: 315.441 | AJ7: -2629.842 | AK7: -1390.32 | AL7: -172.82667 | AM7: -69.003333 | AN7: 1912.3191 | AO7: 178.3125 | AP7: 0 | AQ7: 20.6475 | AR7: 0.012 | AS7: 31.843 | AT7: 75.838725 | AU7: 8.517842 | AV7: 6.35096 | AW7: 8.1834539 | AX7: 0.4014 | AY7: 1527.9988 | AZ7: 265.81365
A8: 2024 Q4 | B8: historical | C8: -1 | D8: 0.0059688045 | E8: 0.0032787138 | F8: 0.0035235298 | G8: 0.003325747 | H8: 0.0062373921 | I8: 0.0057438004 | J8: 29825.2 | K8: 20351.3 | L8: 0 | M8: 1950 | N8: 473.51933 | O8: 79.268143 | P8: 3200.8 | Q8: 4590.3 | R8: 2436.6 | S8: 508.6 | T8: 71.179167 | U8: 174.2 | V8: 2212.098 | W8: 204.3 | X8: 0 | Y8: 0 | Z8: 0 | AA8: 37.3 | AB8: 94 | AC8: -0.901 | AD8: 1.63 | AE8: 2.372 | AF8: 2.649835 | AG8: 0.7 | AH8: 1786.697 | AI8: 314.303 | AJ8: -2642.622 | AK8: -1404.93 | AL8: -177.31333 | AM8: -69.03 | AN8: 1954.4164 | AO8: 181.6425 | AP8: 0 | AQ8: 13.836 | AR8: 0 | AS8: 32.631 | AT8: 65.877975 | AU8: 6.576191 | AV8: 4.56094 | AW8: 6.1234738 | AX8: 0.4023 | AY8: 1556.8684 | AZ8: 279.62662
A9: 2025 Q1 | B9: historical | C9: -1 | D9: 0.014353684 | E9: 0.0099039593 | F9: 0.0066231529 | G9: 0.0092720593 | H9: 0.0084681203 | I9: 0.0056201408 | J9: 30042.1 | K9: 20555 | L9: 0 | M9: 1949.7 | N9: 435.153 | O9: 79.268143 | P9: 3245.8 | Q9: 4710.9 | R9: 2460.1 | S9: 469.2 | T9: 63.72026 | U9: 184.4 | V9: 2312.798 | W9: 203.3 | X9: 0 | Y9: 0 | Z9: 0 | AA9: 37.1 | AB9: 107 | AC9: -0.901 | AD9: 1.63 | AE9: 2.372 | AF9: 2.645442 | AG9: 0.7 | AH9: 1811.332 | AI9: 316.468 | AJ9: -2684.838 | AK9: -1421.406 | AL9: -180.12 | AM9: -69.02 | AN9: 1995.1186 | AO9: 183.555 | AP9: 0 | AQ9: 7.0245 | AR9: 0 | AS9: 33.123 | AT9: 61.47135 | AU9: 4.63454 | AV9: 3.85754 | AW9: 4.0318455 | AX9: 0.3861 | AY9: 1586.3323 | AZ9: 283.75515
A10: 2025 Q2 | B10: historical | C10: -1 | D10: 0.017075286 | E10: 0.0023603402 | F10: 0.0054340243 | G10: 0.0029513035 | H10: 0.0052878919 | I10: 0.0057178013 | J10: 30485.7 | K10: 20789.9 | L10: -0.2 | M10: 1956.4 | N10: 411.32562 | O10: 75.196143 | P10: 3280.6 | Q10: 4925.4 | R10: 2490.5 | S10: 469.7 | T10: 80.118616 | U10: 183 | V10: 2409.698 | W10: 203.5 | X10: 0 | Y10: 0 | Z10: 0 | AA10: 38 | AB10: 119.2 | AC10: -0.901 | AD10: 1.63 | AE10: 2.372 | AF10: 2.6696 | AG10: 0.7 | AH10: 1877.66 | AI10: 319.14 | AJ10: -2747.832 | AK10: -1439.904 | AL10: -181.59 | AM10: -69.64 | AN10: 2051.0759 | AO10: 184.5225 | AP10: 0 | AQ10: 0.213 | AR10: 0 | AS10: 33.62 | AT10: 55.2555 | AU10: 2.745007 | AV10: 3.17264 | AW10: 2.3533203 | AX10: 0.315 | AY10: 1624.5108 | AZ10: 284.7042
A11: 2025 Q3 | B11: historical | C11: -1 | D11: 0.009277919 | E11: 0.012563902 | F11: 0.0085086803 | G11: 0.011785566 | H11: 0.0068499652 | I11: 0.0057366284 | J11: 31095.1 | K11: 21114.9 | L11: 0 | M11: 1988.7 | N11: 437.30693 | O11: 75.196143 | P11: 3334.4 | Q11: 5048 | R11: 2523.6 | S11: 79 | T11: 97.957811 | U11: 166.7 | V11: 2372.398 | W11: 204 | X11: 0 | Y11: 0 | Z11: 0 | AA11: 38.5 | AB11: 123.4 | AC11: -0.901 | AD11: 1.63 | AE11: 2.372 | AF11: -8.306994 | AG11: 0.7 | AH11: 1936.933 | AI11: 345.467 | AJ11: -2815.464 | AK11: -1458.912 | AL11: -170.32667 | AM11: -69.543333 | AN11: 2094.0732 | AO11: 183.3975 | AP11: 0 | AQ11: 0.142 | AR11: 0 | AS11: 34.021 | AT11: 50.655375 | AU11: 0.855474 | AV11: 2.58402 | AW11: 0.19286449 | AX11: 0.315 | AY11: 1667.84 | AZ11: 291.46005
A12: 2025 Q4 | B12: projection | C12: 0 | D12: 0.024606677 | E12: 0.010918464 | F12: 0.010918464 | G12: 0.010918464 | H12: 0.0069304677 | I12: 0.0057166677 | J12: 31393.082 | K12: 21314.94 | L12: -0.9 | M12: 2015.8649 | N12: 436.28059 | O12: 75.196143 | P12: 3365.7243 | Q12: 5133.5913 | R12: 2538.4999 | S12: 333.3376 | T12: 109.65876 | U12: 160.93351 | V12: 2392.6594 | W12: 223.32468 | X12: 0 | Y12: 0 | Z12: 0 | AA12: 35.7 | AB12: 128.64 | AC12: -2.15 | AD12: 1.671 | AE12: 0.49 | AF12: -8.28246 | AG12: 0 | AH12: 1975.155 | AI12: 346.98429 | AJ12: -2877.839 | AK12: -1476.036 | AL12: -167.46125 | AM12: -68.947784 | AN12: 2134.6995 | AO12: 187.67805 | AP12: 0 | AQ12: 0.071 | AR12: 0 | AS12: 33.762 | AT12: 48.740355 | AU12: 0.573855 | AV12: 2.04112 | AW12: -1.6414568 | AX12: 0.28035 | AY12: 1710.243 | AZ12: 298.81334
A13: 2026 Q1 | B13: projection | C13: 0 | D13: -0.014430463 | E13: 0.0096505585 | F13: 0.0096505585 | G13: 0.0096505585 | H13: 0.0058163412 | I13: 0.0056799438 | J13: 31700.922 | K13: 21497.356 | L13: 1.66 | M13: 2060.5066 | N13: 439.29427 | O13: 75.196143 | P13: 3397.94 | Q13: 5077.3371 | R13: 2562.1947 | S13: 331.27795 | T13: 134.70904 | U13: 161.1282 | V13: 2464.9073 | W13: 226.55247 | X13: 0 | Y13: 0 | Z13: 0 | AA13: 35.7 | AB13: 126.49 | AC13: 0 | AD13: 0 | AE13: 0 | AF13: -8.28246 | AG13: 0 | AH13: 2010.9107 | AI13: 351.78373 | AJ13: -2920.7854 | AK13: -1492.5533 | AL13: -164.53052 | AM13: -68.522057 | AN13: 2168.9241 | AO13: 192.90986 | AP13: 0 | AQ13: 0 | AR13: 0 | AS13: 33.567 | AT13: 49.24449 | AU13: 0.378236 | AV13: 1.53068 | AW13: -3.3871227 | AX13: 0.250425 | AY13: 1755.1482 | AZ13: 306.75938
... A19: 2027 Q3 | B19: projection | C19: 0 | D19: 0.0056450949 | E19: 0.0074157411 | F19: 0.0074157411 | G19: 0.0074157411 | H19: 0.0049844807 | I19: 0.0054202205 | J19: 33525.4 | K19: 22640.572 | L19: 0 | M19: 2167.5325 | N19: 455.20727 | O19: 75.196143 | P19: 3577.9255 | Q19: 5421.8674 | R19: 2707.368 | S19: 329.06136 | T19: 83.749804 | U19: 159.87932 | V19: 2672.8931 | W19: 246.92288 | X19: 0 | Y19: 0 | Z19: 0 | AA19: 38.7 | AB19: 126.49 | AC19: 0 | AD19: 0 | AE19: 0 | AF19: 0 | AG19: 0 | AH19: 2200.6662 | AI19: 377.2842 | AJ19: -3160.2141 | AK19: -1582.3023 | AL19: -138.86843 | AM19: -66.540005 | AN19: 2355.8022 | AO19: 217.52621 | AP19: 0 | AQ19: 0 | AR19: 0 | AS19: 33.587 | AT19: 54.158603 | AU19: -0.097818 | AV19: 0.0196 | AW19: -7.4295444 | AX19: 0.1008 | AY19: 1936.9389 | AZ19: 331.93008

Sheet 12-05
A1: date | B1: id | C1: recession | D1: federal_purchases_deflator_growth | E1: consumption_grants_deflator_growth | F1: investment_grants_deflator_growth | G1: state_purchases_deflator_growth | H1: consumption_deflator_growth | I1: real_potential_gdp_growth | J1: gdp | K1: consumption | L1: uncertainty | M1: federal_purchases | N1: consumption_grants | O1: investment_grants | P1: state_purchases | Q1: federal_non_corporate_taxes | R1: state_non_corporate_taxes | S1: federal_corporate_taxes | T1: supply_side_ira | U1: state_corporate_taxes | V1: federal_social_benefits | W1: state_social_benefits | X1: rebate_checks | Y1: rebate_checks_arp | Z1: federal_ui | AA1: state_ui | AB1: federal_subsidies | AC1: federal_aid_to_small_businesses_arp | AD1: federal_other_direct_aid_arp | AE1: federal_other_vulnerable_arp | AF1: federal_student_loans | AG1: state_subsidies | AH1: federal_health_outlays | AI1: state_health_outlays | AJ1: post_mpc_federal_non_corporate_taxes | AK1: post_mpc_state_non_corporate_taxes | AL1: post_mpc_federal_corporate_taxes | AM1: post_mpc_state_corporate_taxes | AN1: post_mpc_federal_social_benefits | AO1: post_mpc_state_social_benefits | AP1: post_mpc_rebate_checks | AQ1: post_mpc_rebate_checks_arp | AR1: post_mpc_federal_ui | AS1: post_mpc_state_ui | AT1: post_mpc_federal_subsidies | AU1: post_mpc_federal_aid_to_small_businesses_arp | AV1: post_mpc_federal_other_vulnerable_arp | AW1: post_mpc_federal_student_loans | AX1: post_mpc_state_subsidies | AY1: post_mpc_federal_health_outlays | AZ1: post_mpc_state_health_outlays
A2: 2023 Q2 | B2: historical | C2: -1 | D2: 0.006582718 | E2: -0.0073827309 | F2: 0.0021322445 | G2: -0.0056211973 | H2: 0.0073926308 | I2: 0.0056240488 | J2: 27530.1 | K2: 18693.1 | L2: 0 | M2: 1738.8 | N2: 436.07272 | O2: 76.015143 | P2: 2934.6 | Q2: 4210.6 | R2: 2236.1 | S2: 415.5 | T2: 46.245323 | U2: 170.2 | V2: 2006.4269 | W2: 183.8 | X2: 0 | Y2: 0 | Z2: 0 | AA2: 32.8 | AB2: 101.3 | AC2: 12.726 | AD2: 1.416 | AE2: 12 | AF2: 45 | AG2: 0.7 | AH2: 1659.996 | AI2: 267.104 | AJ2: -2564.838 | AK2: -1347.348 | AL2: -144.40667 | AM2: -55.99 | AN2: 1790.1942 | AO2: 188.1225 | AP2: 2.1784 | AQ2: 41.153 | AR2: 9.157 | AS2: 22.948 | AT2: 159.5619 | AU2: 14.28301 | AV2: 28.976026 | AW2: 40.95 | AX2: 0.5679 | AY2: 1444.3544 | AZ2: 210.74558
A3: 2023 Q3 | B3: historical | C3: -1 | D3: 0.0094033912 | E3: 0.016732699 | F3: 0.00035461796 | G3: 0.013706093 | H3: 0.0067310092 | I3: 0.0056687159 | J3: 28074.8 | K3: 18961.8 | L3: 0 | M3: 1784.4 | N3: 417.91594 | O3: 76.015143 | P3: 3005.4 | Q3: 4257.9 | R3: 2270.3 | S3: 428.4 | T3: 62.071265 | U3: 168.5 | V3: 2016.4269 | W3: 185.9 | X3: 0 | Y3: 0 | Z3: 0 | AA3: 34.9 | AB3: 103.5 | AC3: 12.726 | AD3: 1.416 | AE3: 12 | AF3: 2.081508 | AG3: 0.7 | AH3: 1613.65 | AI3: 290.05 | AJ3: -2589.162 | AK3: -1357.608 | AL3: -150.09667 | AM3: -58.886667 | AN3: 1810.0624 | AO3: 184.0275 | AP3: 0 | AQ3: 41.153 | AR3: 0.67 | AS3: 26.182 | AT3: 136.66702 | AU3: 14.499352 | AV3: 22.99411 | AW3: 32.366302 | AX3: 0.5706 | AY3: 1456.9297 | AZ3: 229.62533
A4: 2023 Q4 | B4: historical | C4: -1 | D4: 0.0070345423 | E4: 0.00071349046 | F4: 0.0032733965 | G4: 0.0011916352 | H4: 0.0045206985 | I4: 0.0057213587 | J4: 28424.7 | K4: 19190.6 | L4: 0 | M4: 1812 | N4: 434.04594 | O4: 77.674143 | P4: 3049 | Q4: 4302.2 | R4: 2301.1 | S4: 442.7 | T4: 68.31219 | U4: 172.7 | V4: 2024.999 | W4: 189.5 | X4: 0 | Y4: 0 | Z4: 0 | AA4: 35.5 | AB4: 98 | AC4: 1.365 | AD4: 1.479 | AE4: 4.222 | AF4: 2.100618 | AG4: 0.7 | AH4: 1658.388 | AI4: 252.912 | AJ4: -2609.964 | AK4: -1367.988 | AL4: -156.48667 | AM4: -62.036667 | AN4: 1814.9933 | AO4: 168.84 | AP4: 0 | AQ4: 41.153 | AR4: 0.174 | AS4: 28.155 | AT4: 126.927 | AU4: 14.261254 | AV4: 16.69038 | AW4: 25.07398 | AX4: 0.5733 | AY4: 1475.7446 | AZ4: 236.95538
A5: 2024 Q1 | B5: historical | C5: -1 | D5: 0.01026393 | E5: 0.008782995 | F5: 0.0044129366 | G5: 0.0079425584 | H5: 0.0088526155 | I5: 0.0057507902 | J5: 28708.2 | K5: 19443.8 | L5: 0 | M5: 1834.3 | N5: 437.85294 | O5: 77.674143 | P5: 3097.5 | Q5: 4390.9 | R5: 2325.5 | S5: 472.3 | T5: 78.014538 | U5: 173.2 | V5: 2131.899 | W5: 194.8 | X5: 0 | Y5: 0 | Z5: 0 | AA5: 35.5 | AB5: 95 | AC5: 1.365 | AD5: 1.479 | AE5: 4.222 | AF5: 2.58153 | AG5: 0.7 | AH5: 1680.381 | AI5: 298.119 | AJ5: -2614.512 | AK5: -1373.712 | AL5: -162.89667 | AM5: -65.09 | AN5: 1840.4441 | AO5: 169.65 | AP5: 0 | AQ5: 34.1285 | AR5: 0.08 | AS5: 29.581 | AT5: 118.68525 | AU5: 14.023156 | AV5: 12.61027 | AW5: 18.306452 | AX5: 0.5418 | AY5: 1487.7934 | AZ5: 249.34162
A6: 2024 Q2 | B6: historical | C6: -1 | D6: 0.0075830466 | E6: 0.0028193299 | F6: 0.0024774522 | G6: 0.0027475708 | H6: 0.0064180979 | I6: 0.0058015415 | J6: 29147 | K6: 19756.1 | L6: 0 | M6: 1867.5 | N6: 447.07611 | O6: 77.674143 | P6: 3127.6 | Q6: 4456.6 | R6: 2363.6 | S6: 495.3 | T6: 85.438722 | U6: 170.6 | V6: 2160.999 | W6: 199.2 | X6: 0 | Y6: 0 | Z6: 0 | AA6: 36.1 | AB6: 93 | AC6: 1.365 | AD6: 1.479 | AE6: 4.222 | AF6: 2.604045 | AG6: 0.7 | AH6: 1707.978 | AI6: 314.922 | AJ6: -2622.426 | AK6: -1378.08 | AL6: -168.09667 | AM6: -67.456667 | AN6: 1875.2229 | AO6: 173.115 | AP6: 0 | AQ6: 27.388 | AR6: 0.035 | AS6: 30.805 | AT6: 96.491025 | AU6: 13.047051 | AV6: 9.32794 | AW6: 11.957994 | AX6: 0.4005 | AY6: 1498.5893 | AZ6: 260.10068
A7: 2024 Q3 | B7: historical | C7: -1 | D7: 0.0059965041 | E7: 0.0039266712 | F7: 0.0065105722 | G7: 0.0044025399 | H7: 0.0042217342 | I7: 0.0057505722 | J7: 29511.7 | K7: 20032.8 | L7: 0 | M7: 1917.9 | N7: 468.80533 | O7: 77.674143 | P7: 3169.1 | Q7: 4526.7 | R7: 2400.1 | S7: 490.6 | T7: 79.629003 | U7: 170.1 | V7: 2181.299 | W7: 209 | X7: 0 | Y7: 0 | Z7: 0 | AA7: 37 | AB7: 92.1 | AC7: 1.365 | AD7: 1.479 | AE7: 4.222 | AF7: 2.626465 | AG7: 0.7 | AH7: 1744.359 | AI7: 315.441 | AJ7: -2629.842 | AK7: -1390.32 | AL7: -172.82667 | AM7: -69.003333 | AN7: 1912.3191 | AO7: 178.3125 | AP7: 0 | AQ7: 20.6475 | AR7: 0.012 | AS7: 31.843 | AT7: 75.838725 | AU7: 8.517842 | AV7: 6.35096 | AW7: 8.1834539 | AX7: 0.4014 | AY7: 1527.9988 | AZ7: 265.81365
A8: 2024 Q4 | B8: historical | C8: -1 | D8: 0.0059688045 | E8: 0.0032787138 | F8: 0.0035235298 | G8: 0.003325747 | H8: 0.0062373921 | I8: 0.0057438004 | J8: 29825.2 | K8: 20351.3 | L8: 0 | M8: 1950 | N8: 473.51933 | O8: 79.268143 | P8: 3200.8 | Q8: 4590.3 | R8: 2436.6 | S8: 508.6 | T8: 71.179167 | U8: 174.2 | V8: 2212.098 | W8: 204.3 | X8: 0 | Y8: 0 | Z8: 0 | AA8: 37.3 | AB8: 94 | AC8: -0.901 | AD8: 1.63 | AE8: 2.372 | AF8: 2.649835 | AG8: 0.7 | AH8: 1786.697 | AI8: 314.303 | AJ8: -2642.622 | AK8: -1404.93 | AL8: -177.31333 | AM8: -69.03 | AN8: 1954.4164 | AO8: 181.6425 | AP8: 0 | AQ8: 13.836 | AR8: 0 | AS8: 32.631 | AT8: 65.877975 | AU8: 6.576191 | AV8: 4.56094 | AW8: 6.1234738 | AX8: 0.4023 | AY8: 1556.8684 | AZ8: 279.62662
A9: 2025 Q1 | B9: historical | C9: -1 | D9: 0.014353684 | E9: 0.0099039593 | F9: 0.0066231529 | G9: 0.0092720593 | H9: 0.0084681203 | I9: 0.0056201408 | J9: 30042.1 | K9: 20555 | L9: 0 | M9: 1949.7 | N9: 435.153 | O9: 79.268143 | P9: 3245.8 | Q9: 4710.9 | R9: 2460.1 | S9: 469.2 | T9: 73.980636 | U9: 184.4 | V9: 2312.798 | W9: 203.3 | X9: 0 | Y9: 0 | Z9: 0 | AA9: 37.1 | AB9: 107 | AC9: -0.901 | AD9: 1.63 | AE9: 2.372 | AF9: 2.645442 | AG9: 0.7 | AH9: 1811.332 | AI9: 316.468 | AJ9: -2684.838 | AK9: -1421.406 | AL9: -180.12 | AM9: -69.02 | AN9: 1995.1186 | AO9: 183.555 | AP9: 0 | AQ9: 7.0245 | AR9: 0 | AS9: 33.123 | AT9: 61.47135 | AU9: 4.63454 | AV9: 3.85754 | AW9: 4.0318455 | AX9: 0.3861 | AY9: 1586.3323 | AZ9: 283.75515
A10: 2025 Q2 | B10: historical | C10: -1 | D10: 0.017075286 | E10: 0.0023603402 | F10: 0.0054340243 | G10: 0.0029513035 | H10: 0.0052878919 | I10: 0.0057178013 | J10: 30485.7 | K10: 20789.9 | L10: -0.3 | M10: 1956.4 | N10: 411.32562 | O10: 75.196143 | P10: 3280.6 | Q10: 4944.5 | R10: 2490.5 | S10: 469.7 | T10: 88.394443 | U10: 183 | V10: 2409.698 | W10: 203.5 | X10: 0 | Y10: 0 | Z10: 0 | AA10: 38 | AB10: 119.2 | AC10: -0.901 | AD10: 1.63 | AE10: 2.372 | AF10: 2.6696 | AG10: 0.7 | AH10: 1877.66 | AI10: 319.14 | AJ10: -2750.124 | AK10: -1439.904 | AL10: -181.59 | AM10: -69.64 | AN10: 2051.0759 | AO10: 184.5225 | AP10: 0 | AQ10: 0.213 | AR10: 0 | AS10: 33.62 | AT10: 55.2555 | AU10: 2.745007 | AV10: 3.17264 | AW10: 2.3533203 | AX10: 0.315 | AY10: 1624.5108 | AZ10: 284.7042
A11: 2025 Q3 | B11: projection | C11: 0 | D11: 0.006125897 | E11: 0.0077455121 | F11: 0.0077455121 | G11: 0.0077455121 | H11: 0.006823573 | I11: 0.0057366284 | J11: 30789.813 | K11: 20995.964 | L11: -0.3 | M11: 1979.7453 | N11: 413.92898 | O11: 75.196143 | P11: 3310.5813 | Q11: 5095.9814 | R11: 2509.6975 | S11: 78.824649 | T11: 97.957811 | U11: 182.67714 | V11: 2394.8924 | W11: 220.14287 | X11: 0 | Y11: 0 | Z11: 0 | AA11: 35.7 | AB11: 120.101 | AC11: -0.901 | AD11: 1.63 | AE11: 2.372 | AF11: -8.306994 | AG11: 0 | AH11: 1930.5161 | AI11: 339.9592 | AJ11: -2823.5138 | AK11: -1457.2437 | AL11: -170.32082 | AM11: -70.075905 | AN11: 2099.1344 | AO11: 187.02965 | AP11: 0 | AQ11: 0.142 | AR11: 0 | AS11: 33.461 | AT11: 50.492075 | AU11: 0.855474 | AV11: 2.58402 | AW11: 0.19286449 | AX11: 0.28035 | AY11: 1666.3962 | AZ11: 290.2208
A12: 2025 Q4 | B12: projection | C12: 0 | D12: 0.023908713 | E12: 0.0080020266 | F12: 0.0080020266 | G12: 0.0080020266 | H12: 0.0064403633 | I12: 0.0057166677 | J12: 31084.87 | K12: 21194.877 | L12: -1.2 | M12: 2006.7629 | N12: 412.67229 | O12: 75.196143 | P12: 3341.6818 | Q12: 5181.7389 | R12: 2535.4148 | S12: 333.3376 | T12: 109.65876 | U12: 182.58555 | V12: 2398.1707 | W12: 223.32468 | X12: 0 | Y12: 0 | Z12: 0 | AA12: 35.7 | AB12: 124.44 | AC12: -2.15 | AD12: 1.671 | AE12: 0.49 | AF12: -8.28246 | AG12: 0 | AH12: 1966.5821 | AI12: 343.22147 | AJ12: -2890.5204 | AK12: -1473.9975 | AL12: -167.45541 | AM12: -70.20209 | AN12: 2141.0008 | AO12: 191.3102 | AP12: 0 | AQ12: 0.071 | AR12: 0 | AS12: 33.286 | AT12: 48.391423 | AU12: 0.573855 | AV12: 2.04112 | AW12: -1.6414568 | AX12: 0.250425 | AY12: 1706.8703 | AZ12: 296.72745
A13: 2026 Q1 | B13: projection | C13: 0 | D13: -0.01600107 | E13: 0.0081899949 | F13: 0.0081899949 | G13: 0.0081899949 | H13: 0.0055705631 | I13: 0.0056799438 | J13: 31389.687 | K13: 21376.266 | L13: 1.36 | M13: 2051.1056 | N13: 415.45334 | O13: 75.196143 | P13: 3373.6674 | Q13: 5110.0121 | R13: 2559.0591 | S13: 331.27795 | T13: 134.70904 | U13: 182.80643 | V13: 2470.5012 | W13: 226.55247 | X13: 0 | Y13: 0 | Z13: 0 | AA13: 35.7 | AB13: 122.29 | AC13: 0 | AD13: 0 | AE13: 0 | AF13: -8.28246 | AG13: 0 | AH13: 2002.2038 | AI13: 347.73485 | AJ13: -2934.509 | AK13: -1490.9727 | AL13: -164.52467 | AM13: -70.498971 | AN13: 2176.484 | AO13: 196.542 | AP13: 0 | AQ13: 0 | AR13: 0 | AS13: 33.119 | AT13: 48.72343 | AU13: 0.378236 | AV13: 1.53068 | AW13: -3.3871227 | AX13: 0.222075 | AY13: 1749.8164 | AZ13: 303.76249
... A18: 2027 Q2 | B18: projection | C18: 0 | D18: 0.0054914305 | E18: 0.0074988973 | F18: 0.0074988973 | G18: 0.0074988973 | H18: 0.0050077163 | I18: 0.0054538948 | J18: 32894.354 | K18: 22328.33 | L18: -0.04 | M18: 2142.6243 | N18: 426.9721 | O18: 75.196143 | P18: 3522.338 | Q18: 5423.1065 | R18: 2679.991 | S18: 331.10723 | T18: 113.58754 | U18: 182.18149 | V18: 2647.8338 | W18: 243.40486 | X18: 0 | Y18: 0 | Z18: 0 | AA18: 37.7 | AB18: 122.29 | AC18: 0 | AD18: 0 | AE18: 0 | AF18: -11 | AG18: 0 | AH18: 2158.5668 | AI18: 366.69953 | AJ18: -3155.7411 | AK18: -1565.8192 | AL18: -144.2472 | AM18: -72.472075 | AN18: 2326.7883 | AO18: 214.42702 | AP18: 0 | AQ18: 0 | AR18: 0 | AS18: 33.057 | AT18: 52.057024 | AU18: -0.074613 | AV18: 0.11938 | AW18: -9.3859472 | AX18: 0.1008 | AY18: 1902.3898 | AZ18: 324.22895

Sheet diff
A1: date | B1: id | C1: recession | D1: federal_purchases_deflator_growth | E1: consumption_grants_deflator_growth | F1: investment_grants_deflator_growth | G1: state_purchases_deflator_growth | H1: consumption_deflator_growth | I1: real_potential_gdp_growth | J1: gdp | K1: consumption | L1: uncertainty | M1: federal_purchases | N1: consumption_grants | O1: investment_grants | P1: state_purchases | Q1: federal_non_corporate_taxes | R1: state_non_corporate_taxes | S1: federal_corporate_taxes | T1: supply_side_ira | U1: state_corporate_taxes | V1: federal_social_benefits | W1: state_social_benefits | X1: rebate_checks | Y1: rebate_checks_arp | Z1: federal_ui | AA1: state_ui | AB1: federal_subsidies | AC1: federal_aid_to_small_businesses_arp | AD1: federal_other_direct_aid_arp | AE1: federal_other_vulnerable_arp | AF1: federal_student_loans | AG1: state_subsidies | AH1: federal_health_outlays | AI1: state_health_outlays | AJ1: post_mpc_federal_non_corporate_taxes | AK1: post_mpc_state_non_corporate_taxes | AL1: post_mpc_federal_corporate_taxes | AM1: post_mpc_state_corporate_taxes | AN1: post_mpc_federal_social_benefits | AO1: post_mpc_state_social_benefits | AP1: post_mpc_rebate_checks | AQ1: post_mpc_rebate_checks_arp | AR1: post_mpc_federal_ui | AS1: post_mpc_state_ui | AT1: post_mpc_federal_subsidies | AU1: post_mpc_federal_aid_to_small_businesses_arp | AV1: post_mpc_federal_other_vulnerable_arp | AW1: post_mpc_federal_student_loans | AX1: post_mpc_state_subsidies | AY1: post_mpc_federal_health_outlays | AZ1: post_mpc_state_health_outlays
A2: 2023 Q2 | B2: historical | C2: -1 | D2: ='01-13'!D2-'12-05'!D2 -> 0 | E2: ='01-13'!E2-'12-05'!E2 -> 0 | F2: ='01-13'!F2-'12-05'!F2 -> 0 | G2: ='01-13'!G2-'12-05'!G2 -> 0 | H2: ='01-13'!H2-'12-05'!H2 -> 0 | I2: ='01-13'!I2-'12-05'!I2 -> 0 | J2: ='01-13'!J2-'12-05'!J2 -> 0 | K2: ='01-13'!K2-'12-05'!K2 -> 0 | ... AZ2: ='01-13'!AZ2-'12-05'!AZ2 -> 0
A3: 2023 Q3 | B3: historical | C3: -1 | D3: ='01-13'!D3-'12-05'!D3 -> 0 | E3: ='01-13'!E3-'12-05'!E3 -> 0 | F3: ='01-13'!F3-'12-05'!F3 -> 0 | G3: ='01-13'!G3-'12-05'!G3 -> 0 | H3: ='01-13'!H3-'12-05'!H3 -> 0 | I3: ='01-13'!I3-'12-05'!I3 -> 0 | J3: ='01-13'!J3-'12-05'!J3 -> 0 | K3: ='01-13'!K3-'12-05'!K3 -> 0 | ... AZ3: ='01-13'!AZ3-'12-05'!AZ3 -> 0
A4: 2023 Q4 | B4: historical | C4: -1 | D4: ='01-13'!D4-'12-05'!D4 -> 0 | E4: ='01-13'!E4-'12-05'!E4 -> 0 | F4: ='01-13'!F4-'12-05'!F4 -> 0 | G4: ='01-13'!G4-'12-05'!G4 -> 0 | H4: ='01-13'!H4-'12-05'!H4 -> 0 | I4: ='01-13'!I4-'12-05'!I4 -> 0 | J4: ='01-13'!J4-'12-05'!J4 -> 0 | K4: ='01-13'!K4-'12-05'!K4 -> 0 | ... AZ4: ='01-13'!AZ4-'12-05'!AZ4 -> 0
A5: 2024 Q1 | B5: historical | C5: -1 | D5: ='01-13'!D5-'12-05'!D5 -> 0 | E5: ='01-13'!E5-'12-05'!E5 -> 0 | F5: ='01-13'!F5-'12-05'!F5 -> 0 | G5: ='01-13'!G5-'12-05'!G5 -> 0 | H5: ='01-13'!H5-'12-05'!H5 -> 0 | I5: ='01-13'!I5-'12-05'!I5 -> 0 | J5: ='01-13'!J5-'12-05'!J5 -> 0 | K5: ='01-13'!K5-'12-05'!K5 -> 0 | ... AZ5: ='01-13'!AZ5-'12-05'!AZ5 -> 0
A6: 2024 Q2 | B6: historical | C6: -1 | D6: ='01-13'!D6-'12-05'!D6 -> 0 | E6: ='01-13'!E6-'12-05'!E6 -> 0 | F6: ='01-13'!F6-'12-05'!F6 -> 0 | G6: ='01-13'!G6-'12-05'!G6 -> 0 | H6: ='01-13'!H6-'12-05'!H6 -> 0 | I6: ='01-13'!I6-'12-05'!I6 -> 0 | J6: ='01-13'!J6-'12-05'!J6 -> 0 | K6: ='01-13'!K6-'12-05'!K6 -> 0 | ... AZ6: ='01-13'!AZ6-'12-05'!AZ6 -> 0
A7: 2024 Q3 | B7: historical | C7: -1 | D7: ='01-13'!D7-'12-05'!D7 -> 0 | E7: ='01-13'!E7-'12-05'!E7 -> 0 | F7: ='01-13'!F7-'12-05'!F7 -> 0 | G7: ='01-13'!G7-'12-05'!G7 -> 0 | H7: ='01-13'!H7-'12-05'!H7 -> 0 | I7: ='01-13'!I7-'12-05'!I7 -> 0 | J7: ='01-13'!J7-'12-05'!J7 -> 0 | K7: ='01-13'!K7-'12-05'!K7 -> 0 | ... AZ7: ='01-13'!AZ7-'12-05'!AZ7 -> 0
A8: 2024 Q4 | B8: historical | C8: -1 | D8: ='01-13'!D8-'12-05'!D8 -> 0 | E8: ='01-13'!E8-'12-05'!E8 -> 0 | F8: ='01-13'!F8-'12-05'!F8 -> 0 | G8: ='01-13'!G8-'12-05'!G8 -> 0 | H8: ='01-13'!H8-'12-05'!H8 -> 0 | I8: ='01-13'!I8-'12-05'!I8 -> 0 | J8: ='01-13'!J8-'12-05'!J8 -> 0 | K8: ='01-13'!K8-'12-05'!K8 -> 0 | ... AZ8: ='01-13'!AZ8-'12-05'!AZ8 -> 0
A9: 2025 Q1 | B9: historical | C9: -1 | D9: ='01-13'!D9-'12-05'!D9 -> 0 | E9: ='01-13'!E9-'12-05'!E9 -> 0 | F9: ='01-13'!F9-'12-05'!F9 -> 0 | G9: ='01-13'!G9-'12-05'!G9 -> 0 | H9: ='01-13'!H9-'12-05'!H9 -> 0 | I9: ='01-13'!I9-'12-05'!I9 -> 0 | J9: ='01-13'!J9-'12-05'!J9 -> 0 | K9: ='01-13'!K9-'12-05'!K9 -> 0 | ... AZ9: ='01-13'!AZ9-'12-05'!AZ9 -> 0
A10: 2025 Q2 | B10: historical | C10: -1 | D10: ='01-13'!D10-'12-05'!D10 -> 0 | E10: ='01-13'!E10-'12-05'!E10 -> 0 | F10: ='01-13'!F10-'12-05'!F10 -> 0 | G10: ='01-13'!G10-'12-05'!G10 -> 0 | H10: ='01-13'!H10-'12-05'!H10 -> 0 | I10: ='01-13'!I10-'12-05'!I10 -> 0 | J10: ='01-13'!J10-'12-05'!J10 -> 0 | K10: ='01-13'!K10-'12-05'!K10 -> 0 | ... AZ10: ='01-13'!AZ10-'12-05'!AZ10 -> 0
A11: 2025 Q3 | B11: projection | C11: 0 | D11: ='01-13'!D11-'12-05'!D11 -> 0.003152022 | E11: ='01-13'!E11-'12-05'!E11 -> 0.0048183899 | F11: ='01-13'!F11-'12-05'!F11 -> 0.00076316824 | G11: ='01-13'!G11-'12-05'!G11 -> 0.004040054 | H11: ='01-13'!H11-'12-05'!H11 -> 2.6392171e-05 | I11: ='01-13'!I11-'12-05'!I11 -> 0 | J11: ='01-13'!J11-'12-05'!J11 -> 305.28668 | K11: ='01-13'!K11-'12-05'!K11 -> 118.93604 | ... AZ11: ='01-13'!AZ11-'12-05'!AZ11 -> 1.2392542
A12: 2025 Q4 | B12: projection | C12: 0 | D12: ='01-13'!D12-'12-05'!D12 -> 0.00069796478 | E12: ='01-13'!E12-'12-05'!E12 -> 0.0029164376 | F12: ='01-13'!F12-'12-05'!F12 -> 0.0029164376 | G12: ='01-13'!G12-'12-05'!G12 -> 0.0029164376 | H12: ='01-13'!H12-'12-05'!H12 -> 0.00049010445 | I12: ='01-13'!I12-'12-05'!I12 -> 0 | J12: ='01-13'!J12-'12-05'!J12 -> 308.21222 | K12: ='01-13'!K12-'12-05'!K12 -> 120.06282 | ... AZ12: ='01-13'!AZ12-'12-05'!AZ12 -> 2.0858884
A13: 2026 Q1 | B13: projection | C13: 0 | D13: ='01-13'!D13-'12-05'!D13 -> 0.0015706077 | E13: ='01-13'!E13-'12-05'!E13 -> 0.0014605636 | F13: ='01-13'!F13-'12-05'!F13 -> 0.0014605636 | G13: ='01-13'!G13-'12-05'!G13 -> 0.0014605636 | H13: ='01-13'!H13-'12-05'!H13 -> 0.00024577807 | I13: ='01-13'!I13-'12-05'!I13 -> 0 | J13: ='01-13'!J13-'12-05'!J13 -> 311.23454 | K13: ='01-13'!K13-'12-05'!K13 -> 121.09034 | ... AZ13: ='01-13'!AZ13-'12-05'!AZ13 -> 2.9968858
... A18: 2027 Q2 | B18: projection | C18: 0 | D18: ='01-13'!D18-'12-05'!D18 -> 0 | E18: ='01-13'!E18-'12-05'!E18 -> 0 | F18: ='01-13'!F18-'12-05'!F18 -> 0 | G18: ='01-13'!G18-'12-05'!G18 -> 0 | H18: ='01-13'!H18-'12-05'!H18 -> 0 | I18: ='01-13'!I18-'12-05'!I18 -> 0 | J18: ='01-13'!J18-'12-05'!J18 -> 326.15359 | K18: ='01-13'!K18-'12-05'!K18 -> 126.4835 | ... AZ18: ='01-13'!AZ18-'12-05'!AZ18 -> 4.2039256
